Workbook

Sheet Dashboard_Home
A5: BEST TEAM | D5: BEST BATSMAN | G5: BEST BOWLER | J5: BEST CAPTAIN | M5: BEST COACH
A7: =INDEX(Team_Analytics!A:A,MATCH(MAX(Team_Analytics!G:G),Team_Analytics!G:G,0)) -> GT | D7: {=INDEX(Master_Batsman_Analysis!A:A,MATCH(MAX(IF(ISNUMBER(Master_Batsman_Analysis!Q:Q),Master_Batsman_Analysis!Q:Q)),Master_Batsman_Analysis!Q:Q,0))} -> Vaibhav Suryavanshi | G7: =INDEX(Master_Bowler_Analysis!A:A,MATCH(MAX(Master_Bowler_Analysis!Q:Q),Master_Bowler_Analysis!Q:Q,0)) -> Kagiso Rabada | J7: =INDEX(Captain_Clean!A:A,MATCH(MAX(Captain_Clean!G:G),Captain_Clean!G:G,0)) -> Rajat Patidar | M7: =INDEX(Coach_Clean!A:A,MATCH(MAX(Coach_Clean!H:H),Coach_Clean!H:H,0)) -> Mahela Jayawardene
A11: Which teams spent the most? | I11: Which team is strongest overall?
A31: Which team got best output per crore?

Sheet Auction_Intelligence
A6: Which players gave highest performance for lowest price? | J6: Who cost a lot but underperformed?
J8: TOP 5 OVERPRICED PLAYERS
A10: Players | C10: Teams | E10: Price | G10: Value Score | J10: Player | L10: Teams | N10: Price | P10: Overprice Score
A11: 1.Finn Allen | C11: KKR | E11: 2 | G11: 1303.9406 | J11: 1.Akshat Raghuwanshi | L11: LSG | N11: 2.2 | P11: 0.0451023
A12: 2.Pathum Nissanka | C12: DC | E12: 4 | G12: 306.91409 | J12: 2.Kartik Sharma | L12: CSK | N12: 14.2 | P12: 0.010755598
A13: 3.Mukul Choudhary | C13: LSG | E13: 2.6 | G13: 262.40336 | J13: 3.Mukul Choudhary | L13: LSG | N13: 2.6 | P13: 0.0038109269
A14: 4.Kartik Sharma | C14: CSK | E14: 14.2 | G14: 92.974836 | J14: 4.Pathum Nissanka | L14: DC | N14: 4 | P14: 0.0032582408
A15: 5.Akshat Raghuwanshi | C15: LSG | E15: 2.2 | G15: 22.171818 | J15: 5.Finn Allen | L15: KKR | N15: 2 | P15: 0.0007669061
A18: Which role consumed the highest auction budget? | J18: Which low-cost uncapped players can become future stars?
A20: ROLE BUDGET DISTRIBUTION | J20: BEST VALUE UNCAPPPED PLAYERS
J22: Player | L22: Team | M22: Role | O22: Price | Q22: Final Uncapped Score
J23: Emanjot Chahal | L23: RR | M23: All-Rounder | O23: 3 | Q23: 309.61
J26: Prithvi Shaw | L26: DC | M26: Anchor | O26: 0.75 | Q26: 100.02
J29: Brijesh Sharma | L29: RR | M29: Spinner | O29: 0.3 | Q29: 92.97
J32: Gerald Coetzee | L32: SRH | M32: Pacer | O32: 2 | Q32: 72.29
J35: Ruchit Ahir | L35: MI | M35: Anchor | O35: 0.3 | Q35: 66.79
A41: Which teams spent wisely?
A43: TEAM SPENDING EFFICIENCY

Sheet Role_Analytics
A6: BEST ANCHOR | N6: BEST WICKETKEEPER
A9: BASED ON BATTING IMPACT | N9: BASED ON STRIKE RATE
A37: BEST FINISHER | N37: BEST BOWLER
A40: SR v/s B% | N40: BASED ON FINAL BOWLING SCORE

Sheet Leadership_Analytics
A6: COACH ROI | O6: WIN %
A40: Coach Efficiency vs Budget

Sheet Best_XI_2026
I18: VAIBHAV SURYAVANSHI | M18: VIRAT KOHLI
C35: SHUBMAN GILL | K35: HEINRICH KLAASEN | S35: KL RAHUL
K51: HARDIK PANDYA
K68: NITISH KUMAR REDDY
C84: KUNAL PANDYA | K84: HAZELWOOD | T84: RASHID KHAN
K100: KAGISO RABADA

Sheet Master_Player_Analytics
A1: Player | B1: Team | C1: Acquisition | D1: Role | E1: Price | F1: key | G1: Matches | H1: Runs | I1: Balls | J1: Average | K1: Strike Rate | L1: 100s | M1: 50s | N1: 4s | O1: 6s | P1: Not Outs | Q1: Bowling Matches | R1: Overs | S1: Runs Conceded | T1: Wickets | U1: Economy | V1: Maidens | W1: Bowling Average | X1: Cost Per Run | Y1: Cost Per Wicket | Z1: Boundary Percentage | AA1: Opener_Score | AB1: Middle_Order_Score | AC1: Finisher_Score | AD1: AR_Score | AE1: Bowler_Score | AF1: Eligible_Finisher
A2: Ruturaj Gaikwad | B2: CSK | C2: Retained | D2: Anchor | E2: 0 | F2: Ruturaj_Gaikwad_CSK | G2: 14 | H2: 337 | I2: 273 | J2: 28.08 | K2: 123.44 | L2: 0 | M2: 2 | N2: 29 | O2: 12 | P2: 2 | Q2: 0 | R2: 0 | S2: 0 | T2: 0 | U2: 0 | V2: 0 | W2: 0 | X2: 0 | Y2: 0 | Z2: 0.12166172 | AA2: 415.9928 | AB2: 79.62 | AC2: 65.726 | AD2: 129.788 | AE2: 0 | AF2: NO | AI2: Role | AJ2: Anchor
A3: MS Dhoni | B3: CSK | C3: Retained | D3: Wicketkeeper | E3: 0 | F3: MS_Dhoni_CSK | G3: 0 | H3: 0 | I3: 0 | J3: 0 | K3: 0 | L3: 0 | M3: 0 | N3: 0 | O3: 0 | P3: 0 | Q3: 0 | R3: 0 | S3: 0 | T3: 0 | U3: 0 | V3: 0 | W3: 0 | X3: 0 | Y3: 0 | Z3: 0 | AA3: 0 | AB3: 0 | AC3: 0 | AD3: 0 | AE3: 0 | AF3: NO | AN3: Role | AO3: All-Rounder
A4: Dewald Brevis | B4: CSK | C4: Retained | D4: Anchor | E4: 0 | F4: Dewald_Brevis_CSK | G4: 11 | H4: 151 | I4: 118 | J4: 18.87 | K4: 127.96 | L4: 0 | M4: 0 | N4: 8 | O4: 10 | P4: 0 | Q4: 0 | R4: 0 | S4: 0 | T4: 0 | U4: 0 | V4: 0 | W4: 0 | X4: 0 | Y4: 0 | Z4: 0.1192053 | AA4: 193.2196 | AB4: 48.24 | AC4: 65.284 | AD4: 70.892 | AE4: 0 | AF4: NO | AI4: Row Labels | AJ4: Sum of Opener_Score
A5: Akash Madhwal | B5: CSK | C5: Replacement for Ayush Mhatre | D5: Pacer | E5: 0.3 | F5: Akash_Madhwal_CSK | G5: 0 | H5: 0 | I5: 0 | J5: 0 | K5: 0 | L5: 0 | M5: 0 | N5: 0 | O5: 0 | P5: 0 | Q5: 0 | R5: 0 | S5: 0 | T5: 0 | U5: 0 | V5: 0 | W5: 0 | X5: 0 | Y5: 0 | Z5: 0 | AA5: 0 | AB5: 0 | AC5: 0 | AD5: 0 | AE5: 0 | AF5: NO | AI5: Shubman Gill | AJ5: 1193.3064 | AN5: Row Labels | AO5: Sum of AR_Score
A6: Urvil Patel | B6: CSK | C6: Retained | D6: Wicketkeeper | E6: 0 | F6: Urvil_Patel_CSK | G6: 0 | H6: 0 | I6: 0 | J6: 0 | K6: 0 | L6: 0 | M6: 0 | N6: 0 | O6: 0 | P6: 0 | Q6: 0 | R6: 0 | S6: 0 | T6: 0 | U6: 0 | V6: 0 | W6: 0 | X6: 0 | Y6: 0 | Z6: 0 | AA6: 0 | AB6: 0 | AC6: 0 | AD6: 0 | AE6: 0 | AF6: NO | AI6: Vaibhav Suryavanshi | AJ6: 1841.448 | AN6: Abhishek Sharma | AO6: 211.844
A7: Anshul Kamboj | B7: CSK | C7: Retained | D7: All-Rounder | E7: 0 | F7: Anshul_Kamboj_CSK | G7: 14 | H7: 58 | I7: 38 | J7: 29 | K7: 152.63 | L7: 0 | M7: 0 | N7: 3 | O7: 4 | P7: 2 | Q7: 14 | R7: 50.2 | S7: 530 | T7: 21 | U7: 10.52 | V7: 0 | W7: 25.23 | X7: 0 | Y7: 0 | Z7: 0.12068966 | AA7: 88.5254 | AB7: 57.926 | AC7: 73.152 | AD7: 198.886 | AE7: 199.48 | AF7: YES | AI7: Grand Total | AJ7: 3034.7544 | AN7: Anshul Kamboj | AO7: 198.886
A8: Dian Forrester | B8: CSK | C8: Replacement for Jamie Overton | D8: All-Rounder | E8: 0.75 | F8: Dian_Forrester_CSK | G8: 0 | H8: 0 | I8: 0 | J8: 0 | K8: 0 | L8: 0 | M8: 0 | N8: 0 | O8: 0 | P8: 0 | Q8: 0 | R8: 0 | S8: 0 | T8: 0 | U8: 0 | V8: 0 | W8: 0 | X8: 0 | Y8: 0 | Z8: 0 | AA8: 0 | AB8: 0 | AC8: 0 | AD8: 0 | AE8: 0 | AF8: NO | AN8: Hardik Pandya | AO8: 198.14
A9: Macneil Noronha | B9: CSK | C9: Replacement for Ramakrishna Ghosh | D9: All-Rounder | E9: 0.3 | F9: Macneil_Noronha_CSK | G9: 0 | H9: 0 | I9: 0 | J9: 0 | K9: 0 | L9: 0 | M9: 0 | N9: 0 | O9: 0 | P9: 0 | Q9: 0 | R9: 0 | S9: 0 | T9: 0 | U9: 0 | V9: 0 | W9: 0 | X9: 0 | Y9: 0 | Z9: 0 | AA9: 0 | AB9: 0 | AC9: 0 | AD9: 0 | AE9: 0 | AF9: NO | AN9: Grand Total | AO9: 608.87
A10: Shivam Dube | B10: CSK | C10: Retained | D10: All-Rounder | E10: 0 | F10: Shivam_Dube_CSK | G10: 13 | H10: 270 | I10: 170 | J10: 38.57 | K10: 158.82 | L10: 0 | M10: 0 | N10: 24 | O10: 15 | P10: 5 | Q10: 0 | R10: 0 | S10: 0 | T10: 0 | U10: 0 | V10: 0 | W10: 0 | X10: 0 | Y10: 0 | Z10: 0.14444444 | AA10: 428.814 | AB10: 99.192 | AC10: 100.028 | AD10: 122.764 | AE10: 0 | AF10: YES
A11: Kuldip Yadav | B11: CSK | C11: Replacement for Khaleel Ahmed | D11: Pacer | E11: 0.3 | F11: Kuldip_Yadav_CSK | G11: 0 | H11: 0 | I11: 0 | J11: 0 | K11: 0 | L11: 0 | M11: 0 | N11: 0 | O11: 0 | P11: 0 | Q11: 0 | R11: 0 | S11: 0 | T11: 0 | U11: 0 | V11: 0 | W11: 0 | X11: 0 | Y11: 0 | Z11: 0 | AA11: 0 | AB11: 0 | AC11: 0 | AD11: 0 | AE11: 0 | AF11: NO | AI11: Role | AJ11: (Multiple Items)
A12: Noor Ahmad | B12: CSK | C12: Retained | D12: Spinner | E12: 0 | F12: Noor_Ahmad_CSK | G12: 14 | H12: 11 | I12: 23 | J12: 3.66 | K12: 47.82 | L12: 0 | M12: 0 | N12: 0 | O12: 1 | P12: 1 | Q12: 14 | R12: 51 | S12: 428 | T12: 13 | U12: 8.39 | V12: 0 | W12: 32.92 | X12: 0 | Y12: 0 | Z12: 0.090909091 | AA12: 5.2602 | AB12: 17.128 | AC12: 22.978 | AD12: 102.084 | AE12: 121.61 | AF12: NO | AN12: Role | AO12: (Multiple Items)
A13: Mukesh Choudhary | B13: CSK | C13: Retained | D13: Pacer | E13: 0 | F13: Mukesh_Choudhary_CSK | G13: 0 | H13: 0 | I13: 0 | J13: 0 | K13: 0 | L13: 0 | M13: 0 | N13: 0 | O13: 0 | P13: 0 | Q13: 8 | R13: 28 | S13: 249 | T13: 8 | U13: 8.89 | V13: 0 | W13: 31.12 | X13: 0 | Y13: 0 | Z13: 0 | AA13: 0 | AB13: 0 | AC13: 0 | AD13: 46.22 | AE13: 71.11 | AF13: NO | AI13: Row Labels | AJ13: Sum of Middle_Order_Score
A14: Spencer Johnson | B14: CSK | C14: Replacement for Nathan Ellis | D14: Pacer | E14: 1.5 | F14: Spencer_Johnson_CSK | G14: 0 | H14: 0 | I14: 0 | J14: 0 | K14: 0 | L14: 0 | M14: 0 | N14: 0 | O14: 0 | P14: 0 | Q14: 0 | R14: 0 | S14: 0 | T14: 0 | U14: 0 | V14: 0 | W14: 0 | X14: 0 | Y14: 0 | Z14: 0 | AA14: 0 | AB14: 0 | AC14: 0 | AD14: 0 | AE14: 0 | AF14: NO | AI14: Abhishek Sharma | AJ14: 4634.4984 | AN14: Row Labels | AO14: Sum of Bowler_Score
A15: Shreyas Gopal | B15: CSK | C15: Retained | D15: Spinner | E15: 0 | F15: Shreyas_Gopal_CSK | G15: 0 | H15: 0 | I15: 0 | J15: 0 | K15: 0 | L15: 0 | M15: 0 | N15: 0 | O15: 0 | P15: 0 | Q15: 0 | R15: 0 | S15: 0 | T15: 0 | U15: 0 | V15: 0 | W15: 0 | X15: 0 | Y15: 0 | Z15: 0 | AA15: 0 | AB15: 0 | AC15: 0 | AD15: 0 | AE15: 0 | AF15: NO | AI15: Heinrich Klaasen | AJ15: 4792.32 | AN15: Arshdeep Singh | AO15: 129.8
A16: Gurjapneet Singh | B16: CSK | C16: Retained | D16: Pacer | E16: 0 | F16: Gurjapneet_Singh_CSK | G16: 0 | H16: 0 | I16: 0 | J16: 0 | K16: 0 | L16: 0 | M16: 0 | N16: 0 | O16: 0 | P16: 0 | Q16: 8 | R16: 25.1 | S16: 233 | T16: 4 | U16: 9.25 | V16: 0 | W16: 58.25 | X16: 0 | Y16: 0 | Z16: 0 | AA16: 0 | AB16: 0 | AC16: 0 | AD16: 13.5 | AE16: 30.75 | AF16: NO | AI16: KL Rahul | AJ16: 4717.2202 | AN16: Brijesh Sharma | AO16: 130.11
A17: Sanju Samson | B17: CSK | C17: Trade | D17: Wicketkeeper | E17: 0 | F17: Sanju_Samson_CSK | G17: 14 | H17: 477 | I17: 288 | J17: 43.36 | K17: 165.62 | L17: 2 | M17: 1 | N17: 53 | O17: 24 | P17: 3 | Q17: 0 | R17: 0 | S17: 0 | T17: 0 | U17: 0 | V17: 0 | W17: 0 | X17: 0 | Y17: 0 | Z17: 0.16142558 | AA17: 790.0074 | AB17: 113.168 | AC17: 108.848 | AD17: 182.224 | AE17: 0 | AF17: NO | AI17: Grand Total | AJ17: 14144.039 | AN17: Eshan Malinga | AO17: 190.67
A18: Akeal Hosein | B18: CSK | C18: Auction | D18: Pacer | E18: 2 | F18: Akeal_Hosein_CSK | G18: 7 | H18: 5 | I18: 3 | J18: - | K18: 166.66 | L18: 0 | M18: 0 | N18: 0 | O18: 0 | P18: 3 | Q18: 7 | R18: 24.4 | S18: 198 | T18: 8 | U18: 8.02 | V18: 1 | W18: 24.75 | X18: 0.4 | Y18: 0.25 | Z18: 0 | AA18: 8.333 | AB18: #VALUE! | AC18: 75.514 | AD18: 88.792 | AE18: 71.98 | AF18: NO | AN18: Jofra Archer | AO18: 240.69
A19: Prashant Veer | B19: CSK | C19: Auction | D19: All-Rounder | E19: 14.2 | F19: Prashant_Veer_CSK | G19: 6 | H19: 90 | I19: 67 | J19: 45 | K19: 134.32 | L19: 0 | M19: 0 | N19: 10 | O19: 3 | P19: 3 | Q19: 0 | R19: 0 | S19: 0 | T19: 0 | U19: 0 | V19: 0 | W19: 0 | X19: 0.15777778 | Y19: 0 | Z19: 0.14444444 | AA19: 120.888 | AB19: 68.864 | AC19: 65.378 | AD19: 59.864 | AE19: 0 | AF19: NO | AN19: Josh Hazlewood | AO19: 140.41
A20: Kartik Sharma | B20: CSK | C20: Auction | D20: Wicketkeeper | E20: 14.2 | F20: Kartik_Sharma_CSK | G20: 11 | H20: 295 | I20: 216 | J20: 32.77 | K20: 136.57 | L20: 0 | M20: 2 | N20: 24 | O20: 16 | P20: 2 | Q20: 0 | R20: 0 | S20: 0 | T20: 0 | U20: 0 | V20: 0 | W20: 0 | X20: 0.048135593 | Y20: 0 | Z20: 0.13559322 | AA20: 402.8815 | AB20: 79.922 | AC20: 81.828 | AD20: 119.814 | AE20: 0 | AF20: NO | AN20: Kagiso Rabada | AO20: 280.32
A21: Matthew Short | B21: CSK | C21: Auction | D21: All-Rounder | E21: 1.5 | F21: Matthew_Short_CSK | G21: 3 | H21: 60 | I21: 51 | J21: 20 | K21: 117.64 | L21: 0 | M21: 0 | N21: 6 | O21: 1 | P21: 0 | Q21: 0 | R21: 0 | S21: 0 | T21: 0 | U21: 0 | V21: 0 | W21: 0 | X21: 0.025 | Y21: 0 | Z21: 0.11666667 | AA21: 70.584 | AB21: 37.528 | AC21: 46.506 | AD21: 41.528 | AE21: 0 | AF21: NO | AN21: Kartik Tyagi | AO21: 170.24
A22: Aman Khan | B22: CSK | C22: Auction | D22: All-Rounder | E22: 0.4 | F22: Aman_Khan_CSK | G22: 0 | H22: 0 | I22: 0 | J22: 0 | K22: 0 | L22: 0 | M22: 0 | N22: 0 | O22: 0 | P22: 0 | Q22: 0 | R22: 0 | S22: 0 | T22: 0 | U22: 0 | V22: 0 | W22: 0 | X22: 0 | Y22: 0 | Z22: 0 | AA22: 0 | AB22: 0 | AC22: 0 | AD22: 0 | AE22: 0 | AF22: NO | AN22: Lungi Ngidi | AO22: 121.78
A23: Sarfaraz Khan | B23: CSK | C23: Auction | D23: Anchor | E23: 0.75 | F23: Sarfaraz_Khan_CSK | G23: 0 | H23: 0 | I23: 0 | J23: 0 | K23: 0 | L23: 0 | M23: 0 | N23: 0 | O23: 0 | P23: 0 | Q23: 0 | R23: 0 | S23: 0 | T23: 0 | U23: 0 | V23: 0 | W23: 0 | X23: 0 | Y23: 0 | Z23: 0 | AA23: 0 | AB23: 0 | AC23: 0 | AD23: 0 | AE23: 0 | AF23: NO | AN23: Mohammed Siraj | AO23: 180.94
A24: Rahul Chahar | B24: CSK | C24: Auction | D24: Spinner | E24: 1 | F24: Rahul_Chahar_CSK | G24: 0 | H24: 0 | I24: 0 | J24: 0 | K24: 0 | L24: 0 | M24: 0 | N24: 0 | O24: 0 | P24: 0 | Q24: 0 | R24: 0 | S24: 0 | T24: 0 | U24: 0 | V24: 0 | W24: 0 | X24: 0 | Y24: 0 | Z24: 0 | AA24: 0 | AB24: 0 | AC24: 0 | AD24: 0 | AE24: 0 | AF24: NO | AN24: Praful Hinge | AO24: 128.27
A25: Matt Henry | B25: CSK | C25: Auction | D25: Pacer | E25: 2 | F25: Matt_Henry_CSK | G25: 0 | H25: 0 | I25: 0 | J25: 0 | K25: 0 | L25: 0 | M25: 0 | N25: 0 | O25: 0 | P25: 0 | Q25: 0 | R25: 0 | S25: 0 | T25: 0 | U25: 0 | V25: 0 | W25: 0 | X25: 0 | Y25: 0 | Z25: 0 | AA25: 0 | AB25: 0 | AC25: 0 | AD25: 0 | AE25: 0 | AF25: NO | AN25: Prasidh Krishna | AO25: 149.57
A26: Zak Foulkes | B26: CSK | C26: Auction | D26: All-Rounder | E26: 0.75 | F26: Zak_Foulkes_CSK | G26: 0 | H26: 0 | I26: 0 | J26: 0 | K26: 0 | L26: 0 | M26: 0 | N26: 0 | O26: 0 | P26: 0 | Q26: 0 | R26: 0 | S26: 0 | T26: 0 | U26: 0 | V26: 0 | W26: 0 | X26: 0 | Y26: 0 | Z26: 0 | AA26: 0 | AB26: 0 | AC26: 0 | AD26: 0 | AE26: 0 | AF26: NO | AN26: Prince Yadav | AO26: 151.18
A27: KL Rahul | B27: DC | C27: Retained | D27: Wicketkeeper | E27: 0 | F27: KL_Rahul_DC | G27: 14 | H27: 593 | I27: 340 | J27: 45.61 | K27: 174.41 | L27: 1 | M27: 5 | N27: 56 | O27: 31 | P27: 1 | Q27: 0 | R27: 0 | S27: 0 | T27: 0 | U27: 0 | V27: 0 | W27: 0 | X27: 0 | Y27: 0 | Z27: 0.14671164 | AA27: 1034.2513 | AB27: 117.426 | AC27: 117.764 | AD27: 214.782 | AE27: 0 | AF27: NO | AI27: Eligible_Finisher | AJ27: YES | AN27: Rashid Khan | AO27: 200.93
A28: Karun Nair | B28: DC | C28: Retained | D28: Anchor | E28: 0 | F28: Karun_Nair_DC | G28: 2 | H28: 18 | I28: 18 | J28: 9 | K28: 100 | L28: 0 | M28: 0 | N28: 3 | O28: 0 | P28: 0 | Q28: 0 | R28: 0 | S28: 0 | T28: 0 | U28: 0 | V28: 0 | W28: 0 | X28: 0 | Y28: 0 | Z28: 0.16666667 | AA28: 18 | AB28: 25.4 | AC28: 39.1 | AD28: 25.4 | AE28: 0 | AF28: NO | AN28: Rasikh Salam | AO28: 180.55
A29: Abishek Porel | B29: DC | C29: Retained | D29: Wicketkeeper | E29: 0 | F29: Abishek_Porel_DC | G29: 4 | H29: 108 | I29: 88 | J29: 27 | K29: 122.72 | L29: 0 | M29: 1 | N29: 15 | O29: 1 | P29: 0 | Q29: 0 | R29: 0 | S29: 0 | T29: 0 | U29: 0 | V29: 0 | W29: 0 | X29: 0 | Y29: 0 | Z29: 0.14814815 | AA29: 132.5376 | AB29: 46.144 | AC29: 46.688 | AD29: 56.944 | AE29: 0 | AF29: NO | AI29: Row Labels | AJ29: Sum of Finisher_Score | AN29: Sakib Hussain | AO29: 140.55
A30: Tristan Stubbs | B30: DC | C30: Retained | D30: Anchor | E30: 0 | F30: Tristan_Stubbs_DC | G30: 14 | H30: 275 | I30: 216 | J30: 34.37 | K30: 127.31 | L30: 0 | M30: 2 | N30: 18 | O30: 9 | P30: 5 | Q30: 0 | R30: 0 | S30: 0 | T30: 0 | U30: 0 | V30: 0 | W30: 0 | X30: 0 | Y30: 0 | Z30: 0.098181818 | AA30: 350.1025 | AB30: 91.71 | AC30: 73.124 | AD30: 117.962 | AE30: 0 | AF30: NO | AI30: Finn Allen | AJ30: 136.494 | AN30: Grand Total | AO30: 2536.01
A31: Axar Patel | B31: DC | C31: Retained | D31: All-Rounder | E31: 0 | F31: Axar_Patel_DC | G31: 14 | H31: 173 | I31: 132 | J31: 19.22 | K31: 131.06 | L31: 0 | M31: 1 | N31: 16 | O31: 6 | P31: 2 | Q31: 14 | R31: 44 | S31: 360 | T31: 11 | U31: 8.18 | V31: 0 | W31: 32.72 | X31: 0 | Y31: 0 | Z31: 0.12716763 | AA31: 226.7338 | AB31: 61.2 | AC31: 63.824 | AD31: 153.752 | AE31: 101.82 | AF31: NO | AI31: Nitish Kumar Reddy | AJ31: 110.836
A32: Sameer Rizvi | B32: DC | C32: Retained | D32: Anchor | E32: 0 | F32: Sameer_Rizvi_DC | G32: 11 | H32: 252 | I32: 171 | J32: 36 | K32: 147.36 | L32: 0 | M32: 2 | N32: 15 | O32: 17 | P32: 2 | Q32: 0 | R32: 0 | S32: 0 | T32: 0 | U32: 0 | V32: 0 | W32: 0 | X32: 0 | Y32: 0 | Z32: 0.12698413 | AA32: 371.3472 | AB32: 79.072 | AC32: 90.394 | AD32: 109.072 | AE32: 0 | AF32: NO | AI32: Priyansh Arya | AJ32: 140.048
A33: Ashutosh Sharma | B33: DC | C33: Retained | D33: Anchor | E33: 0 | F33: Ashutosh_Sharma_DC | G33: 0 | H33: 0 | I33: 0 | J33: 0 | K33: 0 | L33: 0 | M33: 0 | N33: 0 | O33: 0 | P33: 0 | Q33: 0 | R33: 0 | S33: 0 | T33: 0 | U33: 0 | V33: 0 | W33: 0 | X33: 0 | Y33: 0 | Z33: 0 | AA33: 0 | AB33: 0 | AC33: 0 | AD33: 0 | AE33: 0 | AF33: NO | AI33: Grand Total | AJ33: 387.378
A34: Vipraj Nigam | B34: DC | C34: Retained | D34: All-Rounder | E34: 0 | F34: Vipraj_Nigam_DC | G34: 5 | H34: 15 | I34: 10 | J34: 15 | K34: 150 | L34: 0 | M34: 0 | N34: 2 | O34: 0 | P34: 1 | Q34: 5 | R34: 9 | S34: 113 | T34: 2 | U34: 12.55 | V34: 0 | W34: 56.5 | X34: 0 | Y34: 0 | Z34: 0.13333333 | AA34: 22.5 | AB34: 42.5 | AC34: 62.5 | AD34: 27.4 | AE34: 7.45 | AF34: NO
A35: Ajay Mandal | B35: DC | C35: Retained | D35: All-Rounder | E35: 0 | F35: Ajay_Mandal_DC | G35: 0 | H35: 0 | I35: 0 | J35: 0 | K35: 0 | L35: 0 | M35: 0 | N35: 0 | O35: 0 | P35: 0 | Q35: 0 | R35: 0 | S35: 0 | T35: 0 | U35: 0 | V35: 0 | W35: 0 | X35: 0 | Y35: 0 | Z35: 0 | AA35: 0 | AB35: 0 | AC35: 0 | AD35: 0 | AE35: 0 | AF35: NO
A36: Tripurana Vijay | B36: DC | C36: Retained | D36: All-Rounder | E36: 0 | F36: Tripurana_Vijay_DC | G36: 0 | H36: 0 | I36: 0 | J36: 0 | K36: 0 | L36: 0 | M36: 0 | N36: 0 | O36: 0 | P36: 0 | Q36: 0 | R36: 0 | S36: 0 | T36: 0 | U36: 0 | V36: 0 | W36: 0 | X36: 0 | Y36: 0 | Z36: 0 | AA36: 0 | AB36: 0 | AC36: 0 | AD36: 0 | AE36: 0 | AF36: NO
A37: Madhav Tiwari | B37: DC | C37: Retained | D37: All-Rounder | E37: 0 | F37: Madhav_Tiwari_DC | G37: 0 | H37: 0 | I37: 0 | J37: 0 | K37: 0 | L37: 0 | M37: 0 | N37: 0 | O37: 0 | P37: 0 | Q37: 3 | R37: 10 | S37: 87 | T37: 4 | U37: 8.7 | V37: 0 | W37: 21.75 | X37: 0 | Y37: 0 | Z37: 0 | AA37: 0 | AB37: 0 | AC37: 0 | AD37: 14.6 | AE37: 31.3 | AF37: NO
A38: Mitchell Starc | B38: DC | C38: Retained | D38: Pacer | E38: 0 | F38: Mitchell_Starc_DC | G38: 0 | H38: 0 | I38: 0 | J38: 0 | K38: 0 | L38: 0 | M38: 0 | N38: 0 | O38: 0 | P38: 0 | Q38: 6 | R38: 22 | S38: 224 | T38: 11 | U38: 10.18 | V38: 0 | W38: 20.36 | X38: 0 | Y38: 0 | Z38: 0 | AA38: 0 | AB38: 0 | AC38: 0 | AD38: 67.64 | AE38: 99.82 | AF38: NO
A39: T Natarajan | B39: DC | C39: Retained | D39: Pacer | E39: 0 | F39: T_Natarajan_DC | G39: 0 | H39: 0 | I39: 0 | J39: 0 | K39: 0 | L39: 0 | M39: 0 | N39: 0 | O39: 0 | P39: 0 | Q39: 10 | R39: 31.5 | S39: 356 | T39: 5 | U39: 11.18 | V39: 0 | W39: 71.2 | X39: 0 | Y39: 0 | Z39: 0 | AA39: 0 | AB39: 0 | AC39: 0 | AD39: 17.64 | AE39: 38.82 | AF39: NO
A40: Mukesh Kumar | B40: DC | C40: Retained | D40: Pacer | E40: 0 | F40: Mukesh_Kumar_DC | G40: 0 | H40: 0 | I40: 0 | J40: 0 | K40: 0 | L40: 0 | M40: 0 | N40: 0 | O40: 0 | P40: 0 | Q40: 10 | R40: 31.2 | S40: 353 | T40: 6 | U40: 11.26 | V40: 0 | W40: 58.83 | X40: 0 | Y40: 0 | Z40: 0 | AA40: 0 | AB40: 0 | AC40: 0 | AD40: 25.48 | AE40: 48.74 | AF40: NO
A41: Dushmantha Chameera | B41: DC | C41: Retained | D41: Pacer | E41: 0 | F41: Dushmantha_Chameera_DC | G41: 0 | H41: 0 | I41: 0 | J41: 0 | K41: 0 | L41: 0 | M41: 0 | N41: 0 | O41: 0 | P41: 0 | Q41: 0 | R41: 0 | S41: 0 | T41: 0 | U41: 0 | V41: 0 | W41: 0 | X41: 0 | Y41: 0 | Z41: 0 | AA41: 0 | AB41: 0 | AC41: 0 | AD41: 0 | AE41: 0 | AF41: NO
A42: Kuldeep Yadav | B42: DC | C42: Retained | D42: Spinner | E42: 0 | F42: Kuldeep_Yadav_DC | G42: 12 | H42: 9 | I42: 21 | J42: 3 | K42: 42.85 | L42: 0 | M42: 0 | N42: 0 | O42: 0 | P42: 1 | Q42: 12 | R42: 37 | S42: 381 | T42: 10 | U42: 10.29 | V42: 0 | W42: 38.1 | X42: 0 | Y42: 0 | Z42: 0 | AA42: 3.8565 | AB42: 15.67 | AC42: 19.09 | AD42: 72.69 | AE42: 89.71 | AF42: NO
A43: Nitish Rana | B43: DC | C43: Trade | D43: Anchor | E43: 0 | F43: Nitish_Rana_DC | G43: 0 | H43: 0 | I43: 0 | J43: 0 | K43: 0 | L43: 0 | M43: 0 | N43: 0 | O43: 0 | P43: 0 | Q43: 0 | R43: 0 | S43: 0 | T43: 0 | U43: 0 | V43: 0 | W43: 0 | X43: 0 | Y43: 0 | Z43: 0 | AA43: 0 | AB43: 0 | AC43: 0 | AD43: 0 | AE43: 0 | AF43: NO
A44: Auqib Nabi | B44: DC | C44: Auction | D44: All-Rounder | E44: 8.4 | F44: Auqib_Nabi_DC | G44: 0 | H44: 0 | I44: 0 | J44: 0 | K44: 0 | L44: 0 | M44: 0 | N44: 0 | O44: 0 | P44: 0 | Q44: 0 | R44: 0 | S44: 0 | T44: 0 | U44: 0 | V44: 0 | W44: 0 | X44: 0 | Y44: 0 | Z44: 0 | AA44: 0 | AB44: 0 | AC44: 0 | AD44: 0 | AE44: 0 | AF44: NO
A45: Rehan Ahmed | B45: DC | C45: Replacement for Ben Duckett | D45: Pacer | E45: 0.75 | F45: Rehan_Ahmed_DC | G45: 0 | H45: 0 | I45: 0 | J45: 0 | K45: 0 | L45: 0 | M45: 0 | N45: 0 | O45: 0 | P45: 0 | Q45: 0 | R45: 0 | S45: 0 | T45: 0 | U45: 0 | V45: 0 | W45: 0 | X45: 0 | Y45: 0 | Z45: 0 | AA45: 0 | AB45: 0 | AC45: 0 | AD45: 0 | AE45: 0 | AF45: NO
... A64: Mohammed Siraj | B64: GT | C64: Retained | D64: Pacer | E64: 0 | F64: Mohammed_Siraj_GT | G64: 17 | H64: 5 | I64: 16 | J64: 2.5 | K64: 31.25 | L64: 0 | M64: 0 | N64: 1 | O64: 0 | P64: 0 | Q64: 17 | R64: 62 | S64: 562 | T64: 19 | U64: 9.06 | V64: 1 | W64: 29.57 | X64: 0 | Y64: 0 | Z64: 0.2 | AA64: 1.5625 | AB64: 7.75 | AC64: 11.7 | AD64: 141.63 | AE64: 180.94 | AF64: NO
A65: Prasidh Krishna | B65: GT | C65: Retained | D65: Pacer | E65: 0 | F65: Prasidh_Krishna_GT | G65: 12 | H65: 6 | I65: 7 | J65: - | K65: 85.71 | L65: 0 | M65: 0 | N65: 1 | O65: 0 | P65: 1 | Q65: 12 | R65: 39 | S65: 407 | T65: 16 | U65: 10.43 | V65: 0 | W65: 25.43 | X65: 0 | Y65: 0 | Z65: 0.16666667 | AA65: 5.1426 | AB65: #VALUE! | AC65: 36.934 | AD65: 128.082 | AE65: 149.57 | AF65: NO
A66: Ishant Sharma | B66: GT | C66: Retained | D66: Pacer | E66: 0 | F66: Ishant_Sharma_GT | G66: 0 | H66: 0 | I66: 0 | J66: 0 | K66: 0 | L66: 0 | M66: 0 | N66: 0 | O66: 0 | P66: 0 | Q66: 0 | R66: 0 | S66: 0 | T66: 0 | U66: 0 | V66: 0 | W66: 0 | X66: 0 | Y66: 0 | Z66: 0 | AA66: 0 | AB66: 0 | AC66: 0 | AD66: 0 | AE66: 0 | AF66: NO
A67: Gurnoor Brar | B67: GT | C67: Retained | D67: Pacer | E67: 0 | F67: Gurnoor_Brar_GT | G67: 0 | H67: 0 | I67: 0 | J67: 0 | K67: 0 | L67: 0 | M67: 0 | N67: 0 | O67: 0 | P67: 0 | Q67: 0 | R67: 0 | S67: 0 | T67: 0 | U67: 0 | V67: 0 | W67: 0 | X67: 0 | Y67: 0 | Z67: 0 | AA67: 0 | AB67: 0 | AC67: 0 | AD67: 0 | AE67: 0 | AF67: NO
A68: Rashid Khan | B68: GT | C68: Retained | D68: Spinner | E68: 0 | F68: Rashid_Khan_GT | G68: 17 | H68: 50 | I68: 41 | J68: 12.5 | K68: 121.95 | L68: 0 | M68: 0 | N68: 4 | O68: 2 | P68: 2 | Q68: 17 | R68: 56.5 | S68: 516 | T68: 21 | U68: 9.07 | V68: 0 | W68: 24.57 | X68: 0 | Y68: 0 | Z68: 0.12 | AA68: 60.975 | AB68: 44.39 | AC68: 56.73 | AD68: 193.25 | AE68: 200.93 | AF68: NO
A69: Manav Suthar | B69: GT | C69: Retained | D69: Spinner | E69: 0 | F69: Manav_Suthar_GT | G69: 0 | H69: 0 | I69: 0 | J69: 0 | K69: 0 | L69: 0 | M69: 0 | N69: 0 | O69: 0 | P69: 0 | Q69: 4 | R69: 6 | S69: 68 | T69: 2 | U69: 11.33 | V69: 0 | W69: 34 | X69: 0 | Y69: 0 | Z69: 0 | AA69: 0 | AB69: 0 | AC69: 0 | AD69: -6.66 | AE69: 8.67 | AF69: NO
A70: Sai Kishore | B70: GT | C70: Retained | D70: Spinner | E70: 0 | F70: Sai_Kishore_GT | G70: 0 | H70: 0 | I70: 0 | J70: 0 | K70: 0 | L70: 0 | M70: 0 | N70: 0 | O70: 0 | P70: 0 | Q70: 0 | R70: 0 | S70: 0 | T70: 0 | U70: 0 | V70: 0 | W70: 0 | X70: 0 | Y70: 0 | Z70: 0 | AA70: 0 | AB70: 0 | AC70: 0 | AD70: 0 | AE70: 0 | AF70: NO
A71: Jayant Yadav | B71: GT | C71: Retained | D71: Spinner | E71: 0 | F71: Jayant_Yadav_GT | G71: 0 | H71: 0 | I71: 0 | J71: 0 | K71: 0 | L71: 0 | M71: 0 | N71: 0 | O71: 0 | P71: 0 | Q71: 0 | R71: 0 | S71: 0 | T71: 0 | U71: 0 | V71: 0 | W71: 0 | X71: 0 | Y71: 0 | Z71: 0 | AA71: 0 | AB71: 0 | AC71: 0 | AD71: 0 | AE71: 0 | AF71: NO
A72: Ashok Sharma | B72: GT | C72: Auction | D72: Pacer | E72: 0.9 | F72: Ashok_Sharma_GT | G72: 0 | H72: 0 | I72: 0 | J72: 0 | K72: 0 | L72: 0 | M72: 0 | N72: 0 | O72: 0 | P72: 0 | Q72: 6 | R72: 21 | S72: 228 | T72: 6 | U72: 10.85 | V72: 0 | W72: 38 | X72: 0 | Y72: 0.15 | Z72: 0 | AA72: 0 | AB72: 0 | AC72: 0 | AD72: 26.3 | AE72: 49.15 | AF72: NO
A73: Jason Holder | B73: GT | C73: Auction | D73: All-Rounder | E73: 7 | F73: Jason_Holder_GT | G73: 0 | H73: 0 | I73: 0 | J73: 0 | K73: 0 | L73: 0 | M73: 0 | N73: 0 | O73: 0 | P73: 0 | Q73: 0 | R73: 0 | S73: 0 | T73: 0 | U73: 0 | V73: 0 | W73: 0 | X73: 0 | Y73: 0 | Z73: 0 | AA73: 0 | AB73: 0 | AC73: 0 | AD73: 0 | AE73: 0 | AF73: NO
A74: Connor Esterhuizen | B74: GT | C74: Replacement for Tom Banton | D74: Wicketkeeper | E74: 0.75 | F74: Connor_Esterhuizen_GT | G74: 0 | H74: 0 | I74: 0 | J74: 0 | K74: 0 | L74: 0 | M74: 0 | N74: 0 | O74: 0 | P74: 0 | Q74: 0 | R74: 0 | S74: 0 | T74: 0 | U74: 0 | V74: 0 | W74: 0 | X74: 0 | Y74: 0 | Z74: 0 | AA74: 0 | AB74: 0 | AC74: 0 | AD74: 0 | AE74: 0 | AF74: NO
A75: Luke Wood | B75: GT | C75: Auction | D75: Pacer | E75: 0.75 | F75: Luke_Wood_GT | G75: 0 | H75: 0 | I75: 0 | J75: 0 | K75: 0 | L75: 0 | M75: 0 | N75: 0 | O75: 0 | P75: 0 | Q75: 0 | R75: 0 | S75: 0 | T75: 0 | U75: 0 | V75: 0 | W75: 0 | X75: 0 | Y75: 0 | Z75: 0 | AA75: 0 | AB75: 0 | AC75: 0 | AD75: 0 | AE75: 0 | AF75: NO
A76: Kulwant Khejroliya | B76: GT | C76: Replacement for Prithviraj Yarra | D76: Pacer | E76: 0.3 | F76: Kulwant_Khejroliya_GT | G76: 0 | H76: 0 | I76: 0 | J76: 0 | K76: 0 | L76: 0 | M76: 0 | N76: 0 | O76: 0 | P76: 0 | Q76: 0 | R76: 0 | S76: 0 | T76: 0 | U76: 0 | V76: 0 | W76: 0 | X76: 0 | Y76: 0 | Z76: 0 | AA76: 0 | AB76: 0 | AC76: 0 | AD76: 0 | AE76: 0 | AF76: NO
A77: Ajinkya Rahane | B77: KKR | C77: Retained | D77: Anchor | E77: 0 | F77: Ajinkya_Rahane_KKR | G77: 14 | H77: 335 | I77: 248 | J77: 25.76 | K77: 135.08 | L77: 0 | M77: 2 | N77: 25 | O77: 18 | P77: 1 | Q77: 0 | R77: 0 | S77: 0 | T77: 0 | U77: 0 | V77: 0 | W77: 0 | X77: 0 | Y77: 0 | Z77: 0.12835821 | AA77: 452.518 | AB77: 75.82 | AC77: 80.632 | AD77: 129.516 | AE77: 0 | AF77: NO
... A153: Nehal Wadhera | B153: PBKS | C153: Retained | D153: Anchor | E153: 0 | F153: Nehal_Wadhera_PBKS | G153: 8 | H153: 65 | I153: 57 | J153: 10.83 | K153: 114.03 | L153: 0 | M153: 0 | N153: 4 | O153: 4 | P153: 0 | Q153: 0 | R153: 0 | S153: 0 | T153: 0 | U153: 0 | V153: 0 | W153: 0 | X153: 0 | Y153: 0 | Z153: 0.12307692 | AA153: 74.1195 | AB153: 33.638 | AC153: 50.762 | AD153: 42.306 | AE153: 0 | AF153: NO
A154: Vishnu Vinod | B154: PBKS | C154: Retained | D154: Wicketkeeper | E154: 0 | F154: Vishnu_Vinod_PBKS | G154: 1 | H154: 15 | I154: 8 | J154: - | K154: 187.5 | L154: 0 | M154: 0 | N154: 1 | O154: 1 | P154: 1 | Q154: 0 | R154: 0 | S154: 0 | T154: 0 | U154: 0 | V154: 0 | W154: 0 | X154: 0 | Y154: 0 | Z154: 0.13333333 | AA154: 28.125 | AB154: #VALUE! | AC154: 79.6 | AD154: 44 | AE154: 0 | AF154: YES
A155: Harnoor Singh | B155: PBKS | C155: Retained | D155: Anchor | E155: 0 | F155: Harnoor_Singh_PBKS | G155: 0 | H155: 0 | I155: 0 | J155: 0 | K155: 0 | L155: 0 | M155: 0 | N155: 0 | O155: 0 | P155: 0 | Q155: 0 | R155: 0 | S155: 0 | T155: 0 | U155: 0 | V155: 0 | W155: 0 | X155: 0 | Y155: 0 | Z155: 0 | AA155: 0 | AB155: 0 | AC155: 0 | AD155: 0 | AE155: 0 | AF155: NO
A156: Pyla Avinash | B156: PBKS | C156: Retained | D156: Anchor | E156: 0 | F156: Pyla_Avinash_PBKS | G156: 0 | H156: 0 | I156: 0 | J156: 0 | K156: 0 | L156: 0 | M156: 0 | N156: 0 | O156: 0 | P156: 0 | Q156: 0 | R156: 0 | S156: 0 | T156: 0 | U156: 0 | V156: 0 | W156: 0 | X156: 0 | Y156: 0 | Z156: 0 | AA156: 0 | AB156: 0 | AC156: 0 | AD156: 0 | AE156: 0 | AF156: NO
A157: Prabhsimran Singh | B157: PBKS | C157: Retained | D157: Wicketkeeper | E157: 0 | F157: Prabhsimran_Singh_PBKS | G157: 14 | H157: 510 | I157: 302 | J157: 42.5 | K157: 168.87 | L157: 0 | M157: 6 | N157: 55 | O157: 23 | P157: 1 | Q157: 0 | R157: 0 | S157: 0 | T157: 0 | U157: 0 | V157: 0 | W157: 0 | X157: 0 | Y157: 0 | Z157: 0.15294118 | AA157: 861.237 | AB157: 106.774 | AC157: 101.448 | AD157: 188.774 | AE157: 0 | AF157: NO
A158: Shashank Singh | B158: PBKS | C158: Retained | D158: Anchor | E158: 0 | F158: Shashank_Singh_PBKS | G158: 12 | H158: 132 | I158: 70 | J158: 22 | K158: 188.57 | L158: 0 | M158: 1 | N158: 11 | O158: 8 | P158: 3 | Q158: 12 | R158: 10 | S158: 88 | T158: 4 | U158: 8.8 | V158: 0 | W158: 22 | X158: 0 | Y158: 0 | Z158: 0.14393939 | AA158: 248.9124 | AB158: 74.714 | AC158: 96.928 | AD158: 97.714 | AE158: 31.2 | AF158: NO
A159: Marcus Stoinis | B159: PBKS | C159: Retained | D159: All-Rounder | E159: 0 | F159: Marcus_Stoinis_PBKS | G159: 0 | H159: 0 | I159: 0 | J159: 0 | K159: 0 | L159: 0 | M159: 0 | N159: 0 | O159: 0 | P159: 0 | Q159: 13 | R159: 7.5 | S159: 98 | T159: 2 | U159: 12.51 | V159: 0 | W159: 49 | X159: 0 | Y159: 0 | Z159: 0 | AA159: 0 | AB159: 0 | AC159: 0 | AD159: -9.02 | AE159: 7.49 | AF159: NO
A160: Harpreet Brar | B160: PBKS | C160: Retained | D160: All-Rounder | E160: 0 | F160: Harpreet_Brar_PBKS | G160: 2 | H160: 5 | I160: 3 | J160: - | K160: 166.66 | L160: 0 | M160: 0 | N160: 1 | O160: 0 | P160: 1 | Q160: 2 | R160: 8 | S160: 60 | T160: 2 | U160: 7.5 | V160: 0 | W160: 30 | X160: 0 | Y160: 0 | Z160: 0.2 | AA160: 8.333 | AB160: #VALUE! | AC160: 69.514 | AD160: 37.832 | AE160: 12.5 | AF160: YES
A161: Marco Jansen | B161: PBKS | C161: Retained | D161: All-Rounder | E161: 0 | F161: Marco_Jansen_PBKS | G161: 0 | H161: 0 | I161: 0 | J161: 0 | K161: 0 | L161: 0 | M161: 0 | N161: 0 | O161: 0 | P161: 0 | Q161: 13 | R161: 47.2 | S161: 483 | T161: 9 | U161: 10.2 | V161: 0 | W161: 53.66 | X161: 0 | Y161: 0 | Z161: 0 | AA161: 0 | AB161: 0 | AC161: 0 | AD161: 51.6 | AE161: 79.8 | AF161: NO
A162: Azmatullah Omarzai | B162: PBKS | C162: Retained | D162: All-Rounder | E162: 0 | F162: Azmatullah_Omarzai_PBKS | G162: 3 | H162: 52 | I162: 27 | J162: 26 | K162: 192.59 | L162: 0 | M162: 0 | N162: 3 | O162: 5 | P162: 0 | Q162: 3 | R162: 11 | S162: 103 | T162: 3 | U162: 9.36 | V162: 0 | W162: 34.33 | X162: 0 | Y162: 0 | Z162: 0.15384615 | AA162: 100.1468 | AB162: 54.118 | AC162: 85.686 | AD162: 59.398 | AE162: 20.64 | AF162: YES
A163: Priyansh Arya | B163: PBKS | C163: Retained | D163: All-Rounder | E163: 0 | F163: Priyansh_Arya_PBKS | G163: 13 | H163: 364 | I163: 172 | J163: 28 | K163: 211.62 | L163: 0 | M163: 3 | N163: 27 | O163: 32 | P163: 0 | Q163: 0 | R163: 0 | S163: 0 | T163: 0 | U163: 0 | V163: 0 | W163: 0 | X163: 0 | Y163: 0 | Z163: 0.16208791 | AA163: 770.2968 | AB163: 89.924 | AC163: 140.048 | AD163: 151.524 | AE163: 0 | AF163: YES
A164: Musheer Khan | B164: PBKS | C164: Retained | D164: All-Rounder | E164: 0 | F164: Musheer_Khan_PBKS | G164: 0 | H164: 0 | I164: 0 | J164: 0 | K164: 0 | L164: 0 | M164: 0 | N164: 0 | O164: 0 | P164: 0 | Q164: 0 | R164: 0 | S164: 0 | T164: 0 | U164: 0 | V164: 0 | W164: 0 | X164: 0 | Y164: 0 | Z164: 0 | AA164: 0 | AB164: 0 | AC164: 0 | AD164: 0 | AE164: 0 | AF164: NO
A165: Suryansh Shedge | B165: PBKS | C165: Retained | D165: All-Rounder | E165: 0 | F165: Suryansh_Shedge_PBKS | G165: 7 | H165: 158 | I165: 90 | J165: 39.5 | K165: 175.55 | L165: 0 | M165: 1 | N165: 9 | O165: 12 | P165: 3 | Q165: 0 | R165: 0 | S165: 0 | T165: 0 | U165: 0 | V165: 0 | W165: 0 | X165: 0 | Y165: 0 | Z165: 0.13291139 | AA165: 277.369 | AB165: 81.71 | AC165: 98.72 | AD165: 88.51 | AE165: 0 | AF165: YES
A166: Mitchell Owen | B166: PBKS | C166: Retained | D166: All-Rounder | E166: 0 | F166: Mitchell_Owen_PBKS | G166: 0 | H166: 0 | I166: 0 | J166: 0 | K166: 0 | L166: 0 | M166: 0 | N166: 0 | O166: 0 | P166: 0 | Q166: 0 | R166: 0 | S166: 0 | T166: 0 | U166: 0 | V166: 0 | W166: 0 | X166: 0 | Y166: 0 | Z166: 0 | AA166: 0 | AB166: 0 | AC166: 0 | AD166: 0 | AE166: 0 | AF166: NO
A167: Arshdeep Singh | B167: PBKS | C167: Retained | D167: Pacer | E167: 0 | F167: Arshdeep_Singh_PBKS | G167: 0 | H167: 0 | I167: 0 | J167: 0 | K167: 0 | L167: 0 | M167: 0 | N167: 0 | O167: 0 | P167: 0 | Q167: 14 | R167: 53 | S167: 541 | T167: 14 | U167: 10.2 | V167: 0 | W167: 38.64 | X167: 0 | Y167: 0 | Z167: 0 | AA167: 0 | AB167: 0 | AC167: 0 | AD167: 91.6 | AE167: 129.8 | AF167: NO
A168: Yuzvendra Chahal | B168: PBKS | C168: Retained | D168: Spinner | E168: 0 | F168: Yuzvendra_Chahal_PBKS | G168: 0 | H168: 0 | I168: 0 | J168: 0 | K168: 0 | L168: 0 | M168: 0 | N168: 0 | O168: 0 | P168: 0 | Q168: 0 | R168: 0 | S168: 0 | T168: 0 | U168: 0 | V168: 0 | W168: 0 | X168: 0 | Y168: 0 | Z168: 0 | AA168: 0 | AB168: 0 | AC168: 0 | AD168: 0 | AE168: 0 | AF168: NO
A169: Vijaykumar Vyshak | B169: PBKS | C169: Retained | D169: Pacer | E169: 0 | F169: Vijaykumar_Vyshak_PBKS | G169: 0 | H169: 0 | I169: 0 | J169: 0 | K169: 0 | L169: 0 | M169: 0 | N169: 0 | O169: 0 | P169: 0 | Q169: 10 | R169: 31 | S169: 330 | T169: 9 | U169: 10.64 | V169: 0 | W169: 36.66 | X169: 0 | Y169: 0 | Z169: 0 | AA169: 0 | AB169: 0 | AC169: 0 | AD169: 50.72 | AE169: 79.36 | AF169: NO
A170: Yash Thakur | B170: PBKS | C170: Retained | D170: Pacer | E170: 0 | F170: Yash_Thakur_PBKS | G170: 0 | H170: 0 | I170: 0 | J170: 0 | K170: 0 | L170: 0 | M170: 0 | N170: 0 | O170: 0 | P170: 0 | Q170: 1 | R170: 4 | S170: 55 | T170: 2 | U170: 13.75 | V170: 0 | W170: 27.5 | X170: 0 | Y170: 0 | Z170: 0 | AA170: 0 | AB170: 0 | AC170: 0 | AD170: -11.5 | AE170: 6.25 | AF170: NO
A171: Xavier Bartlett | B171: PBKS | C171: Retained | D171: Pacer | E171: 0 | F171: Xavier_Bartlett_PBKS | G171: 0 | H171: 0 | I171: 0 | J171: 0 | K171: 0 | L171: 0 | M171: 0 | N171: 0 | O171: 0 | P171: 0 | Q171: 9 | R171: 33.3 | S171: 388 | T171: 5 | U171: 11.58 | V171: 0 | W171: 77.6 | X171: 0 | Y171: 0 | Z171: 0 | AA171: 0 | AB171: 0 | AC171: 0 | AD171: 16.84 | AE171: 38.42 | AF171: NO
A172: Lockie Ferguson | B172: PBKS | C172: Retained | D172: Pacer | E172: 0 | F172: Lockie_Ferguson_PBKS | G172: 0 | H172: 0 | I172: 0 | J172: 0 | K172: 0 | L172: 0 | M172: 0 | N172: 0 | O172: 0 | P172: 0 | Q172: 0 | R172: 0 | S172: 0 | T172: 0 | U172: 0 | V172: 0 | W172: 0 | X172: 0 | Y172: 0 | Z172: 0 | AA172: 0 | AB172: 0 | AC172: 0 | AD172: 0 | AE172: 0 | AF172: NO
... A247: Onkar Tarmale | B247: SRH | C247: Auction | D247: Pacer | E247: 0.3 | F247: Onkar_Tarmale_SRH | G247: 0 | H247: 0 | I247: 0 | J247: 0 | K247: 0 | L247: 0 | M247: 0 | N247: 0 | O247: 0 | P247: 0 | Q247: 0 | R247: 0 | S247: 0 | T247: 0 | U247: 0 | V247: 0 | W247: 0 | X247: 0 | Y247: 0 | Z247: 0 | AA247: 0 | AB247: 0 | AC247: 0 | AD247: 0 | AE247: 0 | AF247: NO
A248: Sakib Hussain | B248: SRH | C248: Auction | D248: Pacer | E248: 0.3 | F248: Sakib_Hussain_SRH | G248: 11 | H248: 5 | I248: 7 | J248: - | K248: 71.42 | L248: 0 | M248: 0 | N248: 1 | O248: 0 | P248: 1 | Q248: 11 | R248: 42 | S248: 397 | T248: 15 | U248: 9.45 | V248: 0 | W248: 26.46 | X248: 0.06 | Y248: 0.02 | Z248: 0.2 | AA248: 3.571 | AB248: #VALUE! | AC248: 31.218 | AD248: 118.884 | AE248: 140.55 | AF248: NO
A249: Liam Livingstone | B249: SRH | C249: Auction | D249: All-Rounder | E249: 13 | F249: Liam_Livingstone_SRH | G249: 2 | H249: 15 | I249: 25 | J249: 7.5 | K249: 60 | L249: 0 | M249: 0 | N249: 0 | O249: 1 | P249: 0 | Q249: 0 | R249: 0 | S249: 0 | T249: 0 | U249: 0 | V249: 0 | W249: 0 | X249: 0.86666667 | Y249: 0 | Z249: 0.066666667 | AA249: 9 | AB249: 16.5 | AC249: 24.75 | AD249: 16.5 | AE249: 0 | AF249: NO
A250: RS Ambrish | B250: SRH | C250: Replacement for Shivam Mavi | D250: All-Rounder | E250: 0.3 | F250: RS_Ambrish_SRH | G250: 0 | H250: 0 | I250: 0 | J250: 0 | K250: 0 | L250: 0 | M250: 0 | N250: 0 | O250: 0 | P250: 0 | Q250: 0 | R250: 0 | S250: 0 | T250: 0 | U250: 0 | V250: 0 | W250: 0 | X250: 0 | Y250: 0 | Z250: 0 | AA250: 0 | AB250: 0 | AC250: 0 | AD250: 0 | AE250: 0 | AF250: NO
A251: Gerald Coetzee | B251: SRH | C251: Replacement for David Payne | D251: Pacer | E251: 2 | F251: Gerald_Coetzee_SRH | G251: 0 | H251: 0 | I251: 0 | J251: 0 | K251: 0 | L251: 0 | M251: 0 | N251: 0 | O251: 0 | P251: 0 | Q251: 0 | R251: 0 | S251: 0 | T251: 0 | U251: 0 | V251: 0 | W251: 0 | X251: 0 | Y251: 0 | Z251: 0 | AA251: 0 | AB251: 0 | AC251: 0 | AD251: 0 | AE251: 0 | AF251: NO

Sheet Master_Batsman_Analysis
A1: Player | B1: Team | C1: Role | D1: Price | E1: Matches | F1: Runs | G1: Balls | H1: Average | I1: Strike Rate | J1: 100s | K1: 50s | L1: 4s | M1: 6s | N1: Not Outs | O1: Cost Per Run | P1: Boundary Percentage | Q1: Batting_Impact | R1: Consistency Score | S1: Aggression Score | T1: Value Score | U1: Overprice Score | V1: Key
A2: Vishnu Vinod | B2: PBKS | C2: Wicketkeeper | D2: 0 | E2: 1 | F2: 15 | G2: 8 | H2: - | I2: 187.5 | J2: 0 | K2: 0 | L2: 1 | M2: 1 | N2: 1 | O2: 0 | P2: 0.13333333 | Q2: #VALUE! | R2: #VALUE! | S2: 25 | T2: 0 | U2: #VALUE! | V2: Vishnu Vinod_PBKS
A3: Vaibhav Suryavanshi | B3: RR | C3: Anchor | D3: 0 | E3: 16 | F3: 776 | G3: 327 | H3: 48.5 | I3: 237.3 | J3: 1 | K3: 5 | L3: 63 | M3: 72 | N3: 0 | O3: 0 | P3: 0.17396907 | Q3: 8931.0228 | R3: 776 | S3: 41.282861 | T3: 0 | U3: 0 | V3: Vaibhav Suryavanshi_RR | AB3: Role | AC3: Wicketkeeper
A4: Kartik Sharma | B4: CSK | C4: Wicketkeeper | D4: 14.2 | E4: 11 | F4: 295 | G4: 216 | H4: 32.77 | I4: 136.57 | J4: 0 | K4: 2 | L4: 24 | M4: 16 | N4: 2 | O4: 0.048135593 | P4: 0.13559322 | Q4: 1320.2427 | R4: 360.47 | S4: 18.517966 | T4: 92.974836 | U4: 0.010755598 | V4: Kartik Sharma_CSK
A5: Akash Madhwal | B5: CSK | C5: Pacer | D5: 0.3 | E5: 0 | F5: 0 | G5: 0 | H5: 0 | I5: 0 | J5: 0 | K5: 0 | L5: 0 | M5: 0 | N5: 0 | O5: 0 | P5: 0 | Q5: 0 | Y5: Row Labels | Z5: Sum of Batting_Impact | AB5: Row Labels | AC5: Sum of Strike Rate
A6: Mukul Choudhary | B6: LSG | C6: Wicketkeeper | D6: 2.6 | E6: 10 | F6: 170 | G6: 120 | H6: 28.33 | I6: 141.66 | J6: 0 | K6: 1 | L6: 11 | M6: 12 | N6: 4 | O6: 0.015294118 | P6: 0.13529412 | Q6: 682.24873 | R6: 283.3 | S6: 19.165765 | T6: 262.40336 | U6: 0.0038109269 | V6: Mukul Choudhary_LSG | Y6: Shubman Gill | Z6: 5459.3768 | AB6: Finn Allen | AC6: 214.11
A7: Anshul Kamboj | B7: CSK | C7: All-Rounder | D7: 0 | E7: 14 | F7: 58 | G7: 38 | H7: 29 | I7: 152.63 | J7: 0 | K7: 0 | L7: 3 | M7: 4 | N7: 2 | O7: 0 | P7: 0.12068966 | Q7: 256.72366 | Y7: Vaibhav Suryavanshi | Z7: 8931.0228 | AB7: Ryan Rickelton | AC7: 186.66
A8: Dian Forrester | B8: CSK | C8: All-Rounder | D8: 0.75 | E8: 0 | F8: 0 | G8: 0 | H8: 0 | I8: 0 | J8: 0 | K8: 0 | L8: 0 | M8: 0 | N8: 0 | O8: 0 | P8: 0 | Q8: 0 | Y8: Virat Kohli | Z8: 6296.7375 | AB8: Vishnu Vinod | AC8: 187.5
A9: Macneil Noronha | B9: CSK | C9: All-Rounder | D9: 0.3 | E9: 0 | F9: 0 | G9: 0 | H9: 0 | I9: 0 | J9: 0 | K9: 0 | L9: 0 | M9: 0 | N9: 0 | O9: 0 | P9: 0 | Q9: 0 | Y9: Grand Total | Z9: 20687.137 | AB9: Grand Total | AC9: 588.27
A10: Shivam Dube | B10: CSK | C10: All-Rounder | D10: 0 | E10: 13 | F10: 270 | G10: 170 | H10: 38.57 | I10: 158.82 | J10: 0 | K10: 0 | L10: 24 | M10: 15 | N10: 5 | O10: 0 | P10: 0.14444444 | Q10: 1653.9356
A11: Kuldip Yadav | B11: CSK | C11: Pacer | D11: 0.3 | E11: 0 | F11: 0 | G11: 0 | H11: 0 | I11: 0 | J11: 0 | K11: 0 | L11: 0 | M11: 0 | N11: 0 | O11: 0 | P11: 0 | Q11: 0
A12: Noor Ahmad | B12: CSK | C12: Spinner | D12: 0 | E12: 14 | F12: 11 | G12: 23 | H12: 3.66 | I12: 47.82 | J12: 0 | K12: 0 | L12: 0 | M12: 1 | N12: 1 | O12: 0 | P12: 0.090909091 | Q12: 1.9252332
A13: Mukesh Choudhary | B13: CSK | C13: Pacer | D13: 0 | E13: 0 | F13: 0 | G13: 0 | H13: 0 | I13: 0 | J13: 0 | K13: 0 | L13: 0 | M13: 0 | N13: 0 | O13: 0 | P13: 0 | Q13: 0
A14: Spencer Johnson | B14: CSK | C14: Pacer | D14: 1.5 | E14: 0 | F14: 0 | G14: 0 | H14: 0 | I14: 0 | J14: 0 | K14: 0 | L14: 0 | M14: 0 | N14: 0 | O14: 0 | P14: 0 | Q14: 0
A15: Shreyas Gopal | B15: CSK | C15: Spinner | D15: 0 | E15: 0 | F15: 0 | G15: 0 | H15: 0 | I15: 0 | J15: 0 | K15: 0 | L15: 0 | M15: 0 | N15: 0 | O15: 0 | P15: 0 | Q15: 0 | Y15: Row Labels | Z15: Sum of Strike Rate | AA15: Sum of Boundary Percentage
A16: Gurjapneet Singh | B16: CSK | C16: Pacer | D16: 0 | E16: 0 | F16: 0 | G16: 0 | H16: 0 | I16: 0 | J16: 0 | K16: 0 | L16: 0 | M16: 0 | N16: 0 | O16: 0 | P16: 0 | Q16: 0 | Y16: Finn Allen | Z16: 214.11 | AA16: 0.1747851
A17: Virat Kohli | B17: RCB | C17: Anchor | D17: 0 | E17: 16 | F17: 675 | G17: 407 | H17: 56.25 | I17: 165.84 | J17: 1 | K17: 5 | L17: 73 | M17: 25 | N17: 4 | O17: 0 | P17: 0.14518519 | Q17: 6296.7375 | R17: 900 | S17: 24.077511 | T17: 0 | U17: 0 | V17: Virat Kohli_RCB | Y17: Priyansh Arya | Z17: 211.62 | AA17: 0.16208791
A18: Akeal Hosein | B18: CSK | C18: Pacer | D18: 2 | E18: 7 | F18: 5 | G18: 3 | H18: - | I18: 166.66 | J18: 0 | K18: 0 | L18: 0 | M18: 0 | N18: 3 | O18: 0.4 | P18: 0 | Q18: #VALUE! | Y18: Vaibhav Suryavanshi | Z18: 237.3 | AA18: 0.17396907
A19: Prashant Veer | B19: CSK | C19: All-Rounder | D19: 14.2 | E19: 6 | F19: 90 | G19: 67 | H19: 45 | I19: 134.32 | J19: 0 | K19: 0 | L19: 10 | M19: 3 | N19: 3 | O19: 0.15777778 | P19: 0.14444444 | Q19: 543.996 | Y19: Grand Total | Z19: 663.03 | AA19: 0.51084208
A20: Finn Allen | B20: KKR | C20: Wicketkeeper | D20: 2 | E20: 11 | F20: 349 | G20: 163 | H20: 34.9 | I20: 214.11 | J20: 1 | K20: 1 | L20: 33 | M20: 28 | N20: 1 | O20: 0.005730659 | P20: 0.1747851 | Q20: 2607.8812 | R20: 383.9 | S20: 37.423238 | T20: 1303.9406 | U20: 0.0007669061 | V20: Finn Allen_KKR
A21: Matthew Short | B21: CSK | C21: All-Rounder | D21: 1.5 | E21: 3 | F21: 60 | G21: 51 | H21: 20 | I21: 117.64 | J21: 0 | K21: 0 | L21: 6 | M21: 1 | N21: 0 | O21: 0.025 | P21: 0.11666667 | Q21: 141.168
A22: Aman Khan | B22: CSK | C22: All-Rounder | D22: 0.4 | E22: 0 | F22: 0 | G22: 0 | H22: 0 | I22: 0 | J22: 0 | K22: 0 | L22: 0 | M22: 0 | N22: 0 | O22: 0 | P22: 0 | Q22: 0
A23: Shubman Gill | B23: GT | C23: Anchor | D23: 0 | E23: 16 | F23: 732 | G23: 449 | H23: 45.75 | I23: 163.02 | J23: 1 | K23: 6 | L23: 74 | M23: 33 | N23: 0 | O23: 0 | P23: 0.14617486 | Q23: 5459.3768 | R23: 732 | S23: 23.829426 | T23: 0 | U23: 0 | V23: Shubman Gill_GT
A24: Rahul Chahar | B24: CSK | C24: Spinner | D24: 1 | E24: 0 | F24: 0 | G24: 0 | H24: 0 | I24: 0 | J24: 0 | K24: 0 | L24: 0 | M24: 0 | N24: 0 | O24: 0 | P24: 0 | Q24: 0
A25: Matt Henry | B25: CSK | C25: Pacer | D25: 2 | E25: 0 | F25: 0 | G25: 0 | H25: 0 | I25: 0 | J25: 0 | K25: 0 | L25: 0 | M25: 0 | N25: 0 | O25: 0 | P25: 0 | Q25: 0
A26: Zak Foulkes | B26: CSK | C26: All-Rounder | D26: 0.75 | E26: 0 | F26: 0 | G26: 0 | H26: 0 | I26: 0 | J26: 0 | K26: 0 | L26: 0 | M26: 0 | N26: 0 | O26: 0 | P26: 0 | Q26: 0
A27: MS Dhoni | B27: CSK | C27: Wicketkeeper | D27: 0 | E27: 0 | F27: 0 | G27: 0 | H27: 0 | I27: 0 | J27: 0 | K27: 0 | L27: 0 | M27: 0 | N27: 0 | O27: 0 | P27: 0 | Q27: 0 | R27: 0 | S27: 0 | T27: 0 | U27: 0 | V27: MS Dhoni_CSK
A28: B Sai Sudharsan | B28: GT | C28: Anchor | D28: 0 | E28: 17 | F28: 722 | G28: 457 | H28: 45.12 | I28: 157.98 | J28: 1 | K28: 8 | L28: 75 | M28: 30 | N28: 1 | O28: 0 | P28: 0.14542936 | Q28: 5146.4576 | R28: 767.04 | S28: 22.974931 | T28: 0 | U28: 0 | V28: B Sai Sudharsan_GT
A29: Urvil Patel | B29: CSK | C29: Wicketkeeper | D29: 0 | E29: 0 | F29: 0 | G29: 0 | H29: 0 | I29: 0 | J29: 0 | K29: 0 | L29: 0 | M29: 0 | N29: 0 | O29: 0 | P29: 0 | Q29: 0 | R29: 0 | S29: 0 | T29: 0 | U29: 0 | V29: Urvil Patel_CSK
A30: Sanju Samson | B30: CSK | C30: Wicketkeeper | D30: 0 | E30: 14 | F30: 477 | G30: 288 | H30: 43.36 | I30: 165.62 | J30: 2 | K30: 1 | L30: 53 | M30: 24 | N30: 3 | O30: 0 | P30: 0.16142558 | Q30: 3425.4721 | R30: 607.04 | S30: 26.735304 | T30: 0 | U30: 0 | V30: Sanju Samson_CSK
A31: Axar Patel | B31: DC | C31: All-Rounder | D31: 0 | E31: 14 | F31: 173 | G31: 132 | H31: 19.22 | I31: 131.06 | J31: 0 | K31: 1 | L31: 16 | M31: 6 | N31: 2 | O31: 0 | P31: 0.12716763 | Q31: 435.78236
A32: Shreyas Iyer | B32: PBKS | C32: Anchor | D32: 0 | E32: 14 | F32: 498 | G32: 295 | H32: 55.33 | I32: 168.81 | J32: 1 | K32: 5 | L32: 39 | M32: 30 | N32: 4 | O32: 0 | P32: 0.13855422 | Q32: 4651.4481 | R32: 774.62 | S32: 23.389337 | T32: 0 | U32: 0 | V32: Shreyas Iyer_PBKS
A33: KL Rahul | B33: DC | C33: Wicketkeeper | D33: 0 | E33: 14 | F33: 593 | G33: 340 | H33: 45.61 | I33: 174.41 | J33: 1 | K33: 5 | L33: 56 | M33: 31 | N33: 1 | O33: 0 | P33: 0.14671164 | Q33: 4717.2202 | R33: 638.54 | S33: 25.587976 | T33: 0 | U33: 0 | V33: KL Rahul_DC
A34: Vipraj Nigam | B34: DC | C34: All-Rounder | D34: 0 | E34: 5 | F34: 15 | G34: 10 | H34: 15 | I34: 150 | J34: 0 | K34: 0 | L34: 2 | M34: 0 | N34: 1 | O34: 0 | P34: 0.13333333 | Q34: 33.75
A35: Ajay Mandal | B35: DC | C35: All-Rounder | D35: 0 | E35: 0 | F35: 0 | G35: 0 | H35: 0 | I35: 0 | J35: 0 | K35: 0 | L35: 0 | M35: 0 | N35: 0 | O35: 0 | P35: 0 | Q35: 0
A36: Tripurana Vijay | B36: DC | C36: All-Rounder | D36: 0 | E36: 0 | F36: 0 | G36: 0 | H36: 0 | I36: 0 | J36: 0 | K36: 0 | L36: 0 | M36: 0 | N36: 0 | O36: 0 | P36: 0 | Q36: 0
A37: Madhav Tiwari | B37: DC | C37: All-Rounder | D37: 0 | E37: 0 | F37: 0 | G37: 0 | H37: 0 | I37: 0 | J37: 0 | K37: 0 | L37: 0 | M37: 0 | N37: 0 | O37: 0 | P37: 0 | Q37: 0
A38: Mitchell Starc | B38: DC | C38: Pacer | D38: 0 | E38: 0 | F38: 0 | G38: 0 | H38: 0 | I38: 0 | J38: 0 | K38: 0 | L38: 0 | M38: 0 | N38: 0 | O38: 0 | P38: 0 | Q38: 0
A39: T Natarajan | B39: DC | C39: Pacer | D39: 0 | E39: 0 | F39: 0 | G39: 0 | H39: 0 | I39: 0 | J39: 0 | K39: 0 | L39: 0 | M39: 0 | N39: 0 | O39: 0 | P39: 0 | Q39: 0
A40: Mukesh Kumar | B40: DC | C40: Pacer | D40: 0 | E40: 0 | F40: 0 | G40: 0 | H40: 0 | I40: 0 | J40: 0 | K40: 0 | L40: 0 | M40: 0 | N40: 0 | O40: 0 | P40: 0 | Q40: 0
A41: Dushmantha Chameera | B41: DC | C41: Pacer | D41: 0 | E41: 0 | F41: 0 | G41: 0 | H41: 0 | I41: 0 | J41: 0 | K41: 0 | L41: 0 | M41: 0 | N41: 0 | O41: 0 | P41: 0 | Q41: 0
A42: Kuldeep Yadav | B42: DC | C42: Spinner | D42: 0 | E42: 12 | F42: 9 | G42: 21 | H42: 3 | I42: 42.85 | J42: 0 | K42: 0 | L42: 0 | M42: 0 | N42: 1 | O42: 0 | P42: 0 | Q42: 1.15695
A43: Rajat Patidar | B43: RCB | C43: Anchor | D43: 0 | E43: 15 | F43: 501 | G43: 260 | H43: 41.75 | I43: 192.69 | J43: 0 | K43: 5 | L43: 30 | M43: 42 | N43: 2 | O43: 0 | P43: 0.14371257 | Q43: 4030.4486 | R43: 626.25 | S43: 27.691976 | T43: 0 | U43: 0 | V43: Rajat Patidar_RCB
A44: Auqib Nabi | B44: DC | C44: All-Rounder | D44: 8.4 | E44: 0 | F44: 0 | G44: 0 | H44: 0 | I44: 0 | J44: 0 | K44: 0 | L44: 0 | M44: 0 | N44: 0 | O44: 0 | P44: 0 | Q44: 0
A45: Rehan Ahmed | B45: DC | C45: Pacer | D45: 0.75 | E45: 0 | F45: 0 | G45: 0 | H45: 0 | I45: 0 | J45: 0 | K45: 0 | L45: 0 | M45: 0 | N45: 0 | O45: 0 | P45: 0 | Q45: 0
A46: Abishek Porel | B46: DC | C46: Wicketkeeper | D46: 0 | E46: 4 | F46: 108 | G46: 88 | H46: 27 | I46: 122.72 | J46: 0 | K46: 1 | L46: 15 | M46: 1 | N46: 0 | O46: 0 | P46: 0.14814815 | Q46: 357.85152 | R46: 108 | S46: 18.180741 | T46: 0 | U46: 0 | V46: Abishek Porel_DC
A47: Mitchell Marsh | B47: LSG | C47: Anchor | D47: 0 | E47: 13 | F47: 563 | G47: 345 | H47: 43.3 | I47: 163.18 | J47: 1 | K47: 3 | L47: 51 | M47: 36 | N47: 0 | O47: 0 | P47: 0.15452931 | Q47: 3977.9857 | R47: 562.9 | S47: 25.216092 | T47: 0 | U47: 0 | V47: Mitchell Marsh_LSG
A48: Lungi Ngidi | B48: DC | C48: Pacer | D48: 2 | E48: 0 | F48: 0 | G48: 0 | H48: 0 | I48: 0 | J48: 0 | K48: 0 | L48: 0 | M48: 0 | N48: 0 | O48: 0 | P48: 0 | Q48: 0
A49: Angkrish Raghuvanshi | B49: KKR | C49: Anchor | D49: 0 | E49: 13 | F49: 422 | G49: 288 | H49: 42.2 | I49: 146.52 | J49: 0 | K49: 5 | L49: 40 | M49: 19 | N49: 2 | O49: 0 | P49: 0.13981043 | Q49: 2609.2868 | R49: 548.6 | S49: 20.485024 | T49: 0 | U49: 0 | V49: Angkrish Raghuvanshi_KKR
A50: Rinku Singh | B50: KKR | C50: Anchor | D50: 0 | E50: 14 | F50: 295 | G50: 198 | H50: 59 | I50: 148.98 | J50: 0 | K50: 2 | L50: 27 | M50: 11 | N50: 6 | O50: 0 | P50: 0.12881356 | Q50: 2592.9969 | R50: 826 | S50: 19.190644 | T50: 0 | U50: 0 | V50: Rinku Singh_KKR
A51: Kyle Jamieson | B51: DC | C51: Pacer | D51: 2 | E51: 0 | F51: 0 | G51: 0 | H51: 0 | I51: 0 | J51: 0 | K51: 0 | L51: 0 | M51: 0 | N51: 0 | O51: 0 | P51: 0 | Q51: 0
A52: Yashasvi Jaiswal | B52: RR | C52: Anchor | D52: 0 | E52: 16 | F52: 427 | G52: 280 | H52: 30.5 | I52: 152.5 | J52: 0 | K52: 3 | L52: 52 | M52: 18 | N52: 2 | O52: 0 | P52: 0.16393443 | Q52: 1986.0838 | R52: 488 | S52: 25 | T52: 0 | U52: 0 | V52: Yashasvi Jaiswal_RR
A53: Travis Head | B53: SRH | C53: Anchor | D53: 0 | E53: 15 | F53: 410 | G53: 241 | H53: 27.33 | I53: 170.12 | J53: 0 | K53: 2 | L53: 46 | M53: 23 | N53: 0 | O53: 0 | P53: 0.16829268 | Q53: 1906.2456 | R53: 409.95 | S53: 28.629951 | T53: 0 | U53: 0 | V53: Travis Head_SRH
A54: Rohit Sharma | B54: MI | C54: Anchor | D54: 0 | E54: 9 | F54: 283 | G54: 180 | H54: 35.37 | I54: 157.22 | J54: 0 | K54: 2 | L54: 21 | M54: 21 | N54: 1 | O54: 0 | P54: 0.14840989 | Q54: 1573.7266 | R54: 318.33 | S54: 23.333004 | T54: 0 | U54: 0 | V54: Rohit Sharma_MI
A55: Tilak Varma | B55: MI | C55: Anchor | D55: 0 | E55: 14 | F55: 359 | G55: 246 | H55: 29.91 | I55: 145.93 | J55: 1 | K55: 2 | L55: 30 | M55: 17 | N55: 2 | O55: 0 | P55: 0.13091922 | Q55: 1566.9511 | R55: 418.74 | S55: 19.105042 | T55: 0 | U55: 0 | V55: Tilak Varma_MI
A56: Sameer Rizvi | B56: DC | C56: Anchor | D56: 0 | E56: 11 | F56: 252 | G56: 171 | H56: 36 | I56: 147.36 | J56: 0 | K56: 2 | L56: 15 | M56: 17 | N56: 2 | O56: 0 | P56: 0.12698413 | Q56: 1336.8499 | R56: 396 | S56: 18.712381 | T56: 0 | U56: 0 | V56: Sameer Rizvi_DC
A57: Nishant Sindhu | B57: GT | C57: All-Rounder | D57: 0 | E57: 0 | F57: 0 | G57: 0 | H57: 0 | I57: 0 | J57: 0 | K57: 0 | L57: 0 | M57: 0 | N57: 0 | O57: 0 | P57: 0 | Q57: 0
A58: Glenn Phillips | B58: GT | C58: All-Rounder | D58: 0 | E58: 0 | F58: 0 | G58: 0 | H58: 0 | I58: 0 | J58: 0 | K58: 0 | L58: 0 | M58: 0 | N58: 0 | O58: 0 | P58: 0 | Q58: 0
A59: Washington Sundar | B59: GT | C59: All-Rounder | D59: 0 | E59: 17 | F59: 377 | G59: 251 | H59: 37.7 | I59: 150.19 | J59: 0 | K59: 3 | L59: 40 | M59: 12 | N59: 6 | O59: 0 | P59: 0.13793103 | Q59: 2134.6355
A60: Arshad Khan | B60: GT | C60: Pacer | D60: 0 | E60: 8 | F60: 23 | G60: 11 | H60: 23 | I60: 209.09 | J60: 0 | K60: 0 | L60: 1 | M60: 2 | N60: 1 | O60: 0 | P60: 0.13043478 | Q60: 110.60861
A61: Pathum Nissanka | B61: DC | C61: Anchor | D61: 4 | E61: 10 | F61: 278 | G61: 175 | H61: 27.8 | I61: 158.85 | J61: 0 | K61: 2 | L61: 33 | M61: 12 | N61: 0 | O61: 0.014388489 | P61: 0.1618705 | Q61: 1227.6563 | R61: 278 | S61: 25.713129 | T61: 306.91409 | U61: 0.0032582408 | V61: Pathum Nissanka_DC
A62: Rahul Tewatia | B62: GT | C62: All-Rounder | D62: 0 | E62: 16 | F62: 190 | G62: 132 | H62: 27.14 | I62: 143.93 | J62: 0 | K62: 1 | L62: 20 | M62: 8 | N62: 8 | O62: 0 | P62: 0.14736842 | Q62: 742.18944
A63: Kagiso Rabada | B63: GT | C63: Pacer | D63: 0 | E63: 17 | F63: 47 | G63: 38 | H63: 23.5 | I63: 123.68 | J63: 0 | K63: 0 | L63: 5 | M63: 2 | N63: 2 | O63: 0 | P63: 0.14893617 | Q63: 136.60456
A64: Mohammed Siraj | B64: GT | C64: Pacer | D64: 0 | E64: 17 | F64: 5 | G64: 16 | H64: 2.5 | I64: 31.25 | J64: 0 | K64: 0 | L64: 1 | M64: 0 | N64: 0 | O64: 0 | P64: 0.2 | Q64: 0.390625
A65: Prasidh Krishna | B65: GT | C65: Pacer | D65: 0 | E65: 12 | F65: 6 | G65: 7 | H65: - | I65: 85.71 | J65: 0 | K65: 0 | L65: 1 | M65: 0 | N65: 1 | O65: 0 | P65: 0.16666667 | Q65: #VALUE!
A66: Ishant Sharma | B66: GT | C66: Pacer | D66: 0 | E66: 0 | F66: 0 | G66: 0 | H66: 0 | I66: 0 | J66: 0 | K66: 0 | L66: 0 | M66: 0 | N66: 0 | O66: 0 | P66: 0 | Q66: 0
A67: Gurnoor Brar | B67: GT | C67: Pacer | D67: 0 | E67: 0 | F67: 0 | G67: 0 | H67: 0 | I67: 0 | J67: 0 | K67: 0 | L67: 0 | M67: 0 | N67: 0 | O67: 0 | P67: 0 | Q67: 0
A68: Rashid Khan | B68: GT | C68: Spinner | D68: 0 | E68: 17 | F68: 50 | G68: 41 | H68: 12.5 | I68: 121.95 | J68: 0 | K68: 0 | L68: 4 | M68: 2 | N68: 2 | O68: 0 | P68: 0.12 | Q68: 76.21875
A69: Manav Suthar | B69: GT | C69: Spinner | D69: 0 | E69: 0 | F69: 0 | G69: 0 | H69: 0 | I69: 0 | J69: 0 | K69: 0 | L69: 0 | M69: 0 | N69: 0 | O69: 0 | P69: 0 | Q69: 0
A70: Sai Kishore | B70: GT | C70: Spinner | D70: 0 | E70: 0 | F70: 0 | G70: 0 | H70: 0 | I70: 0 | J70: 0 | K70: 0 | L70: 0 | M70: 0 | N70: 0 | O70: 0 | P70: 0 | Q70: 0
A71: Jayant Yadav | B71: GT | C71: Spinner | D71: 0 | E71: 0 | F71: 0 | G71: 0 | H71: 0 | I71: 0 | J71: 0 | K71: 0 | L71: 0 | M71: 0 | N71: 0 | O71: 0 | P71: 0 | Q71: 0
A72: Ashok Sharma | B72: GT | C72: Pacer | D72: 0.9 | E72: 0 | F72: 0 | G72: 0 | H72: 0 | I72: 0 | J72: 0 | K72: 0 | L72: 0 | M72: 0 | N72: 0 | O72: 0 | P72: 0 | Q72: 0
A73: Jason Holder | B73: GT | C73: All-Rounder | D73: 7 | E73: 0 | F73: 0 | G73: 0 | H73: 0 | I73: 0 | J73: 0 | K73: 0 | L73: 0 | M73: 0 | N73: 0 | O73: 0 | P73: 0 | Q73: 0
A74: Kumar Kushagra | B74: GT | C74: Wicketkeeper | D74: 0 | E74: 1 | F74: 18 | G74: 14 | H74: 18 | I74: 128.57 | J74: 0 | K74: 0 | L74: 3 | M74: 0 | N74: 0 | O74: 0 | P74: 0.16666667 | Q74: 41.65668 | R74: 18 | S74: 21.428333 | T74: 0 | U74: 0 | V74: Kumar Kushagra_GT
A75: Luke Wood | B75: GT | C75: Pacer | D75: 0.75 | E75: 0 | F75: 0 | G75: 0 | H75: 0 | I75: 0 | J75: 0 | K75: 0 | L75: 0 | M75: 0 | N75: 0 | O75: 0 | P75: 0 | Q75: 0
A76: Kulwant Khejroliya | B76: GT | C76: Pacer | D76: 0.3 | E76: 0 | F76: 0 | G76: 0 | H76: 0 | I76: 0 | J76: 0 | K76: 0 | L76: 0 | M76: 0 | N76: 0 | O76: 0 | P76: 0 | Q76: 0
A77: Anuj Rawat | B77: GT | C77: Wicketkeeper | D77: 0 | E77: 0 | F77: 0 | G77: 0 | H77: 0 | I77: 0 | J77: 0 | K77: 0 | L77: 0 | M77: 0 | N77: 0 | O77: 0 | P77: 0 | Q77: 0 | R77: 0 | S77: 0 | T77: 0 | U77: 0 | V77: Anuj Rawat_GT
A78: Jos Buttler | B78: GT | C78: Wicketkeeper | D78: 0 | E78: 17 | F78: 526 | G78: 345 | H78: 37.57 | I78: 152.46 | J78: 0 | K78: 4 | L78: 51 | M78: 26 | N78: 3 | O78: 0 | P78: 0.14638783 | Q78: 3012.8871 | R78: 638.69 | S78: 22.318289 | T78: 0 | U78: 0 | V78: Jos Buttler_GT
A79: Tristan Stubbs | B79: DC | C79: Anchor | D79: 0 | E79: 14 | F79: 275 | G79: 216 | H79: 34.37 | I79: 127.31 | J79: 0 | K79: 2 | L79: 18 | M79: 9 | N79: 5 | O79: 0 | P79: 0.098181818 | Q79: 1203.3023 | R79: 481.18 | S79: 12.499527 | T79: 0 | U79: 0 | V79: Tristan Stubbs_DC
A80: Connor Esterhuizen | B80: GT | C80: Wicketkeeper | D80: 0.75 | E80: 0 | F80: 0 | G80: 0 | H80: 0 | I80: 0 | J80: 0 | K80: 0 | L80: 0 | M80: 0 | N80: 0 | O80: 0 | P80: 0 | Q80: 0 | R80: 0 | S80: 0 | T80: 0 | U80: 0 | V80: Connor Esterhuizen_GT
A81: Rovman Powell | B81: KKR | C81: All-Rounder | D81: 0 | E81: 0 | F81: 0 | G81: 0 | H81: 0 | I81: 0 | J81: 0 | K81: 0 | L81: 0 | M81: 0 | N81: 0 | O81: 0 | P81: 0 | Q81: 0
A82: Anukul Roy | B82: KKR | C82: All-Rounder | D82: 0 | E82: 0 | F82: 0 | G82: 0 | H82: 0 | I82: 0 | J82: 0 | K82: 0 | L82: 0 | M82: 0 | N82: 0 | O82: 0 | P82: 0 | Q82: 0
A83: Ruturaj Gaikwad | B83: CSK | C83: Anchor | D83: 0 | E83: 14 | F83: 337 | G83: 273 | H83: 28.08 | I83: 123.44 | J83: 0 | K83: 2 | L83: 29 | M83: 12 | N83: 2 | O83: 0 | P83: 0.12166172 | Q83: 1168.1078 | R83: 393.12 | S83: 15.017923 | T83: 0 | U83: 0 | V83: Ruturaj Gaikwad_CSK
A84: Vaibhav Arora | B84: KKR | C84: Pacer | D84: 0 | E84: 0 | F84: 0 | G84: 0 | H84: 0 | I84: 0 | J84: 0 | K84: 0 | L84: 0 | M84: 0 | N84: 0 | O84: 0 | P84: 0 | Q84: 0
A85: Sunil Narine | B85: KKR | C85: All-Rounder | D85: 0 | E85: 13 | F85: 40 | G85: 32 | H85: 13.33 | I85: 125 | J85: 0 | K85: 0 | L85: 2 | M85: 4 | N85: 1 | O85: 0 | P85: 0.15 | Q85: 66.65
A86: Varun Chakravarthy | B86: KKR | C86: Spinner | D86: 0 | E86: 0 | F86: 0 | G86: 0 | H86: 0 | I86: 0 | J86: 0 | K86: 0 | L86: 0 | M86: 0 | N86: 0 | O86: 0 | P86: 0 | Q86: 0
A87: Navdeep Saini | B87: KKR | C87: Pacer | D87: 0.75 | E87: 0 | F87: 0 | G87: 0 | H87: 0 | I87: 0 | J87: 0 | K87: 0 | L87: 0 | M87: 0 | N87: 0 | O87: 0 | P87: 0 | Q87: 0
A88: Umran Malik | B88: KKR | C88: Pacer | D88: 0 | E88: 0 | F88: 0 | G88: 0 | H88: 0 | I88: 0 | J88: 0 | K88: 0 | L88: 0 | M88: 0 | N88: 0 | O88: 0 | P88: 0 | Q88: 0
A89: Cameron Green | B89: KKR | C89: All-Rounder | D89: 25.2 | E89: 0 | F89: 0 | G89: 0 | H89: 0 | I89: 0 | J89: 0 | K89: 0 | L89: 0 | M89: 0 | N89: 0 | O89: 0 | P89: 0 | Q89: 0
A90: Ajinkya Rahane | B90: KKR | C90: Anchor | D90: 0 | E90: 14 | F90: 335 | G90: 248 | H90: 25.76 | I90: 135.08 | J90: 0 | K90: 2 | L90: 25 | M90: 18 | N90: 1 | O90: 0 | P90: 0.12835821 | Q90: 1165.6864 | R90: 360.64 | S90: 17.338627 | T90: 0 | U90: 0 | V90: Ajinkya Rahane_KKR
A91: Riyan Parag | B91: RR | C91: Anchor | D91: 0 | E91: 14 | F91: 309 | G91: 196 | H91: 23.76 | I91: 157.65 | J91: 0 | K91: 2 | L91: 24 | M91: 21 | N91: 1 | O91: 0 | P91: 0.14563107 | Q91: 1157.4411 | R91: 332.64 | S91: 22.958738 | T91: 0 | U91: 0 | V91: Riyan Parag_RR
A92: Suryakumar Yadav | B92: MI | C92: Anchor | D92: 0 | E92: 13 | F92: 270 | G92: 183 | H92: 20.76 | I92: 147.54 | J92: 0 | K92: 2 | L92: 28 | M92: 10 | N92: 0 | O92: 0 | P92: 0.14074074 | Q92: 826.99121 | R92: 269.88 | S92: 20.764889 | T92: 0 | U92: 0 | V92: Suryakumar Yadav_MI
A93: Prashant Solanki | B93: KKR | C93: Pacer | D93: 0.3 | E93: 0 | F93: 0 | G93: 0 | H93: 0 | I93: 0 | J93: 0 | K93: 0 | L93: 0 | M93: 0 | N93: 0 | O93: 0 | P93: 0 | Q93: 0
A94: Kartik Tyagi | B94: KKR | C94: Pacer | D94: 0.3 | E94: 14 | F94: 11 | G94: 10 | H94: 3.66 | I94: 110 | J94: 0 | K94: 0 | L94: 1 | M94: 1 | N94: 0 | O94: 0.027272727 | P94: 0.18181818 | Q94: 4.4286
A95: Aiden Markram | B95: LSG | C95: Anchor | D95: 0 | E95: 12 | F95: 231 | G95: 167 | H95: 25.66 | I95: 138.32 | J95: 0 | K95: 0 | L95: 20 | M95: 11 | N95: 2 | O95: 0 | P95: 0.13419913 | Q95: 819.88627 | R95: 307.92 | S95: 18.562424 | T95: 0 | U95: 0 | V95: Aiden Markram_LSG
A96: Luvnith Sisodia | B96: KKR | C96: Wicketkeeper | D96: 0.3 | E96: 0 | F96: 0 | G96: 0 | H96: 0 | I96: 0 | J96: 0 | K96: 0 | L96: 0 | M96: 0 | N96: 0 | O96: 0 | P96: 0 | Q96: 0 | R96: 0 | S96: 0 | T96: 0 | U96: 0 | V96: Luvnith Sisodia_KKR
A97: Sarthak Ranjan | B97: KKR | C97: All-Rounder | D97: 0.3 | E97: 0 | F97: 0 | G97: 0 | H97: 0 | I97: 0 | J97: 0 | K97: 0 | L97: 0 | M97: 0 | N97: 0 | O97: 0 | P97: 0 | Q97: 0
A98: Daksh Kamra | B98: KKR | C98: All-Rounder | D98: 0.3 | E98: 0 | F98: 0 | G98: 0 | H98: 0 | I98: 0 | J98: 0 | K98: 0 | L98: 0 | M98: 0 | N98: 0 | O98: 0 | P98: 0 | Q98: 0
A99: Saurabh Dubey | B99: KKR | C99: Pacer | D99: 0.3 | E99: 0 | F99: 0 | G99: 0 | H99: 0 | I99: 0 | J99: 0 | K99: 0 | L99: 0 | M99: 0 | N99: 0 | O99: 0 | P99: 0 | Q99: 0
A100: Rachin Ravindra | B100: KKR | C100: All-Rounder | D100: 2 | E100: 0 | F100: 0 | G100: 0 | H100: 0 | I100: 0 | J100: 0 | K100: 0 | L100: 0 | M100: 0 | N100: 0 | O100: 0 | P100: 0 | Q100: 0
...

Sheet Master_Bowler_Analysis
A1: Player | B1: Team | C1: Role | D1: Bowling Matches | E1: Overs | F1: Runs Conceded | G1: Wickets | H1: Economy | I1: Maidens | J1: Bowling Average | K1: Cost Per Wicket | L1: Bowling Impact | M1: Wicket Efficiency | N1: Control Score | O1: Maiden Rate | P1: Adjusted Bowling Score | Q1: Final Professional Bowling Score | R1: key
A2: Ruturaj Gaikwad | B2: CSK | C2: Anchor | D2: 0 | E2: 0 | F2: 0 | G2: 0 | H2: 0 | I2: 0 | J2: 0 | K2: 0 | Q2: 0
A3: MS Dhoni | B3: CSK | C3: Wicketkeeper | D3: 0 | E3: 0 | F3: 0 | G3: 0 | H3: 0 | I3: 0 | J3: 0 | K3: 0 | Q3: 0
A4: Dewald Brevis | B4: CSK | C4: Anchor | D4: 0 | E4: 0 | F4: 0 | G4: 0 | H4: 0 | I4: 0 | J4: 0 | K4: 0 | Q4: 0 | U4: Row Labels | V4: Sum of Bowling Average
A5: Akash Madhwal | B5: CSK | C5: Pacer | D5: 0 | E5: 0 | F5: 0 | G5: 0 | H5: 0 | I5: 0 | J5: 0 | K5: 0 | L5: 0 | M5: 0 | N5: 0 | O5: 0 | P5: 0 | Q5: 0 | R5: Akash Madhwal_CSK | U5: Jasprit Bumrah | V5: 102.5
A6: Urvil Patel | B6: CSK | C6: Wicketkeeper | D6: 0 | E6: 0 | F6: 0 | G6: 0 | H6: 0 | I6: 0 | J6: 0 | K6: 0 | Q6: 0 | U6: Raghu Sharma | V6: 130
A7: Anshul Kamboj | B7: CSK | C7: All-Rounder | D7: 14 | E7: 50.2 | F7: 530 | G7: 21 | H7: 10.52 | I7: 0 | J7: 25.23 | K7: 25.238095 | Q7: 79.73 | U7: Trent Boult | V7: 94
A8: Dian Forrester | B8: CSK | C8: All-Rounder | D8: 0 | E8: 0 | F8: 0 | G8: 0 | H8: 0 | I8: 0 | J8: 0 | K8: 0 | Q8: 0 | U8: Grand Total | V8: 326.5
A9: Macneil Noronha | B9: CSK | C9: All-Rounder | D9: 0 | E9: 0 | F9: 0 | G9: 0 | H9: 0 | I9: 0 | J9: 0 | K9: 0 | Q9: 0
A10: Shivam Dube | B10: CSK | C10: All-Rounder | D10: 0 | E10: 0 | F10: 0 | G10: 0 | H10: 0 | I10: 0 | J10: 0 | K10: 0 | Q10: 0
A11: Kuldip Yadav | B11: CSK | C11: Pacer | D11: 0 | E11: 0 | F11: 0 | G11: 0 | H11: 0 | I11: 0 | J11: 0 | K11: 0 | L11: 0 | M11: 0 | N11: 0 | O11: 0 | P11: 0 | Q11: 0 | R11: Kuldip Yadav_CSK
A12: Noor Ahmad | B12: CSK | C12: Spinner | D12: 14 | E12: 51 | F12: 428 | G12: 13 | H12: 8.39 | I12: 0 | J12: 32.92 | K12: 32.923077 | L12: 0 | M12: 0 | N12: 0 | O12: 0 | P12: 0 | Q12: 28.3 | R12: Noor Ahmad_CSK
A13: Mukesh Choudhary | B13: CSK | C13: Pacer | D13: 8 | E13: 28 | F13: 249 | G13: 8 | H13: 8.89 | I13: 0 | J13: 31.12 | K13: 31.125 | L13: 0 | M13: 0 | N13: 0 | O13: 0 | P13: 0 | Q13: -0.9 | R13: Mukesh Choudhary_CSK | U13: Row Labels | V13: Sum of Final Professional Bowling Score
A14: Spencer Johnson | B14: CSK | C14: Pacer | D14: 0 | E14: 0 | F14: 0 | G14: 0 | H14: 0 | I14: 0 | J14: 0 | K14: 0 | L14: 0 | M14: 0 | N14: 0 | O14: 0 | P14: 0 | Q14: 0 | R14: Spencer Johnson_CSK | U14: Bhuvneshwar Kumar | V14: 136.32834
A15: Shreyas Gopal | B15: CSK | C15: Spinner | D15: 0 | E15: 0 | F15: 0 | G15: 0 | H15: 0 | I15: 0 | J15: 0 | K15: 0 | L15: 3.3131835 | M15: 0.92857143 | N15: 0.11918951 | O15: 0 | P15: 66.99 | Q15: 4.0718542 | R15: Shreyas Gopal_CSK | U15: Jofra Archer | V15: 109.02
A16: Gurjapneet Singh | B16: CSK | C16: Pacer | D16: 8 | E16: 25.1 | F16: 233 | G16: 4 | H16: 9.25 | I16: 0 | J16: 58.25 | K16: 58.25 | L16: 2.285347 | M16: 1 | N16: 0.11248594 | O16: 0 | P16: 7.09 | Q16: -48.412542 | R16: Gurjapneet Singh_CSK | U16: Kagiso Rabada | V16: 136.36242
A17: Sanju Samson | B17: CSK | C17: Wicketkeeper | D17: 0 | E17: 0 | F17: 0 | G17: 0 | H17: 0 | I17: 0 | J17: 0 | K17: 0 | Q17: 0 | U17: Grand Total | V17: 381.71076
A18: Akeal Hosein | B18: CSK | C18: Pacer | D18: 7 | E18: 24.4 | F18: 198 | G18: 8 | H18: 8.02 | I18: 1 | J18: 24.75 | K18: 24.75 | L18: 0 | M18: 0 | N18: 0 | O18: 0 | P18: 0 | Q18: 7.21 | R18: Akeal Hosein_CSK
A19: Prashant Veer | B19: CSK | C19: All-Rounder | D19: 0 | E19: 0 | F19: 0 | G19: 0 | H19: 0 | I19: 0 | J19: 0 | K19: 0 | Q19: 0
A20: Kartik Sharma | B20: CSK | C20: Wicketkeeper | D20: 0 | E20: 0 | F20: 0 | G20: 0 | H20: 0 | I20: 0 | J20: 0 | K20: 0 | Q20: 0
A21: Matthew Short | B21: CSK | C21: All-Rounder | D21: 0 | E21: 0 | F21: 0 | G21: 0 | H21: 0 | I21: 0 | J21: 0 | K21: 0 | Q21: 0
A22: Aman Khan | B22: CSK | C22: All-Rounder | D22: 0 | E22: 0 | F22: 0 | G22: 0 | H22: 0 | I22: 0 | J22: 0 | K22: 0 | Q22: 0
A23: Sarfaraz Khan | B23: CSK | C23: Anchor | D23: 0 | E23: 0 | F23: 0 | G23: 0 | H23: 0 | I23: 0 | J23: 0 | K23: 0 | Q23: 0
A24: Rahul Chahar | B24: CSK | C24: Spinner | D24: 0 | E24: 0 | F24: 0 | G24: 0 | H24: 0 | I24: 0 | J24: 0 | K24: 0 | L24: 0 | M24: 0 | N24: 0 | O24: 0 | P24: 0 | Q24: 0 | R24: Rahul Chahar_CSK
A25: Matt Henry | B25: CSK | C25: Pacer | D25: 3 | E25: 10 | F25: 130 | G25: 2 | H25: 13 | I25: 0 | J25: 65 | K25: 65 | L25: 0 | M25: 0 | N25: 0 | O25: 0 | P25: 0 | Q25: -79 | R25: Matt Henry_CSK
A26: Zak Foulkes | B26: CSK | C26: All-Rounder | D26: 0 | E26: 0 | F26: 0 | G26: 0 | H26: 0 | I26: 0 | J26: 0 | K26: 0 | Q26: 0
A27: KL Rahul | B27: DC | C27: Wicketkeeper | D27: 0 | E27: 0 | F27: 0 | G27: 0 | H27: 0 | I27: 0 | J27: 0 | K27: 0 | Q27: 0
A28: Karun Nair | B28: DC | C28: Anchor | D28: 0 | E28: 0 | F28: 0 | G28: 0 | H28: 0 | I28: 0 | J28: 0 | K28: 0 | Q28: 0
A29: Abishek Porel | B29: DC | C29: Wicketkeeper | D29: 0 | E29: 0 | F29: 0 | G29: 0 | H29: 0 | I29: 0 | J29: 0 | K29: 0 | Q29: 0
A30: Tristan Stubbs | B30: DC | C30: Anchor | D30: 0 | E30: 0 | F30: 0 | G30: 0 | H30: 0 | I30: 0 | J30: 0 | K30: 0 | Q30: 0
A31: Axar Patel | B31: DC | C31: All-Rounder | D31: 14 | E31: 44 | F31: 360 | G31: 11 | H31: 8.18 | I31: 0 | J31: 32.72 | K31: 32.727273 | Q31: 16.92
A32: Sameer Rizvi | B32: DC | C32: Anchor | D32: 0 | E32: 0 | F32: 0 | G32: 0 | H32: 0 | I32: 0 | J32: 0 | K32: 0 | Q32: 0
A33: Ashutosh Sharma | B33: DC | C33: Anchor | D33: 0 | E33: 0 | F33: 0 | G33: 0 | H33: 0 | I33: 0 | J33: 0 | K33: 0 | Q33: 0
A34: Vipraj Nigam | B34: DC | C34: All-Rounder | D34: 5 | E34: 9 | F34: 113 | G34: 2 | H34: 12.55 | I34: 0 | J34: 56.5 | K34: 56.5 | Q34: -69.6
A35: Ajay Mandal | B35: DC | C35: All-Rounder | D35: 0 | E35: 0 | F35: 0 | G35: 0 | H35: 0 | I35: 0 | J35: 0 | K35: 0 | Q35: 0
A36: Tripurana Vijay | B36: DC | C36: All-Rounder | D36: 0 | E36: 0 | F36: 0 | G36: 0 | H36: 0 | I36: 0 | J36: 0 | K36: 0 | Q36: 0
A37: Madhav Tiwari | B37: DC | C37: All-Rounder | D37: 3 | E37: 10 | F37: 87 | G37: 4 | H37: 8.7 | I37: 0 | J37: 21.75 | K37: 21.75 | Q37: -15.15
A38: Mitchell Starc | B38: DC | C38: Pacer | D38: 6 | E38: 22 | F38: 224 | G38: 11 | H38: 10.18 | I38: 0 | J38: 20.36 | K38: 20.363636 | L38: 0 | M38: 0 | N38: 0 | O38: 0 | P38: 0 | Q38: 25.28 | R38: Mitchell Starc_DC
A39: T Natarajan | B39: DC | C39: Pacer | D39: 10 | E39: 31.5 | F39: 356 | G39: 5 | H39: 11.18 | I39: 0 | J39: 71.2 | K39: 71.2 | L39: 0 | M39: 0 | N39: 0 | O39: 0 | P39: 0 | Q39: -63.56 | R39: T Natarajan_DC
A40: Mukesh Kumar | B40: DC | C40: Pacer | D40: 10 | E40: 31.2 | F40: 353 | G40: 6 | H40: 11.26 | I40: 0 | J40: 58.83 | K40: 58.833333 | L40: 1.6 | M40: 1.3333333 | N40: 0.11494253 | O40: 0 | P40: -23.6 | Q40: -39.671839 | R40: Mukesh Kumar_DC
A41: Dushmantha Chameera | B41: DC | C41: Pacer | D41: 0 | E41: 0 | F41: 0 | G41: 0 | H41: 0 | I41: 0 | J41: 0 | K41: 0 | L41: 5.5 | M41: 1.8333333 | N41: 0.098231827 | O41: 0 | P41: 50.74 | Q41: 7.6280288 | R41: Dushmantha Chameera_DC
A42: Kuldeep Yadav | B42: DC | C42: Spinner | D42: 12 | E42: 37 | F42: 381 | G42: 10 | H42: 10.29 | I42: 0 | J42: 38.1 | K42: 38.1 | L42: 0.78511236 | M42: 0.5 | N42: 0.089445438 | O42: 0 | P42: -105.94 | Q42: 3.5883363 | R42: Kuldeep Yadav_DC
A43: Nitish Rana | B43: DC | C43: Anchor | D43: 0 | E43: 0 | F43: 0 | G43: 0 | H43: 0 | I43: 0 | J43: 0 | K43: 0 | Q43: 0
A44: Auqib Nabi | B44: DC | C44: All-Rounder | D44: 0 | E44: 0 | F44: 0 | G44: 0 | H44: 0 | I44: 0 | J44: 0 | K44: 0 | Q44: 0
A45: Rehan Ahmed | B45: DC | C45: Pacer | D45: 0 | E45: 0 | F45: 0 | G45: 0 | H45: 0 | I45: 0 | J45: 0 | K45: 0 | L45: 2.7007874 | M45: 0.83333333 | N45: 0.09718173 | O45: 0 | P45: 16.93 | Q45: 3.6248785 | R45: Rehan Ahmed_DC
A46: David Miller | B46: DC | C46: Anchor | D46: 0 | E46: 0 | F46: 0 | G46: 0 | H46: 0 | I46: 0 | J46: 0 | K46: 0 | Q46: 0
A47: Pathum Nissanka | B47: DC | C47: Anchor | D47: 0 | E47: 0 | F47: 0 | G47: 0 | H47: 0 | I47: 0 | J47: 0 | K47: 0 | Q47: 0
A48: Lungi Ngidi | B48: DC | C48: Pacer | D48: 12 | E48: 41.2 | F48: 340 | G48: 13 | H48: 8.22 | I48: 0 | J48: 26.15 | K48: 26.153846 | L48: 0 | M48: 0 | N48: 0 | O48: 0 | P48: 0 | Q48: 35.41 | R48: Lungi Ngidi_DC
A49: Sahil Parakh | B49: DC | C49: Anchor | D49: 0 | E49: 0 | F49: 0 | G49: 0 | H49: 0 | I49: 0 | J49: 0 | K49: 0 | Q49: 0
A50: Prithvi Shaw | B50: DC | C50: Anchor | D50: 0 | E50: 0 | F50: 0 | G50: 0 | H50: 0 | I50: 0 | J50: 0 | K50: 0 | Q50: 0
A51: Kyle Jamieson | B51: DC | C51: Pacer | D51: 2 | E51: 7 | F51: 90 | G51: 2 | H51: 12.85 | I51: 0 | J51: 45 | K51: 45 | L51: 4.0864245 | M51: 1.0833333 | N51: 0.1216545 | O51: 0 | P51: 77.04 | Q51: -54.001703 | R51: Kyle Jamieson_DC
A52: Shubman Gill | B52: GT | C52: Anchor | D52: 0 | E52: 0 | F52: 0 | G52: 0 | H52: 0 | I52: 0 | J52: 0 | K52: 0 | Q52: 0
A53: B Sai Sudharsan | B53: GT | C53: Anchor | D53: 0 | E53: 0 | F53: 0 | G53: 0 | H53: 0 | I53: 0 | J53: 0 | K53: 0 | Q53: 0
A54: Kumar Kushagra | B54: GT | C54: Wicketkeeper | D54: 0 | E54: 0 | F54: 0 | G54: 0 | H54: 0 | I54: 0 | J54: 0 | K54: 0 | Q54: 0
A55: Anuj Rawat | B55: GT | C55: Wicketkeeper | D55: 0 | E55: 0 | F55: 0 | G55: 0 | H55: 0 | I55: 0 | J55: 0 | K55: 0 | Q55: 0
A56: Jos Buttler | B56: GT | C56: Wicketkeeper | D56: 0 | E56: 0 | F56: 0 | G56: 0 | H56: 0 | I56: 0 | J56: 0 | K56: 0 | Q56: 0
A57: Nishant Sindhu | B57: GT | C57: All-Rounder | D57: 0 | E57: 0 | F57: 0 | G57: 0 | H57: 0 | I57: 0 | J57: 0 | K57: 0 | Q57: 0
A58: Glenn Phillips | B58: GT | C58: All-Rounder | D58: 0 | E58: 0 | F58: 0 | G58: 0 | H58: 0 | I58: 0 | J58: 0 | K58: 0 | Q58: 0
A59: Washington Sundar | B59: GT | C59: All-Rounder | D59: 17 | E59: 9.1 | F59: 84 | G59: 1 | H59: 9.16 | I59: 0 | J59: 84 | K59: 84 | Q59: -96.32
A60: Arshad Khan | B60: GT | C60: Pacer | D60: 8 | E60: 17.2 | F60: 172 | G60: 6 | H60: 9.92 | I60: 0 | J60: 28.66 | K60: 28.666667 | L60: 0 | M60: 0 | N60: 0 | O60: 0 | P60: 0 | Q60: -12.5 | R60: Arshad Khan_GT
A61: M Shahrukh Khan | B61: GT | C61: Anchor | D61: 0 | E61: 0 | F61: 0 | G61: 0 | H61: 0 | I61: 0 | J61: 0 | K61: 0 | Q61: 0
A62: Rahul Tewatia | B62: GT | C62: All-Rounder | D62: 0 | E62: 0 | F62: 0 | G62: 0 | H62: 0 | I62: 0 | J62: 0 | K62: 0 | Q62: 0
A63: Kagiso Rabada | B63: GT | C63: Pacer | D63: 17 | E63: 64.4 | F63: 626 | G63: 29 | H63: 9.68 | I63: 1 | J63: 21.58 | K63: 21.586207 | L63: 2.076762 | M63: 0.75 | N63: 0.10080645 | O63: 0 | P63: -11.08 | Q63: 136.36242 | R63: Kagiso Rabada_GT
A64: Mohammed Siraj | B64: GT | C64: Pacer | D64: 17 | E64: 62 | F64: 562 | G64: 19 | H64: 9.06 | I64: 1 | J64: 29.57 | K64: 29.578947 | L64: 0 | M64: 0 | N64: 0 | O64: 0 | P64: 0 | Q64: 66.31 | R64: Mohammed Siraj_GT
A65: Prasidh Krishna | B65: GT | C65: Pacer | D65: 12 | E65: 39 | F65: 407 | G65: 16 | H65: 10.43 | I65: 0 | J65: 25.43 | K65: 25.4375 | L65: 0 | M65: 0 | N65: 0 | O65: 0 | P65: 0 | Q65: 49.71 | R65: Prasidh Krishna_GT
A66: Ishant Sharma | B66: GT | C66: Pacer | D66: 0 | E66: 0 | F66: 0 | G66: 0 | H66: 0 | I66: 0 | J66: 0 | K66: 0 | L66: 13.008341 | M66: 1.7058824 | N66: 0.10330579 | O66: 0.058823529 | P66: 251.8 | Q66: 7.2510938 | R66: Ishant Sharma_GT
A67: Gurnoor Brar | B67: GT | C67: Pacer | D67: 0 | E67: 0 | F67: 0 | G67: 0 | H67: 0 | I67: 0 | J67: 0 | K67: 0 | L67: 5.8214406 | M67: 1.1176471 | N67: 0.11037528 | O67: 0.058823529 | P67: 137.68 | Q67: 4.9193611 | R67: Gurnoor Brar_GT
A68: Rashid Khan | B68: GT | C68: Spinner | D68: 17 | E68: 56.5 | F68: 516 | G68: 21 | H68: 9.07 | I68: 0 | J68: 24.57 | K68: 24.571429 | L68: 6.562328 | M68: 1.3333333 | N68: 0.095877277 | O68: 0 | P68: 101.85 | Q68: 88.910965 | R68: Rashid Khan_GT
A69: Manav Suthar | B69: GT | C69: Spinner | D69: 4 | E69: 6 | F69: 68 | G69: 2 | H69: 11.33 | I69: 0 | J69: 34 | K69: 34 | L69: 0 | M69: 0 | N69: 0 | O69: 0 | P69: 0 | Q69: -44.66 | R69: Manav Suthar_GT
A70: Sai Kishore | B70: GT | C70: Spinner | D70: 0 | E70: 0 | F70: 0 | G70: 0 | H70: 0 | I70: 0 | J70: 0 | K70: 0 | L70: 0 | M70: 0 | N70: 0 | O70: 0 | P70: 0 | Q70: 0 | R70: Sai Kishore_GT
A71: Jayant Yadav | B71: GT | C71: Spinner | D71: 0 | E71: 0 | F71: 0 | G71: 0 | H71: 0 | I71: 0 | J71: 0 | K71: 0 | L71: 7.7521368 | M71: 1.2352941 | N71: 0.11025358 | O71: 0 | P71: 167.65 | Q71: 5.2719372 | R71: Jayant Yadav_GT
A72: Ashok Sharma | B72: GT | C72: Pacer | D72: 6 | E72: 21 | F72: 228 | G72: 6 | H72: 10.85 | I72: 0 | J72: 38 | K72: 38 | L72: 0.66647059 | M72: 0.5 | N72: 0.088261253 | O72: 0 | P72: -73.99 | Q72: -21.435216 | R72: Ashok Sharma_GT
A73: Jason Holder | B73: GT | C73: All-Rounder | D73: 11 | E73: 38.2 | F73: 290 | G73: 17 | H73: 7.56 | I73: 0 | J73: 17.05 | K73: 17.058824 | Q73: 69.83
A74: Connor Esterhuizen | B74: GT | C74: Wicketkeeper | D74: 0 | E74: 0 | F74: 0 | G74: 0 | H74: 0 | I74: 0 | J74: 0 | K74: 0 | Q74: 0
A75: Luke Wood | B75: GT | C75: Pacer | D75: 0 | E75: 0 | F75: 0 | G75: 0 | H75: 0 | I75: 0 | J75: 0 | K75: 0 | L75: 1.7131579 | M75: 1 | N75: 0.092165899 | O75: 0 | P75: -36.55 | Q75: 4.2764977 | R75: Luke Wood_GT
A76: Kulwant Khejroliya | B76: GT | C76: Pacer | D76: 0 | E76: 0 | F76: 0 | G76: 0 | H76: 0 | I76: 0 | J76: 0 | K76: 0 | L76: 7.5378299 | M76: 1.5454545 | N76: 0.13227513 | O76: 0 | P76: 135.22 | Q76: 6.5786436 | R76: Kulwant Khejroliya_GT
A77: Ajinkya Rahane | B77: KKR | C77: Anchor | D77: 0 | E77: 0 | F77: 0 | G77: 0 | H77: 0 | I77: 0 | J77: 0 | K77: 0 | Q77: 0
A78: Rinku Singh | B78: KKR | C78: Anchor | D78: 0 | E78: 0 | F78: 0 | G78: 0 | H78: 0 | I78: 0 | J78: 0 | K78: 0 | Q78: 0
A79: Angkrish Raghuvanshi | B79: KKR | C79: Anchor | D79: 0 | E79: 0 | F79: 0 | G79: 0 | H79: 0 | I79: 0 | J79: 0 | K79: 0 | Q79: 0
A80: Manish Pandey | B80: KKR | C80: Anchor | D80: 0 | E80: 0 | F80: 0 | G80: 0 | H80: 0 | I80: 0 | J80: 0 | K80: 0 | Q80: 0
A81: Rovman Powell | B81: KKR | C81: All-Rounder | D81: 0 | E81: 0 | F81: 0 | G81: 0 | H81: 0 | I81: 0 | J81: 0 | K81: 0 | Q81: 0
A82: Anukul Roy | B82: KKR | C82: All-Rounder | D82: 0 | E82: 0 | F82: 0 | G82: 0 | H82: 0 | I82: 0 | J82: 0 | K82: 0 | Q82: 0
A83: Ramandeep Singh | B83: KKR | C83: Anchor | D83: 8 | E83: 2.4 | F83: 31 | G83: 1 | H83: 11.62 | I83: 0 | J83: 31 | K83: 31 | Q83: -48.24
A84: Vaibhav Arora | B84: KKR | C84: Pacer | D84: 11 | E84: 38 | F84: 390 | G84: 11 | H84: 10.26 | I84: 0 | J84: 35.45 | K84: 35.454545 | L84: 0 | M84: 0 | N84: 0 | O84: 0 | P84: 0 | Q84: 10.03 | R84: Vaibhav Arora_KKR
A85: Sunil Narine | B85: KKR | C85: All-Rounder | D85: 13 | E85: 51 | F85: 339 | G85: 15 | H85: 6.64 | I85: 0 | J85: 22.6 | K85: 22.6 | Q85: 54.12
A86: Varun Chakravarthy | B86: KKR | C86: Spinner | D86: 11 | E86: 41 | F86: 360 | G86: 11 | H86: 8.78 | I86: 0 | J86: 32.72 | K86: 32.727273 | L86: 0.37483871 | M86: 0.125 | N86: 0.08605852 | O86: 0 | P86: -70.86 | Q86: 16.478176 | R86: Varun Chakravarthy_KKR
A87: Navdeep Saini | B87: KKR | C87: Pacer | D87: 0 | E87: 0 | F87: 0 | G87: 0 | H87: 0 | I87: 0 | J87: 0 | K87: 0 | L87: 3.1836389 | M87: 1 | N87: 0.097465887 | O87: 0 | P87: 30.32 | Q87: 4.2923977 | R87: Navdeep Saini_KKR
A88: Umran Malik | B88: KKR | C88: Pacer | D88: 0 | E88: 0 | F88: 0 | G88: 0 | H88: 0 | I88: 0 | J88: 0 | K88: 0 | L88: 4.4070796 | M88: 1.1538462 | N88: 0.15060241 | O88: 0 | P88: 110.88 | Q88: 5.0671918 | R88: Umran Malik_KKR
A89: Cameron Green | B89: KKR | C89: All-Rounder | D89: 14 | E89: 22 | F89: 234 | G89: 7 | H89: 10.63 | I89: 0 | J89: 33.42 | K89: 33.428571 | Q89: -12.68
A90: Luvnith Sisodia | B90: KKR | C90: Wicketkeeper | D90: 0 | E90: 0 | F90: 0 | G90: 0 | H90: 0 | I90: 0 | J90: 0 | K90: 0 | Q90: 0
A91: Finn Allen | B91: KKR | C91: Wicketkeeper | D91: 0 | E91: 0 | F91: 0 | G91: 0 | H91: 0 | I91: 0 | J91: 0 | K91: 0 | Q91: 0
A92: Tejasvi Dahiya | B92: KKR | C92: Wicketkeeper | D92: 0 | E92: 0 | F92: 0 | G92: 0 | H92: 0 | I92: 0 | J92: 0 | K92: 0 | Q92: 0
A93: Prashant Solanki | B93: KKR | C93: Pacer | D93: 0 | E93: 0 | F93: 0 | G93: 0 | H93: 0 | I93: 0 | J93: 0 | K93: 0 | L93: 0 | M93: 0 | N93: 0 | O93: 0 | P93: 0 | Q93: 0 | R93: Prashant Solanki_KKR
A94: Kartik Tyagi | B94: KKR | C94: Pacer | D94: 14 | E94: 51 | F94: 498 | G94: 18 | H94: 9.76 | I94: 0 | J94: 27.66 | K94: 27.666667 | L94: 0 | M94: 0 | N94: 0 | O94: 0 | P94: 0 | Q94: 60.82 | R94: Kartik Tyagi_KKR
A95: Rahul Tripathi | B95: KKR | C95: Anchor | D95: 0 | E95: 0 | F95: 0 | G95: 0 | H95: 0 | I95: 0 | J95: 0 | K95: 0 | Q95: 0
A96: Tim Seifert | B96: KKR | C96: Wicketkeeper | D96: 0 | E96: 0 | F96: 0 | G96: 0 | H96: 0 | I96: 0 | J96: 0 | K96: 0 | Q96: 0
A97: Sarthak Ranjan | B97: KKR | C97: All-Rounder | D97: 0 | E97: 0 | F97: 0 | G97: 0 | H97: 0 | I97: 0 | J97: 0 | K97: 0 | Q97: 0
A98: Daksh Kamra | B98: KKR | C98: All-Rounder | D98: 0 | E98: 0 | F98: 0 | G98: 0 | H98: 0 | I98: 0 | J98: 0 | K98: 0 | Q98: 0
A99: Saurabh Dubey | B99: KKR | C99: Pacer | D99: 0 | E99: 0 | F99: 0 | G99: 0 | H99: 0 | I99: 0 | J99: 0 | K99: 0 | L99: 0 | M99: 0 | N99: 0 | O99: 0 | P99: 0 | Q99: 0 | R99: Saurabh Dubey_KKR
A100: Rachin Ravindra | B100: KKR | C100: All-Rounder | D100: 0 | E100: 0 | F100: 0 | G100: 0 | H100: 0 | I100: 0 | J100: 0 | K100: 0 | Q100: 0
...

Sheet Master_AllRounder_Analysis
A1: Player | B1: Team | C1: Role | D1: Batting Matches | E1: Runs | F1: Balls | G1: Bat Avg | H1: Strike Rate | I1: 4s | J1: 6s | K1: Bowling Matches | L1: Overs | M1: Runs Conceded | N1: Wickets | O1: Economy | P1: Maidens | Q1: Bowling Avg | R1: Batting Impact | S1: Bowling Impact
A2: Ruturaj Gaikwad | B2: CSK | C2: Anchor | D2: 14 | E2: 337 | F2: 273 | G2: 28.08 | H2: 123.44 | I2: 29 | J2: 12 | K2: 0 | L2: 0 | M2: 0 | N2: 0 | O2: 0 | P2: 0 | Q2: 0 | R2: 1168.1078 | S2: 0
A3: MS Dhoni | B3: CSK | C3: Wicketkeeper | D3: 0 | E3: 0 | F3: 0 | G3: 0 | H3: 0 | I3: 0 | J3: 0 | K3: 0 | L3: 0 | M3: 0 | N3: 0 | O3: 0 | P3: 0 | Q3: 0 | R3: 0 | S3: 0
A4: Dewald Brevis | B4: CSK | C4: Anchor | D4: 11 | E4: 151 | F4: 118 | G4: 18.87 | H4: 127.96 | I4: 8 | J4: 10 | K4: 0 | L4: 0 | M4: 0 | N4: 0 | O4: 0 | P4: 0 | Q4: 0 | R4: 364.60539 | S4: 0
A5: Akash Madhwal | B5: CSK | C5: Pacer | D5: 0 | E5: 0 | F5: 0 | G5: 0 | H5: 0 | I5: 0 | J5: 0 | K5: 0 | L5: 0 | M5: 0 | N5: 0 | O5: 0 | P5: 0 | Q5: 0 | R5: 0 | S5: 0
A6: Urvil Patel | B6: CSK | C6: Wicketkeeper | D6: 7 | E6: 129 | F6: 64 | G6: 18.42 | H6: 201.56 | I6: 6 | J6: 14 | K6: 0 | L6: 0 | M6: 0 | N6: 0 | O6: 0 | P6: 0 | Q6: 0 | R6: 478.94284 | S6: 0 | V6: Role | W6: (All)
A7: Anshul Kamboj | B7: CSK | C7: All-Rounder | D7: 14 | E7: 58 | F7: 38 | G7: 29 | H7: 152.63 | I7: 3 | J7: 4 | K7: 14 | L7: 50.2 | M7: 530 | N7: 21 | O7: 10.52 | P7: 0 | Q7: 25.23 | R7: 256.72366 | S7: 8.7562426
A8: Dian Forrester | B8: CSK | C8: All-Rounder | D8: 0 | E8: 0 | F8: 0 | G8: 0 | H8: 0 | I8: 0 | J8: 0 | K8: 0 | L8: 0 | M8: 0 | N8: 0 | O8: 0 | P8: 0 | Q8: 0 | R8: 0 | S8: 0 | V8: Row Labels | W8: Sum of Batting Impact | X8: Sum of Bowling Impact
A9: Macneil Noronha | B9: CSK | C9: All-Rounder | D9: 0 | E9: 0 | F9: 0 | G9: 0 | H9: 0 | I9: 0 | J9: 0 | K9: 0 | L9: 0 | M9: 0 | N9: 0 | O9: 0 | P9: 0 | Q9: 0 | R9: 0 | S9: 0 | V9: Shubman Gill | W9: 5459.3768 | X9: 0
A10: Shivam Dube | B10: CSK | C10: All-Rounder | D10: 13 | E10: 270 | F10: 170 | G10: 38.57 | H10: 158.82 | I10: 24 | J10: 15 | K10: 0 | L10: 0 | M10: 0 | N10: 0 | O10: 0 | P10: 0 | Q10: 0 | R10: 1653.9356 | S10: 0 | V10: Vaibhav Suryavanshi | W10: 8931.0228 | X10: 0
A11: Kuldip Yadav | B11: CSK | C11: Pacer | D11: 0 | E11: 0 | F11: 0 | G11: 0 | H11: 0 | I11: 0 | J11: 0 | K11: 0 | L11: 0 | M11: 0 | N11: 0 | O11: 0 | P11: 0 | Q11: 0 | R11: 0 | S11: 0 | V11: Virat Kohli | W11: 6296.7375 | X11: 0
A12: Noor Ahmad | B12: CSK | C12: Spinner | D12: 14 | E12: 11 | F12: 23 | G12: 3.66 | H12: 47.82 | I12: 0 | J12: 1 | K12: 14 | L12: 51 | M12: 428 | N12: 13 | O12: 8.39 | P12: 0 | Q12: 32.92 | R12: 1.9252332 | S12: 3.3131835 | V12: Grand Total | W12: 20687.137 | X12: 0
A13: Mukesh Choudhary | B13: CSK | C13: Pacer | D13: 0 | E13: 0 | F13: 0 | G13: 0 | H13: 0 | I13: 0 | J13: 0 | K13: 8 | L13: 28 | M13: 249 | N13: 8 | O13: 8.89 | P13: 0 | Q13: 31.12 | R13: 0 | S13: 2.285347
A14: Spencer Johnson | B14: CSK | C14: Pacer | D14: 0 | E14: 0 | F14: 0 | G14: 0 | H14: 0 | I14: 0 | J14: 0 | K14: 0 | L14: 0 | M14: 0 | N14: 0 | O14: 0 | P14: 0 | Q14: 0 | R14: 0 | S14: 0
A15: Shreyas Gopal | B15: CSK | C15: Spinner | D15: 0 | E15: 0 | F15: 0 | G15: 0 | H15: 0 | I15: 0 | J15: 0 | K15: 0 | L15: 0 | M15: 0 | N15: 0 | O15: 0 | P15: 0 | Q15: 0 | R15: 0 | S15: 0
A16: Gurjapneet Singh | B16: CSK | C16: Pacer | D16: 0 | E16: 0 | F16: 0 | G16: 0 | H16: 0 | I16: 0 | J16: 0 | K16: 8 | L16: 25.1 | M16: 233 | N16: 4 | O16: 9.25 | P16: 0 | Q16: 58.25 | R16: 0 | S16: 0.63519313
A17: Sanju Samson | B17: CSK | C17: Wicketkeeper | D17: 14 | E17: 477 | F17: 288 | G17: 43.36 | H17: 165.62 | I17: 53 | J17: 24 | K17: 0 | L17: 0 | M17: 0 | N17: 0 | O17: 0 | P17: 0 | Q17: 0 | R17: 3425.4721 | S17: 0
A18: Akeal Hosein | B18: CSK | C18: Pacer | D18: 7 | E18: 5 | F18: 3 | G18: - | H18: 166.66 | I18: 0 | J18: 0 | K18: 7 | L18: 24.4 | M18: 198 | N18: 8 | O18: 8.02 | P18: 1 | Q18: 24.75 | R18: #VALUE! | S18: 2.5923232
A19: Prashant Veer | B19: CSK | C19: All-Rounder | D19: 6 | E19: 90 | F19: 67 | G19: 45 | H19: 134.32 | I19: 10 | J19: 3 | K19: 0 | L19: 0 | M19: 0 | N19: 0 | O19: 0 | P19: 0 | Q19: 0 | R19: 543.996 | S19: 0
A20: Kartik Sharma | B20: CSK | C20: Wicketkeeper | D20: 11 | E20: 295 | F20: 216 | G20: 32.77 | H20: 136.57 | I20: 24 | J20: 16 | K20: 0 | L20: 0 | M20: 0 | N20: 0 | O20: 0 | P20: 0 | Q20: 0 | R20: 1320.2427 | S20: 0
A21: Matthew Short | B21: CSK | C21: All-Rounder | D21: 3 | E21: 60 | F21: 51 | G21: 20 | H21: 117.64 | I21: 6 | J21: 1 | K21: 0 | L21: 0 | M21: 0 | N21: 0 | O21: 0 | P21: 0 | Q21: 0 | R21: 141.168 | S21: 0
A22: Aman Khan | B22: CSK | C22: All-Rounder | D22: 0 | E22: 0 | F22: 0 | G22: 0 | H22: 0 | I22: 0 | J22: 0 | K22: 0 | L22: 0 | M22: 0 | N22: 0 | O22: 0 | P22: 0 | Q22: 0 | R22: 0 | S22: 0
A23: Sarfaraz Khan | B23: CSK | C23: Anchor | D23: 0 | E23: 0 | F23: 0 | G23: 0 | H23: 0 | I23: 0 | J23: 0 | K23: 0 | L23: 0 | M23: 0 | N23: 0 | O23: 0 | P23: 0 | Q23: 0 | R23: 0 | S23: 0
A24: Rahul Chahar | B24: CSK | C24: Spinner | D24: 0 | E24: 0 | F24: 0 | G24: 0 | H24: 0 | I24: 0 | J24: 0 | K24: 0 | L24: 0 | M24: 0 | N24: 0 | O24: 0 | P24: 0 | Q24: 0 | R24: 0 | S24: 0
A25: Matt Henry | B25: CSK | C25: Pacer | D25: 3 | E25: 7 | F25: 10 | G25: 3.5 | H25: 70 | I25: 1 | J25: 0 | K25: 3 | L25: 10 | M25: 130 | N25: 2 | O25: 13 | P25: 0 | Q25: 65 | R25: 1.715 | S25: 0.4
A26: Zak Foulkes | B26: CSK | C26: All-Rounder | D26: 0 | E26: 0 | F26: 0 | G26: 0 | H26: 0 | I26: 0 | J26: 0 | K26: 0 | L26: 0 | M26: 0 | N26: 0 | O26: 0 | P26: 0 | Q26: 0 | R26: 0 | S26: 0
A27: KL Rahul | B27: DC | C27: Wicketkeeper | D27: 14 | E27: 593 | F27: 340 | G27: 45.61 | H27: 174.41 | I27: 56 | J27: 31 | K27: 0 | L27: 0 | M27: 0 | N27: 0 | O27: 0 | P27: 0 | Q27: 0 | R27: 4717.2202 | S27: 0
A28: Karun Nair | B28: DC | C28: Anchor | D28: 2 | E28: 18 | F28: 18 | G28: 9 | H28: 100 | I28: 3 | J28: 0 | K28: 0 | L28: 0 | M28: 0 | N28: 0 | O28: 0 | P28: 0 | Q28: 0 | R28: 16.2 | S28: 0
A29: Abishek Porel | B29: DC | C29: Wicketkeeper | D29: 4 | E29: 108 | F29: 88 | G29: 27 | H29: 122.72 | I29: 15 | J29: 1 | K29: 0 | L29: 0 | M29: 0 | N29: 0 | O29: 0 | P29: 0 | Q29: 0 | R29: 357.85152 | S29: 0
A30: Tristan Stubbs | B30: DC | C30: Anchor | D30: 14 | E30: 275 | F30: 216 | G30: 34.37 | H30: 127.31 | I30: 18 | J30: 9 | K30: 0 | L30: 0 | M30: 0 | N30: 0 | O30: 0 | P30: 0 | Q30: 0 | R30: 1203.3023 | S30: 0
... A36: Tripurana Vijay | B36: DC | C36: All-Rounder | D36: 0 | E36: 0 | F36: 0 | G36: 0 | H36: 0 | I36: 0 | J36: 0 | K36: 0 | L36: 0 | M36: 0 | N36: 0 | O36: 0 | P36: 0 | Q36: 0 | R36: 0 | S36: 0
A37: Madhav Tiwari | B37: DC | C37: All-Rounder | D37: 3 | E37: 18 | F37: 8 | G37: - | H37: 225 | I37: 2 | J37: 1 | K37: 3 | L37: 10 | M37: 87 | N37: 4 | O37: 8.7 | P37: 0 | Q37: 21.75 | R37: #VALUE! | S37: 1.6
A38: Mitchell Starc | B38: DC | C38: Pacer | D38: 0 | E38: 0 | F38: 0 | G38: 0 | H38: 0 | I38: 0 | J38: 0 | K38: 6 | L38: 22 | M38: 224 | N38: 11 | O38: 10.18 | P38: 0 | Q38: 20.36 | R38: 0 | S38: 5.5
A39: T Natarajan | B39: DC | C39: Pacer | D39: 0 | E39: 0 | F39: 0 | G39: 0 | H39: 0 | I39: 0 | J39: 0 | K39: 10 | L39: 31.5 | M39: 356 | N39: 5 | O39: 11.18 | P39: 0 | Q39: 71.2 | R39: 0 | S39: 0.78511236
A40: Mukesh Kumar | B40: DC | C40: Pacer | D40: 0 | E40: 0 | F40: 0 | G40: 0 | H40: 0 | I40: 0 | J40: 0 | K40: 10 | L40: 31.2 | M40: 353 | N40: 6 | O40: 11.26 | P40: 0 | Q40: 58.83 | R40: 0 | S40: 1.1483937
A41: Dushmantha Chameera | B41: DC | C41: Pacer | D41: 0 | E41: 0 | F41: 0 | G41: 0 | H41: 0 | I41: 0 | J41: 0 | K41: 0 | L41: 0 | M41: 0 | N41: 0 | O41: 0 | P41: 0 | Q41: 0 | R41: 0 | S41: 0
A42: Kuldeep Yadav | B42: DC | C42: Spinner | D42: 12 | E42: 9 | F42: 21 | G42: 3 | H42: 42.85 | I42: 0 | J42: 0 | K42: 12 | L42: 37 | M42: 381 | N42: 10 | O42: 10.29 | P42: 0 | Q42: 38.1 | R42: 1.15695 | S42: 2.7007874
A43: Nitish Rana | B43: DC | C43: Anchor | D43: 9 | E43: 225 | F43: 149 | G43: 25 | H43: 151 | I43: 27 | J43: 10 | K43: 0 | L43: 0 | M43: 0 | N43: 0 | O43: 0 | P43: 0 | Q43: 0 | R43: 849.375 | S43: 0
A44: Auqib Nabi | B44: DC | C44: All-Rounder | D44: 5 | E44: 14 | F44: 4 | G44: 14 | H44: 350 | I44: 2 | J44: 1 | K44: 0 | L44: 0 | M44: 0 | N44: 0 | O44: 0 | P44: 0 | Q44: 0 | R44: 68.6 | S44: 0
A45: Rehan Ahmed | B45: DC | C45: Pacer | D45: 0 | E45: 0 | F45: 0 | G45: 0 | H45: 0 | I45: 0 | J45: 0 | K45: 0 | L45: 0 | M45: 0 | N45: 0 | O45: 0 | P45: 0 | Q45: 0 | R45: 0 | S45: 0
A46: David Miller | B46: DC | C46: Anchor | D46: 11 | E46: 211 | F46: 137 | G46: 35.16 | H46: 154.01 | I46: 15 | J46: 14 | K46: 0 | L46: 0 | M46: 0 | N46: 0 | O46: 0 | P46: 0 | Q46: 0 | R46: 1142.5632 | S46: 0
A47: Pathum Nissanka | B47: DC | C47: Anchor | D47: 10 | E47: 278 | F47: 175 | G47: 27.8 | H47: 158.85 | I47: 33 | J47: 12 | K47: 0 | L47: 0 | M47: 0 | N47: 0 | O47: 0 | P47: 0 | Q47: 0 | R47: 1227.6563 | S47: 0
A48: Lungi Ngidi | B48: DC | C48: Pacer | D48: 0 | E48: 0 | F48: 0 | G48: 0 | H48: 0 | I48: 0 | J48: 0 | K48: 12 | L48: 41.2 | M48: 340 | N48: 13 | O48: 8.22 | P48: 0 | Q48: 26.15 | R48: 0 | S48: 4.0864245
A49: Sahil Parakh | B49: DC | C49: Anchor | D49: 4 | E49: 46 | F49: 33 | G49: 11.5 | H49: 139.39 | I49: 5 | J49: 2 | K49: 0 | L49: 0 | M49: 0 | N49: 0 | O49: 0 | P49: 0 | Q49: 0 | R49: 73.73731 | S49: 0
... A64: Mohammed Siraj | B64: GT | C64: Pacer | D64: 17 | E64: 5 | F64: 16 | G64: 2.5 | H64: 31.25 | I64: 1 | J64: 0 | K64: 17 | L64: 62 | M64: 562 | N64: 19 | O64: 9.06 | P64: 1 | Q64: 29.57 | R64: 0.390625 | S64: 5.8214406
A65: Prasidh Krishna | B65: GT | C65: Pacer | D65: 12 | E65: 6 | F65: 7 | G65: - | H65: 85.71 | I65: 1 | J65: 0 | K65: 12 | L65: 39 | M65: 407 | N65: 16 | O65: 10.43 | P65: 0 | Q65: 25.43 | R65: #VALUE! | S65: 6.562328
A66: Ishant Sharma | B66: GT | C66: Pacer | D66: 0 | E66: 0 | F66: 0 | G66: 0 | H66: 0 | I66: 0 | J66: 0 | K66: 0 | L66: 0 | M66: 0 | N66: 0 | O66: 0 | P66: 0 | Q66: 0 | R66: 0 | S66: 0
A67: Gurnoor Brar | B67: GT | C67: Pacer | D67: 0 | E67: 0 | F67: 0 | G67: 0 | H67: 0 | I67: 0 | J67: 0 | K67: 0 | L67: 0 | M67: 0 | N67: 0 | O67: 0 | P67: 0 | Q67: 0 | R67: 0 | S67: 0
A68: Rashid Khan | B68: GT | C68: Spinner | D68: 17 | E68: 50 | F68: 41 | G68: 12.5 | H68: 121.95 | I68: 4 | J68: 2 | K68: 17 | L68: 56.5 | M68: 516 | N68: 21 | O68: 9.07 | P68: 0 | Q68: 24.57 | R68: 76.21875 | S68: 7.7521368
A69: Manav Suthar | B69: GT | C69: Spinner | D69: 0 | E69: 0 | F69: 0 | G69: 0 | H69: 0 | I69: 0 | J69: 0 | K69: 4 | L69: 6 | M69: 68 | N69: 2 | O69: 11.33 | P69: 0 | Q69: 34 | R69: 0 | S69: 0.66647059
A70: Sai Kishore | B70: GT | C70: Spinner | D70: 0 | E70: 0 | F70: 0 | G70: 0 | H70: 0 | I70: 0 | J70: 0 | K70: 0 | L70: 0 | M70: 0 | N70: 0 | O70: 0 | P70: 0 | Q70: 0 | R70: 0 | S70: 0
A71: Jayant Yadav | B71: GT | C71: Spinner | D71: 0 | E71: 0 | F71: 0 | G71: 0 | H71: 0 | I71: 0 | J71: 0 | K71: 0 | L71: 0 | M71: 0 | N71: 0 | O71: 0 | P71: 0 | Q71: 0 | R71: 0 | S71: 0
A72: Ashok Sharma | B72: GT | C72: Pacer | D72: 0 | E72: 0 | F72: 0 | G72: 0 | H72: 0 | I72: 0 | J72: 0 | K72: 6 | L72: 21 | M72: 228 | N72: 6 | O72: 10.85 | P72: 0 | Q72: 38 | R72: 0 | S72: 1.7131579
A73: Jason Holder | B73: GT | C73: All-Rounder | D73: 11 | E73: 65 | F73: 52 | G73: 13 | H73: 125 | I73: 3 | J73: 3 | K73: 11 | L73: 38.2 | M73: 290 | N73: 17 | O73: 7.56 | P73: 0 | Q73: 17.05 | R73: 105.625 | S73: 7.5378299
A74: Connor Esterhuizen | B74: GT | C74: Wicketkeeper | D74: 0 | E74: 0 | F74: 0 | G74: 0 | H74: 0 | I74: 0 | J74: 0 | K74: 0 | L74: 0 | M74: 0 | N74: 0 | O74: 0 | P74: 0 | Q74: 0 | R74: 0 | S74: 0
A75: Luke Wood | B75: GT | C75: Pacer | D75: 0 | E75: 0 | F75: 0 | G75: 0 | H75: 0 | I75: 0 | J75: 0 | K75: 0 | L75: 0 | M75: 0 | N75: 0 | O75: 0 | P75: 0 | Q75: 0 | R75: 0 | S75: 0
A76: Kulwant Khejroliya | B76: GT | C76: Pacer | D76: 0 | E76: 0 | F76: 0 | G76: 0 | H76: 0 | I76: 0 | J76: 0 | K76: 0 | L76: 0 | M76: 0 | N76: 0 | O76: 0 | P76: 0 | Q76: 0 | R76: 0 | S76: 0
A77: Ajinkya Rahane | B77: KKR | C77: Anchor | D77: 14 | E77: 335 | F77: 248 | G77: 25.76 | H77: 135.08 | I77: 25 | J77: 18 | K77: 0 | L77: 0 | M77: 0 | N77: 0 | O77: 0 | P77: 0 | Q77: 0 | R77: 1165.6864 | S77: 0
... A118: Akash Singh | B118: LSG | C118: Pacer | D118: 0 | E118: 0 | F118: 0 | G118: 0 | H118: 0 | I118: 0 | J118: 0 | K118: 2 | L118: 7 | M118: 80 | N118: 4 | O118: 11.42 | P118: 0 | Q118: 20 | R118: 0 | S118: 2.284
A119: Arjun Tendulkar | B119: LSG | C119: Spinner | D119: 1 | E119: 5 | F119: 5 | G119: - | H119: 100 | I119: 0 | J119: 0 | K119: 1 | L119: 4 | M119: 36 | N119: 1 | O119: 9 | P119: 0 | Q119: 36 | R119: #VALUE! | S119: 0.25
A120: Mohammed Shami | B120: LSG | C120: Pacer | D120: 13 | E120: 31 | F120: 22 | G120: 6.2 | H120: 140.9 | I120: 2 | J120: 3 | K120: 13 | L120: 51 | M120: 459 | N120: 12 | O120: 9 | P120: 0 | Q120: 38.25 | R120: 27.08098 | S120: 2.8235294
A121: Anrich Nortje | B121: LSG | C121: Pacer | D121: 0 | E121: 0 | F121: 0 | G121: 0 | H121: 0 | I121: 0 | J121: 0 | K121: 0 | L121: 0 | M121: 0 | N121: 0 | O121: 0 | P121: 0 | Q121: 0 | R121: 0 | S121: 0
A122: George Linde | B122: LSG | C122: All-Rounder | D122: 3 | E122: 31 | F122: 21 | G122: 10.33 | H122: 147.61 | I122: 6 | J122: 0 | K122: 3 | L122: 6.1 | M122: 55 | N122: 1 | O122: 8.91 | P122: 0 | Q122: 55 | R122: 47.26915 | S122: 0.162
A123: Mukul Choudhary | B123: LSG | C123: Wicketkeeper | D123: 10 | E123: 170 | F123: 120 | G123: 28.33 | H123: 141.66 | I123: 11 | J123: 12 | K123: 0 | L123: 0 | M123: 0 | N123: 0 | O123: 0 | P123: 0 | Q123: 0 | R123: 682.24873 | S123: 0
A124: Naman Tiwari | B124: LSG | C124: All-Rounder | D124: 0 | E124: 0 | F124: 0 | G124: 0 | H124: 0 | I124: 0 | J124: 0 | K124: 0 | L124: 0 | M124: 0 | N124: 0 | O124: 0 | P124: 0 | Q124: 0 | R124: 0 | S124: 0
A125: Akshat Raghuwanshi | B125: LSG | C125: Anchor | D125: 3 | E125: 29 | F125: 25 | G125: 14.5 | H125: 116 | I125: 1 | J125: 1 | K125: 0 | L125: 0 | M125: 0 | N125: 0 | O125: 0 | P125: 0 | Q125: 0 | R125: 48.778 | S125: 0
A126: Josh Inglis | B126: LSG | C126: Anchor | D126: 5 | E126: 266 | F126: 143 | G126: 53.2 | H126: 186.01 | I126: 32 | J126: 12 | K126: 0 | L126: 0 | M126: 0 | N126: 0 | O126: 0 | P126: 0 | Q126: 0 | R126: 2632.2647 | S126: 0
A127: Rohit Sharma | B127: MI | C127: Anchor | D127: 9 | E127: 283 | F127: 180 | G127: 35.37 | H127: 157.22 | I127: 21 | J127: 21 | K127: 0 | L127: 0 | M127: 0 | N127: 0 | O127: 0 | P127: 0 | Q127: 0 | R127: 1573.7266 | S127: 0
A128: Suryakumar Yadav | B128: MI | C128: Anchor | D128: 13 | E128: 270 | F128: 183 | G128: 20.76 | H128: 147.54 | I128: 28 | J128: 10 | K128: 0 | L128: 0 | M128: 0 | N128: 0 | O128: 0 | P128: 0 | Q128: 0 | R128: 826.99121 | S128: 0
A129: Robin Minz | B129: MI | C129: Wicketkeeper | D129: 2 | E129: 6 | F129: 4 | G129: 6 | H129: 150 | I129: 1 | J129: 0 | K129: 0 | L129: 0 | M129: 0 | N129: 0 | O129: 0 | P129: 0 | Q129: 0 | R129: 5.4 | S129: 0
A130: Ryan Rickelton | B130: MI | C130: Wicketkeeper | D130: 12 | E130: 448 | F130: 240 | G130: 40.72 | H130: 186.66 | I130: 31 | J130: 38 | K130: 0 | L130: 0 | M130: 0 | N130: 0 | O130: 0 | P130: 0 | Q130: 0 | R130: 3405.1562 | S130: 0
A131: Tilak Varma | B131: MI | C131: Anchor | D131: 14 | E131: 359 | F131: 246 | G131: 29.91 | H131: 145.93 | I131: 30 | J131: 17 | K131: 0 | L131: 0 | M131: 0 | N131: 0 | O131: 0 | P131: 0 | Q131: 0 | R131: 1566.9511 | S131: 0
... A153: Nehal Wadhera | B153: PBKS | C153: Anchor | D153: 8 | E153: 65 | F153: 57 | G153: 10.83 | H153: 114.03 | I153: 4 | J153: 4 | K153: 0 | L153: 0 | M153: 0 | N153: 0 | O153: 0 | P153: 0 | Q153: 0 | R153: 80.271418 | S153: 0
A154: Vishnu Vinod | B154: PBKS | C154: Wicketkeeper | D154: 1 | E154: 15 | F154: 8 | G154: - | H154: 187.5 | I154: 1 | J154: 1 | K154: 0 | L154: 0 | M154: 0 | N154: 0 | O154: 0 | P154: 0 | Q154: 0 | R154: #VALUE! | S154: 0
A155: Harnoor Singh | B155: PBKS | C155: Anchor | D155: 0 | E155: 0 | F155: 0 | G155: 0 | H155: 0 | I155: 0 | J155: 0 | K155: 0 | L155: 0 | M155: 0 | N155: 0 | O155: 0 | P155: 0 | Q155: 0 | R155: 0 | S155: 0
A156: Pyla Avinash | B156: PBKS | C156: Anchor | D156: 0 | E156: 0 | F156: 0 | G156: 0 | H156: 0 | I156: 0 | J156: 0 | K156: 0 | L156: 0 | M156: 0 | N156: 0 | O156: 0 | P156: 0 | Q156: 0 | R156: 0 | S156: 0
A157: Prabhsimran Singh | B157: PBKS | C157: Wicketkeeper | D157: 14 | E157: 510 | F157: 302 | G157: 42.5 | H157: 168.87 | I157: 55 | J157: 23 | K157: 0 | L157: 0 | M157: 0 | N157: 0 | O157: 0 | P157: 0 | Q157: 0 | R157: 3660.2573 | S157: 0
A158: Shashank Singh | B158: PBKS | C158: Anchor | D158: 12 | E158: 132 | F158: 70 | G158: 22 | H158: 188.57 | I158: 11 | J158: 8 | K158: 12 | L158: 10 | M158: 88 | N158: 4 | O158: 8.8 | P158: 0 | Q158: 22 | R158: 547.60728 | S158: 1.6
A159: Marcus Stoinis | B159: PBKS | C159: All-Rounder | D159: 13 | E159: 216 | F159: 120 | G159: 36 | H159: 180 | I159: 23 | J159: 11 | K159: 13 | L159: 7.5 | M159: 98 | N159: 2 | O159: 12.51 | P159: 0 | Q159: 49 | R159: 1399.68 | S159: 0.51061224
A160: Harpreet Brar | B160: PBKS | C160: All-Rounder | D160: 2 | E160: 5 | F160: 3 | G160: - | H160: 166.66 | I160: 1 | J160: 0 | K160: 2 | L160: 8 | M160: 60 | N160: 2 | O160: 7.5 | P160: 0 | Q160: 30 | R160: #VALUE! | S160: 0.5
A161: Marco Jansen | B161: PBKS | C161: All-Rounder | D161: 13 | E161: 51 | F161: 45 | G161: 12.75 | H161: 113.33 | I161: 1 | J161: 3 | K161: 13 | L161: 47.2 | M161: 483 | N161: 9 | O161: 10.2 | P161: 0 | Q161: 53.66 | R161: 73.692833 | S161: 1.7107715
A162: Azmatullah Omarzai | B162: PBKS | C162: All-Rounder | D162: 3 | E162: 52 | F162: 27 | G162: 26 | H162: 192.59 | I162: 3 | J162: 5 | K162: 3 | L162: 11 | M162: 103 | N162: 3 | O162: 9.36 | P162: 0 | Q162: 34.33 | R162: 260.38168 | S162: 0.81794349
A163: Priyansh Arya | B163: PBKS | C163: All-Rounder | D163: 13 | E163: 364 | F163: 172 | G163: 28 | H163: 211.62 | I163: 27 | J163: 32 | K163: 0 | L163: 0 | M163: 0 | N163: 0 | O163: 0 | P163: 0 | Q163: 0 | R163: 2156.831 | S163: 0
A164: Musheer Khan | B164: PBKS | C164: All-Rounder | D164: 0 | E164: 0 | F164: 0 | G164: 0 | H164: 0 | I164: 0 | J164: 0 | K164: 0 | L164: 0 | M164: 0 | N164: 0 | O164: 0 | P164: 0 | Q164: 0 | R164: 0 | S164: 0
A165: Suryansh Shedge | B165: PBKS | C165: All-Rounder | D165: 7 | E165: 158 | F165: 90 | G165: 39.5 | H165: 175.55 | I165: 9 | J165: 12 | K165: 0 | L165: 0 | M165: 0 | N165: 0 | O165: 0 | P165: 0 | Q165: 0 | R165: 1095.6075 | S165: 0
A166: Mitchell Owen | B166: PBKS | C166: All-Rounder | D166: 0 | E166: 0 | F166: 0 | G166: 0 | H166: 0 | I166: 0 | J166: 0 | K166: 0 | L166: 0 | M166: 0 | N166: 0 | O166: 0 | P166: 0 | Q166: 0 | R166: 0 | S166: 0
A167: Arshdeep Singh | B167: PBKS | C167: Pacer | D167: 0 | E167: 0 | F167: 0 | G167: 0 | H167: 0 | I167: 0 | J167: 0 | K167: 14 | L167: 53 | M167: 541 | N167: 14 | O167: 10.2 | P167: 0 | Q167: 38.64 | R167: 0 | S167: 3.6956522
A168: Yuzvendra Chahal | B168: PBKS | C168: Spinner | D168: 0 | E168: 0 | F168: 0 | G168: 0 | H168: 0 | I168: 0 | J168: 0 | K168: 14 | L168: 41 | M168: 385 | N168: 12 | O168: 9.39 | P168: 0 | Q168: 32.08 | R168: 0 | S168: 3.5124688
A169: Vijaykumar Vyshak | B169: PBKS | C169: Pacer | D169: 0 | E169: 0 | F169: 0 | G169: 0 | H169: 0 | I169: 0 | J169: 0 | K169: 10 | L169: 31 | M169: 330 | N169: 9 | O169: 10.64 | P169: 0 | Q169: 36.66 | R169: 0 | S169: 2.6121113
A170: Yash Thakur | B170: PBKS | C170: Pacer | D170: 0 | E170: 0 | F170: 0 | G170: 0 | H170: 0 | I170: 0 | J170: 0 | K170: 1 | L170: 4 | M170: 55 | N170: 2 | O170: 13.75 | P170: 0 | Q170: 27.5 | R170: 0 | S170: 1
A171: Xavier Bartlett | B171: PBKS | C171: Pacer | D171: 9 | E171: 29 | F171: 13 | G171: 29 | H171: 223.07 | I171: 2 | J171: 2 | K171: 9 | L171: 33.3 | M171: 388 | N171: 5 | O171: 11.58 | P171: 0 | Q171: 77.6 | R171: 187.60187 | S171: 0.74613402
A172: Lockie Ferguson | B172: PBKS | C172: Pacer | D172: 0 | E172: 0 | F172: 0 | G172: 0 | H172: 0 | I172: 0 | J172: 0 | K172: 0 | L172: 0 | M172: 0 | N172: 0 | O172: 0 | P172: 0 | Q172: 0 | R172: 0 | S172: 0
... A212: Josh Hazlewood | B212: RCB | C212: Pacer | D212: 0 | E212: 0 | F212: 0 | G212: 0 | H212: 0 | I212: 0 | J212: 0 | K212: 13 | L212: 51.3 | M212: 494 | N212: 15 | O212: 9.59 | P212: 0 | Q212: 32.93 | R212: 0 | S212: 4.3683571
A213: Bhuvneshwar Kumar | B213: RCB | C213: Pacer | D213: 16 | E213: 34 | F213: 26 | G213: - | H213: 130.76 | I213: 3 | J213: 1 | K213: 16 | L213: 63 | M213: 501 | N213: 28 | O213: 7.95 | P213: 0 | Q213: 17.89 | R213: #VALUE! | S213: 12.442705
A214: Rasikh Salam | B214: RCB | C214: Pacer | D214: 0 | E214: 0 | F214: 0 | G214: 0 | H214: 0 | I214: 0 | J214: 0 | K214: 12 | L214: 42.5 | M214: 405 | N214: 19 | O214: 9.45 | P214: 1 | Q214: 21.31 | R214: 0 | S214: 8.4256218
A215: Yash Dayal | B215: RCB | C215: Spinner | D215: 0 | E215: 0 | F215: 0 | G215: 0 | H215: 0 | I215: 0 | J215: 0 | K215: 0 | L215: 0 | M215: 0 | N215: 0 | O215: 0 | P215: 0 | Q215: 0 | R215: 0 | S215: 0
A216: Suyash Sharma | B216: RCB | C216: Spinner | D216: 0 | E216: 0 | F216: 0 | G216: 0 | H216: 0 | I216: 0 | J216: 0 | K216: 12 | L216: 40.5 | M216: 376 | N216: 9 | O216: 9.2 | P216: 1 | Q216: 41.77 | R216: 0 | S216: 1.9822839
A217: Richard Gleeson | B217: RCB | C217: Pacer | D217: 0 | E217: 0 | F217: 0 | G217: 0 | H217: 0 | I217: 0 | J217: 0 | K217: 0 | L217: 0 | M217: 0 | N217: 0 | O217: 0 | P217: 0 | Q217: 0 | R217: 0 | S217: 0
A218: Abhinandan Singh | B218: RCB | C218: Pacer | D218: 0 | E218: 0 | F218: 0 | G218: 0 | H218: 0 | I218: 0 | J218: 0 | K218: 3 | L218: 9.4 | M218: 122 | N218: 3 | O218: 12.62 | P218: 0 | Q218: 40.66 | R218: 0 | S218: 0.93113625
A219: Venkatesh Iyer | B219: RCB | C219: All-Rounder | D219: 7 | E219: 209 | F219: 112 | G219: 52.25 | H219: 186.6 | I219: 21 | J219: 13 | K219: 0 | L219: 0 | M219: 0 | N219: 0 | O219: 0 | P219: 0 | Q219: 0 | R219: 2037.7186 | S219: 0
...

Sheet Team_Analytics
A1: Team | B1: Total Squad Cost | C1: Total Runs | D1: Total Wickets | E1: Avg Batting Impact | F1: Avg Bowling Impact | G1: Team Strength Score | H1: Squad Efficiency | I1: Team Rank | J1: Value Grade | K1: Dominance Score | L1: Balance Index | M1: Best Team | N1: Best Value Team | O1: Most Dominant Team | P1: Most Balance Team
A2: MI | B2: 2.75 | C2: 2098 | D2: 61 | E2: 83.92 | F2: 2.44 | G2: 86.36 | H2: 785.09091 | I2: 4 | J2: 1 | K2: 2159 | L2: 81.48 | M2: GT | N2: MI | O2: GT | P2: RCB
A3: GT | B3: 9.7 | C3: 2739 | D3: 100 | E3: 109.56 | F3: 4 | G3: 113.56 | H3: 292.68041 | I3: 1 | J3: 2 | K3: 2839 | L3: 105.56 | M3: GT | N3: MI | O3: GT | P3: RCB
A4: PBKS | B4: 8 | C4: 1799 | D4: 50 | E4: 71.96 | F4: 2 | G4: 73.96 | H4: 231.125 | I4: 6 | J4: 3 | K4: 1849 | L4: 69.96 | M4: GT | N4: MI | O4: GT | P4: RCB
A5: RR | B5: 12.75 | C5: 2027 | D5: 87 | E5: 81.08 | F5: 3.48 | G5: 84.56 | H5: 165.80392 | I5: 5 | J5: 4 | K5: 2114 | L5: 77.6 | M5: GT | N5: MI | O5: GT | P5: RCB
A6: SRH | B6: 19.35 | C6: 2630 | D6: 87 | E6: 105.2 | F6: 3.48 | G6: 108.68 | H6: 140.41344 | I6: 2 | J6: 5 | K6: 2717 | L6: 101.72 | M6: GT | N6: MI | O6: GT | P6: RCB
A7: LSG | B7: 17.4 | C7: 2134 | D7: 54 | E7: 85.36 | F7: 2.16 | G7: 87.52 | H7: 125.74713 | I7: 3 | J7: 6 | K7: 2188 | L7: 83.2 | M7: GT | N7: MI | O7: GT | P7: RCB
A8: DC | B8: 20.2 | C8: 1721 | D8: 62 | E8: 68.84 | F8: 2.48 | G8: 71.32 | H8: 88.267327 | I8: 8 | J8: 7 | K8: 1783 | L8: 66.36 | M8: GT | N8: MI | O8: GT | P8: RCB
A9: RCB | B9: 17.75 | C9: 1474 | D9: 55 | E9: 58.96 | F9: 2.2 | G9: 61.16 | H9: 86.140845 | I9: 10 | J9: 8 | K9: 1529 | L9: 56.76 | M9: GT | N9: MI | O9: GT | P9: RCB
A10: CSK | B10: 39.95 | C10: 1754 | D10: 54 | E10: 70.16 | F10: 2.16 | G10: 72.32 | H10: 45.256571 | I10: 7 | J10: 9 | K10: 1808 | L10: 68 | M10: GT | N10: MI | O10: GT | P10: RCB
A11: KKR | B11: 37 | C11: 1604 | D11: 56 | E11: 64.16 | F11: 2.24 | G11: 66.4 | H11: 44.864865 | I11: 9 | J11: 10 | K11: 1660 | L11: 61.92 | M11: GT | N11: MI | O11: GT | P11: RCB
L13: Row Labels | M13: Sum of Squad Efficiency
B14: Row Labels | C14: Sum of Total Squad Cost | E14: Row Labels | F14: Sum of Team Strength Score | H14: Row Labels | I14: Sum of Squad Efficiency | L14: CSK | M14: 45.256571
B15: CSK | C15: 39.95 | E15: CSK | F15: 72.32 | H15: CSK | I15: 45.256571 | L15: DC | M15: 88.267327
B16: DC | C16: 20.2 | E16: DC | F16: 71.32 | H16: DC | I16: 88.267327 | L16: GT | M16: 292.68041
B17: GT | C17: 9.7 | E17: GT | F17: 113.56 | H17: GT | I17: 292.68041 | L17: KKR | M17: 44.864865
B18: KKR | C18: 37 | E18: KKR | F18: 66.4 | H18: KKR | I18: 44.864865 | L18: LSG | M18: 125.74713
B19: LSG | C19: 17.4 | E19: LSG | F19: 87.52 | H19: LSG | I19: 125.74713 | L19: MI | M19: 785.09091
B20: MI | C20: 2.75 | E20: MI | F20: 86.36 | H20: MI | I20: 785.09091 | L20: PBKS | M20: 231.125
B21: PBKS | C21: 8 | E21: PBKS | F21: 73.96 | H21: PBKS | I21: 231.125 | L21: RCB | M21: 86.140845
B22: RCB | C22: 17.75 | E22: RCB | F22: 61.16 | H22: RCB | I22: 86.140845 | L22: RR | M22: 165.80392
B23: RR | C23: 12.75 | E23: RR | F23: 84.56 | H23: RR | I23: 165.80392 | L23: SRH | M23: 140.41344
B24: SRH | C24: 19.35 | E24: SRH | F24: 108.68 | H24: SRH | I24: 140.41344 | L24: Grand Total | M24: 2005.3904
B25: Grand Total | C25: 184.85 | E25: Grand Total | F25: 825.84 | H25: Grand Total | I25: 2005.3904

Sheet Player_Master_Clean
A1: Player | B1: Team | C1: Acquisition | D1: Role | E1: Price | F1: key | G1: Uncapped Player Value
A2: Ruturaj Gaikwad | B2: CSK | C2: Retained | D2: Anchor | E2: 0 | F2: Ruturaj Gaikwad_CSK
A3: MS Dhoni | B3: CSK | C3: Retained | D3: Wicketkeeper | E3: 0 | F3: MS Dhoni_CSK | H3: Row Labels | I3: Sum of Price
A4: Dewald Brevis | B4: CSK | C4: Retained | D4: Anchor | E4: 0 | F4: Dewald Brevis_CSK | H4: All-Rounder | I4: 98.6
A5: Akash Madhwal | B5: CSK | C5: Replacement | D5: Pacer | E5: 0.3 | F5: Akash Madhwal_CSK | G5: 0 | H5: Anchor | I5: 21
A6: Urvil Patel | B6: CSK | C6: Retained | D6: Wicketkeeper | E6: 0 | F6: Urvil Patel_CSK | H6: Pacer | I6: 30.6
A7: Anshul Kamboj | B7: CSK | C7: Retained | D7: All-Rounder | E7: 0 | F7: Anshul Kamboj_CSK | H7: Spinner | I7: 8.8
A8: Akeal Hosein | B8: CSK | C8: Auction | D8: Pacer | E8: 2 | F8: Akeal Hosein_CSK | G8: 0 | H8: Wicketkeeper | I8: 25.85
A9: Aman Khan | B9: CSK | C9: Auction | D9: All-Rounder | E9: 0.4 | F9: Aman Khan_CSK | G9: 0 | H9: (blank)
A10: Shivam Dube | B10: CSK | C10: Retained | D10: All-Rounder | E10: 0 | F10: Shivam Dube_CSK | H10: Grand Total | I10: 184.85
A11: Aman Rao | B11: RR | C11: Auction | D11: Anchor | E11: 0.3 | F11: Aman Rao_RR | G11: 7.21
A12: Noor Ahmad | B12: CSK | C12: Retained | D12: Spinner | E12: 0 | F12: Noor Ahmad_CSK
A13: Mukesh Choudhary | B13: CSK | C13: Retained | D13: Pacer | E13: 0 | F13: Mukesh Choudhary_CSK
A14: Amit Kumar | B14: SRH | C14: Auction | D14: Pacer | E14: 0.3 | F14: Amit Kumar_SRH | G14: 0
A15: Shreyas Gopal | B15: CSK | C15: Retained | D15: Spinner | E15: 0 | F15: Shreyas Gopal_CSK
A16: Gurjapneet Singh | B16: CSK | C16: Retained | D16: Pacer | E16: 0 | F16: Gurjapneet Singh_CSK
A17: Sanju Samson | B17: CSK | C17: Trade | D17: Wicketkeeper | E17: 0 | F17: Sanju Samson_CSK
A18: Anrich Nortje | B18: LSG | C18: Auction | D18: Pacer | E18: 2 | F18: Anrich Nortje_LSG | G18: 4.0718542
A19: Prashant Veer | B19: CSK | C19: Auction | D19: All-Rounder | E19: 14.2 | F19: Prashant Veer_CSK
A20: Kartik Sharma | B20: CSK | C20: Auction | D20: Wicketkeeper | E20: 14.2 | F20: Kartik Sharma_CSK
A21: Ashok Sharma | B21: GT | C21: Auction | D21: Pacer | E21: 0.9 | F21: Ashok Sharma_GT | G21: 8.262697
A22: Blessing Muzarabani | B22: KKR | C22: Replacement | D22: Pacer | E22: 0 | F22: Blessing Muzarabani_KKR | G22: 0
A23: Brijesh Sharma | B23: RR | C23: Auction | D23: Spinner | E23: 0.3 | F23: Brijesh Sharma_RR | G23: 92.974836
A24: Connor Esterhuizen | B24: GT | C24: Replacement | D24: Wicketkeeper | E24: 0.75 | F24: Connor Esterhuizen_GT | G24: -21.435216
A25: Daksh Kamra | B25: KKR | C25: Auction | D25: All-Rounder | E25: 0.3 | F25: Daksh Kamra_KKR | G25: 0
A26: Danish Malewar | B26: MI | C26: Auction | D26: Anchor | E26: 0.3 | F26: Danish Malewar_MI | G26: 32.08
A27: KL Rahul | B27: DC | C27: Retained | D27: Wicketkeeper | E27: 0 | F27: KL Rahul_DC
A28: Karun Nair | B28: DC | C28: Retained | D28: Anchor | E28: 0 | F28: Karun Nair_DC
A29: Abishek Porel | B29: DC | C29: Retained | D29: Wicketkeeper | E29: 0 | F29: Abishek Porel_DC
A30: Tristan Stubbs | B30: DC | C30: Retained | D30: Anchor | E30: 0 | F30: Tristan Stubbs_DC
A31: Axar Patel | B31: DC | C31: Retained | D31: All-Rounder | E31: 0 | F31: Axar Patel_DC
A32: Sameer Rizvi | B32: DC | C32: Retained | D32: Anchor | E32: 0 | F32: Sameer Rizvi_DC
A33: Ashutosh Sharma | B33: DC | C33: Retained | D33: Anchor | E33: 0 | F33: Ashutosh Sharma_DC
A34: Vipraj Nigam | B34: DC | C34: Retained | D34: All-Rounder | E34: 0 | F34: Vipraj Nigam_DC
A35: Ajay Mandal | B35: DC | C35: Retained | D35: All-Rounder | E35: 0 | F35: Ajay Mandal_DC
A36: Tripurana Vijay | B36: DC | C36: Retained | D36: All-Rounder | E36: 0 | F36: Tripurana Vijay_DC
A37: Madhav Tiwari | B37: DC | C37: Retained | D37: All-Rounder | E37: 0 | F37: Madhav Tiwari_DC
A38: Mitchell Starc | B38: DC | C38: Retained | D38: Pacer | E38: 0 | F38: Mitchell Starc_DC
... A44: Auqib Nabi | B44: DC | C44: Auction | D44: All-Rounder | E44: 8.4 | F44: Auqib Nabi_DC
A45: Dasun Shanaka | B45: RR | C45: Replacement | D45: All-Rounder | E45: 0 | F45: Dasun Shanaka_RR | G45: 3.5883363
A46: David Miller | B46: DC | C46: Auction | D46: Anchor | E46: 2 | F46: David Miller_DC | G46: 0
A47: Pathum Nissanka | B47: DC | C47: Auction | D47: Anchor | E47: 4 | F47: Pathum Nissanka_DC
A48: Dian Forrester | B48: CSK | C48: Replacement | D48: All-Rounder | E48: 0.75 | F48: Dian Forrester_CSK | G48: 0
A49: Dilshan Madushanka | B49: SRH | C49: Replacement | D49: Pacer | E49: 0.75 | F49: Dilshan Madushanka_SRH | G49: 0
A50: Emanjot Chahal | B50: RR | C50: Replacement | D50: All-Rounder | E50: 0.3 | F50: Emanjot Chahal_RR | G50: 306.91409
A51: Finn Allen | B51: KKR | C51: Auction | D51: Wicketkeeper | E51: 2 | F51: Finn Allen_KKR | G51: 0
A52: Shubman Gill | B52: GT | C52: Retained | D52: Anchor | E52: 0 | F52: Shubman Gill_GT
A53: B Sai Sudharsan | B53: GT | C53: Retained | D53: Anchor | E53: 0 | F53: B Sai Sudharsan_GT
A54: Kumar Kushagra | B54: GT | C54: Retained | D54: Wicketkeeper | E54: 0 | F54: Kumar Kushagra_GT
A55: Anuj Rawat | B55: GT | C55: Retained | D55: Wicketkeeper | E55: 0 | F55: Anuj Rawat_GT
A56: Jos Buttler | B56: GT | C56: Retained | D56: Wicketkeeper | E56: 0 | F56: Jos Buttler_GT
A57: Nishant Sindhu | B57: GT | C57: Retained | D57: All-Rounder | E57: 0 | F57: Nishant Sindhu_GT
A58: Glenn Phillips | B58: GT | C58: Retained | D58: All-Rounder | E58: 0 | F58: Glenn Phillips_GT
A59: Washington Sundar | B59: GT | C59: Retained | D59: All-Rounder | E59: 0 | F59: Washington Sundar_GT
A60: Arshad Khan | B60: GT | C60: Retained | D60: Pacer | E60: 0 | F60: Arshad Khan_GT
A61: M Shahrukh Khan | B61: GT | C61: Retained | D61: Anchor | E61: 0 | F61: M Shahrukh Khan_GT
A62: Rahul Tewatia | B62: GT | C62: Retained | D62: All-Rounder | E62: 0 | F62: Rahul Tewatia_GT
A63: Kagiso Rabada | B63: GT | C63: Retained | D63: Pacer | E63: 0 | F63: Kagiso Rabada_GT
... A71: Jayant Yadav | B71: GT | C71: Retained | D71: Spinner | E71: 0 | F71: Jayant Yadav_GT
A72: George Linde | B72: LSG | C72: Replacement | D72: All-Rounder | E72: 1 | F72: George Linde_LSG | G72: -44.66
A73: Jason Holder | B73: GT | C73: Auction | D73: All-Rounder | E73: 7 | F73: Jason Holder_GT
A74: Gerald Coetzee | B74: SRH | C74: Replacement | D74: Pacer | E74: 2 | F74: Gerald Coetzee_SRH | G74: 5.2719372
A75: Jacob Duffy | B75: RCB | C75: Auction | D75: Pacer | E75: 2 | F75: Jacob Duffy_RCB | G75: 0
A76: Jordan Cox | B76: RCB | C76: Auction | D76: Anchor | E76: 0.75 | F76: Jordan Cox_RCB | G76: 0
A77: Ajinkya Rahane | B77: KKR | C77: Retained | D77: Anchor | E77: 0 | F77: Ajinkya Rahane_KKR
A78: Rinku Singh | B78: KKR | C78: Retained | D78: Anchor | E78: 0 | F78: Rinku Singh_KKR
A79: Angkrish Raghuvanshi | B79: KKR | C79: Retained | D79: Anchor | E79: 0 | F79: Angkrish Raghuvanshi_KKR
A80: Manish Pandey | B80: KKR | C80: Retained | D80: Anchor | E80: 0 | F80: Manish Pandey_KKR
A81: Rovman Powell | B81: KKR | C81: Retained | D81: All-Rounder | E81: 0 | F81: Rovman Powell_KKR
A82: Anukul Roy | B82: KKR | C82: Retained | D82: All-Rounder | E82: 0 | F82: Anukul Roy_KKR
A83: Ramandeep Singh | B83: KKR | C83: Retained | D83: Anchor | E83: 0 | F83: Ramandeep Singh_KKR
A84: Vaibhav Arora | B84: KKR | C84: Retained | D84: Pacer | E84: 0 | F84: Vaibhav Arora_KKR
A85: Sunil Narine | B85: KKR | C85: Retained | D85: All-Rounder | E85: 0 | F85: Sunil Narine_KKR
A86: Varun Chakravarthy | B86: KKR | C86: Retained | D86: Spinner | E86: 0 | F86: Varun Chakravarthy_KKR
A87: Kanishk Chouhan | B87: RCB | C87: Auction | D87: All-Rounder | E87: 0.3 | F87: Kanishk Chouhan_RCB | G87: 10.03
A88: Umran Malik | B88: KKR | C88: Retained | D88: Pacer | E88: 0 | F88: Umran Malik_KKR
A89: Cameron Green | B89: KKR | C89: Auction | D89: All-Rounder | E89: 25.2 | F89: Cameron Green_KKR
A90: Kartik Tyagi | B90: KKR | C90: Auction | D90: Pacer | E90: 0.3 | F90: Kartik Tyagi_KKR | G90: 0
A91: Keshav Maharaj | B91: MI | C91: Replacement | D91: Pacer | E91: 0.75 | F91: Keshav Maharaj_MI | G91: 5.0671918
A92: Tejasvi Dahiya | B92: KKR | C92: Auction | D92: Wicketkeeper | E92: 3 | F92: Tejasvi Dahiya_KKR
A93: Krains Fuletra | B93: SRH | C93: Auction | D93: Pacer | E93: 0.3 | F93: Krains Fuletra_SRH | G93: 60.82
A94: Krish Bhagat | B94: MI | C94: Replacement | D94: Pacer | E94: 0.3 | F94: Krish Bhagat_MI | G94: 0
A95: Kuldeep Sen | B95: RR | C95: Auction | D95: Pacer | E95: 0.75 | F95: Kuldeep Sen_RR | G95: 0
A96: Kuldip Yadav | B96: CSK | C96: Replacement | D96: Pacer | E96: 0.3 | F96: Kuldip Yadav_CSK | G96: 0
A97: Kulwant Khejroliya | B97: GT | C97: Replacement | D97: Pacer | E97: 0.3 | F97: Kulwant Khejroliya_GT | G97: 5.5778321
A98: Kyle Jamieson | B98: DC | C98: Auction | D98: Pacer | E98: 2 | F98: Kyle Jamieson_DC | G98: 4.611029
A99: Luke Wood | B99: GT | C99: Auction | D99: Pacer | E99: 0.75 | F99: Luke Wood_GT | G99: 0
A100: Lungi Ngidi | B100: DC | C100: Auction | D100: Pacer | E100: 2 | F100: Lungi Ngidi_DC | G100: 6.5786436
A101: Luvnith Sisodia | B101: KKR | C101: Replacement | D101: Wicketkeeper | E101: 0.3 | F101: Luvnith Sisodia_KKR | G101: -54.001703
A102: Rishabh Pant | B102: LSG | C102: Retained | D102: Wicketkeeper | E102: 0 | F102: Rishabh Pant_LSG
A103: Ayush Badoni | B103: LSG | C103: Retained | D103: All-Rounder | E103: 0 | F103: Ayush Badoni_LSG
A104: Abdul Samad | B104: LSG | C104: Retained | D104: Anchor | E104: 0 | F104: Abdul Samad_LSG
A105: Aiden Markram | B105: LSG | C105: Retained | D105: Anchor | E105: 0 | F105: Aiden Markram_LSG
A106: Himmat Singh | B106: LSG | C106: Retained | D106: Anchor | E106: 0 | F106: Himmat Singh_LSG
A107: Matthew Breetzke | B107: LSG | C107: Retained | D107: Anchor | E107: 0 | F107: Matthew Breetzke_LSG
A108: Nicholas Pooran | B108: LSG | C108: Retained | D108: Wicketkeeper | E108: 0 | F108: Nicholas Pooran_LSG
A109: Mitchell Marsh | B109: LSG | C109: Retained | D109: Anchor | E109: 0 | F109: Mitchell Marsh_LSG
A110: Shahbaz Ahmed | B110: LSG | C110: Retained | D110: All-Rounder | E110: 0 | F110: Shahbaz Ahmed_LSG
A111: Arshin Kulkarni | B111: LSG | C111: Retained | D111: All-Rounder | E111: 0 | F111: Arshin Kulkarni_LSG
A112: Mayank Yadav | B112: LSG | C112: Retained | D112: Pacer | E112: 0 | F112: Mayank Yadav_LSG
...

Sheet Batting_Clean
A1: Player | B1: Team | C1: Matches | D1: Runs | E1: Balls | F1: Average | G1: Strike Rate | H1: 100s | I1: 50s | J1: 4s | K1: 6s | L1: Not Outs | M1: Key
A2: Vaibhav Suryavanshi | B2: RR | C2: 16 | D2: 776 | E2: 327 | F2: 48.5 | G2: 237.3 | H2: 1 | I2: 5 | J2: 63 | K2: 72 | L2: 0 | M2: Vaibhav_Suryavanshi_RR
A3: Shubman Gill | B3: GT | C3: 16 | D3: 732 | E3: 449 | F3: 45.75 | G3: 163.02 | H3: 1 | I3: 6 | J3: 74 | K3: 33 | L3: 0 | M3: Shubman_Gill_GT
A4: B Sai Sudharsan | B4: GT | C4: 17 | D4: 722 | E4: 457 | F4: 45.12 | G4: 157.98 | H4: 1 | I4: 8 | J4: 75 | K4: 30 | L4: 1 | M4: B_Sai_Sudharsan_GT
A5: Virat Kohli | B5: RCB | C5: 16 | D5: 675 | E5: 407 | F5: 56.25 | G5: 165.84 | H5: 1 | I5: 5 | J5: 73 | K5: 25 | L5: 4 | M5: Virat_Kohli_RCB
A6: Heinrich Klaasen | B6: SRH | C6: 15 | D6: 624 | E6: 390 | F6: 48 | G6: 160 | H6: 0 | I6: 6 | J6: 48 | K6: 31 | L6: 2 | M6: Heinrich_Klaasen_SRH
A7: Ishan Kishan | B7: SRH | C7: 15 | D7: 602 | E7: 330 | F7: 40.13 | G7: 182.42 | H7: 0 | I7: 6 | J7: 60 | K7: 32 | L7: 0 | M7: Ishan_Kishan_SRH
A8: KL Rahul | B8: DC | C8: 14 | D8: 593 | E8: 340 | F8: 45.61 | G8: 174.41 | H8: 1 | I8: 5 | J8: 56 | K8: 31 | L8: 1 | M8: KL_Rahul_DC
A9: Abhishek Sharma | B9: SRH | C9: 15 | D9: 563 | E9: 275 | F9: 40.21 | G9: 204.72 | H9: 1 | I9: 4 | J9: 50 | K9: 43 | L9: 1 | M9: Abhishek_Sharma_SRH
A10: Mitchell Marsh | B10: LSG | C10: 13 | D10: 563 | E10: 345 | F10: 43.3 | G10: 163.18 | H10: 1 | I10: 3 | J10: 51 | K10: 36 | L10: 0 | M10: Mitchell_Marsh_LSG
A11: Jos Buttler | B11: GT | C11: 17 | D11: 526 | E11: 345 | F11: 37.57 | G11: 152.46 | H11: 0 | I11: 4 | J11: 51 | K11: 26 | L11: 3 | M11: Jos_Buttler_GT
A12: Dhruv Jurel | B12: RCB | C12: 16 | D12: 515 | E12: 333 | F12: 36.78 | G12: 154.65 | H12: 0 | I12: 6 | J12: 47 | K12: 24 | L12: 2 | M12: Dhruv_Jurel_RCB
A13: Prabhsimran Singh | B13: PBKS | C13: 14 | D13: 510 | E13: 302 | F13: 42.5 | G13: 168.87 | H13: 0 | I13: 6 | J13: 55 | K13: 23 | L13: 1 | M13: Prabhsimran_Singh_PBKS
... A91: Anshul Kamboj | B91: CSK | C91: 14 | D91: 58 | E91: 38 | F91: 29 | G91: 152.63 | H91: 0 | I91: 0 | J91: 3 | K91: 4 | L91: 2 | M91: Anshul_Kamboj_CSK
A92: Shahbaz Ahmed | B92: LSG | C92: 5 | D92: 58 | E92: 41 | F92: - | G92: 141.46 | H92: 0 | I92: 0 | J92: 4 | K92: 3 | L92: 2 | M92: Shahbaz_Ahmed_LSG
A93: Shivang Kumar | B93: SRH | C93: 13 | D93: 53 | E93: 46 | F93: 8.83 | G93: 115.21 | H93: 0 | I93: 0 | J93: 6 | K93: 1 | L93: 0 | M93: Shivang_Kumar_SRH
A94: Azmatullah Omarzai | B94: PBKS | C94: 3 | D94: 52 | E94: 27 | F94: 26 | G94: 192.59 | H94: 0 | I94: 0 | J94: 3 | K94: 5 | L94: 0 | M94: Azmatullah_Omarzai_PBKS
A95: Arshin Kulkarni | B95: PBKS | C95: 14 | D95: 52 | E95: 39 | F95: 13 | G95: 133.33 | H95: 0 | I95: 0 | J95: 3 | K95: 2 | L95: 3 | M95: Arshin_Kulkarni_PBKS
A96: Marco Jansen | B96: LSG | C96: 13 | D96: 51 | E96: 45 | F96: 12.75 | G96: 113.33 | H96: 0 | I96: 0 | J96: 1 | K96: 3 | L96: 1 | M96: Marco_Jansen_LSG
A97: Corbin Bosch | B97: PBKS | C97: 6 | D97: 50 | E97: 31 | F97: 50 | G97: 161.29 | H97: 0 | I97: 0 | J97: 5 | K97: 2 | L97: 3 | M97: Corbin_Bosch_PBKS
A98: Rashid Khan | B98: GT | C98: 17 | D98: 50 | E98: 41 | F98: 12.5 | G98: 121.95 | H98: 0 | I98: 0 | J98: 4 | K98: 2 | L98: 2 | M98: Rashid_Khan_GT
A99: Kagiso Rabada | B99: GT | C99: 17 | D99: 47 | E99: 38 | F99: 23.5 | G99: 123.68 | H99: 0 | I99: 0 | J99: 5 | K99: 2 | L99: 2 | M99: Kagiso_Rabada_GT
A100: Sahil Parakh | B100: PBKS | C100: 4 | D100: 46 | E100: 33 | F100: 11.5 | G100: 139.39 | H100: 0 | I100: 0 | J100: 5 | K100: 2 | L100: 0 | M100: Sahil_Parakh_PBKS
A101: M Shahrukh Khan | B101: GT | C101: 9 | D101: 43 | E101: 33 | F101: 10.75 | G101: 130.3 | H101: 0 | I101: 0 | J101: 3 | K101: 2 | L101: 1 | M101: M_Shahrukh_Khan_GT
A102: Sunil Narine | B102: KKR | C102: 13 | D102: 40 | E102: 32 | F102: 13.33 | G102: 125 | H102: 0 | I102: 0 | J102: 2 | K102: 4 | L102: 1 | M102: Sunil_Narine_KKR
A103: Bhuvneshwar Kumar | B103: SRH | C103: 16 | D103: 34 | E103: 26 | F103: - | G103: 130.76 | H103: 0 | I103: 0 | J103: 3 | K103: 1 | L103: 4 | M103: Bhuvneshwar_Kumar_SRH
A104: George Linde | B104: PBKS | C104: 3 | D104: 31 | E104: 21 | F104: 10.33 | G104: 147.61 | H104: 0 | I104: 0 | J104: 6 | K104: 0 | L104: 0 | M104: George_Linde_PBKS
A105: Mohammed Shami | B105: SRH | C105: 13 | D105: 31 | E105: 22 | F105: 6.2 | G105: 140.9 | H105: 0 | I105: 0 | J105: 2 | K105: 3 | L105: 2 | M105: Mohammed_Shami_SRH
A106: Pat Cummins | B106: SRH | C106: 8 | D106: 30 | E106: 19 | F106: 10 | G106: 157.89 | H106: 0 | I106: 0 | J106: 1 | K106: 3 | L106: 0 | M106: Pat_Cummins_SRH
A107: Xavier Bartlett | B107: DC | C107: 9 | D107: 29 | E107: 13 | F107: 29 | G107: 223.07 | H107: 0 | I107: 0 | J107: 2 | K107: 2 | L107: 2 | M107: Xavier_Bartlett_DC
A108: Akshat Raghuwanshi | B108: LSG | C108: 3 | D108: 29 | E108: 25 | F108: 14.5 | G108: 116 | H108: 0 | I108: 0 | J108: 1 | K108: 1 | L108: 0 | M108: Akshat_Raghuwanshi_LSG
A109: Tushar Deshpande | B109: RR | C109: 7 | D109: 26 | E109: 14 | F109: 13 | G109: 185.71 | H109: 0 | I109: 0 | J109: 0 | K109: 3 | L109: 0 | M109: Tushar_Deshpande_RR
A110: Mitchell Santner | B110: CSK | C110: 4 | D110: 26 | E110: 19 | F110: - | G110: 136.84 | H110: 0 | I110: 0 | J110: 3 | K110: 0 | L110: 2 | M110: Mitchell_Santner_CSK
A111: Deepak Chahar | B111: CSK | C111: 8 | D111: 25 | E111: 19 | F111: 12.5 | G111: 131.57 | H111: 0 | I111: 0 | J111: 3 | K111: 1 | L111: 2 | M111: Deepak_Chahar_CSK
A112: Shardul Thakur | B112: MI | C112: 9 | D112: 24 | E112: 30 | F112: 12 | G112: 80 | H112: 0 | I112: 0 | J112: 2 | K112: 0 | L112: 1 | M112: Shardul_Thakur_MI
A113: Arshad Khan | B113: GT | C113: 8 | D113: 23 | E113: 11 | F113: 23 | G113: 209.09 | H113: 0 | I113: 0 | J113: 1 | K113: 2 | L113: 1 | M113: Arshad_Khan_GT
A114: Tim Seifert | B114: DC | C114: 3 | D114: 19 | E114: 18 | F114: 6.33 | G114: 105.55 | H114: 0 | I114: 0 | J114: 2 | K114: 1 | L114: 0 | M114: Tim_Seifert_DC
A115: Ravichandran Smaran | B115: SRH | C115: 6 | D115: 19 | E115: 25 | F115: 6.33 | G115: 76 | H115: 0 | I115: 0 | J115: 3 | K115: 0 | L115: 1 | M115: Ravichandran_Smaran_SRH
A116: Madhav Tiwari | B116: PBKS | C116: 3 | D116: 18 | E116: 8 | F116: - | G116: 225 | H116: 0 | I116: 0 | J116: 2 | K116: 1 | L116: 1 | M116: Madhav_Tiwari_PBKS
A117: Kumar Kushagra | B117: GT | C117: 1 | D117: 18 | E117: 14 | F117: 18 | G117: 128.57 | H117: 0 | I117: 0 | J117: 3 | K117: 0 | L117: 0 | M117: Kumar_Kushagra_GT
A118: Karun Nair | B118: DC | C118: 2 | D118: 18 | E118: 18 | F118: 9 | G118: 100 | H118: 0 | I118: 0 | J118: 3 | K118: 0 | L118: 0 | M118: Karun_Nair_DC
A119: Arjun Kulkarni | B119: PBKS | C119: 2 | D119: 17 | E119: 25 | F119: 8.5 | G119: 68 | H119: 0 | I119: 0 | J119: 1 | K119: 0 | L119: 0 | M119: Arjun_Kulkarni_PBKS
A120: Raj Bawa | B120: MI | C120: 3 | D120: 16 | E120: 14 | F120: 16 | G120: 114.28 | H120: 0 | I120: 0 | J120: 1 | K120: 0 | L120: 0 | M120: Raj_Bawa_MI
A121: Vishnu Vinod | B121: PBKS | C121: 1 | D121: 15 | E121: 8 | F121: - | G121: 187.5 | H121: 0 | I121: 0 | J121: 1 | K121: 1 | L121: 1 | M121: Vishnu_Vinod_PBKS
A122: Vipraj Nigam | B122: DC | C122: 5 | D122: 15 | E122: 10 | F122: 15 | G122: 150 | H122: 0 | I122: 0 | J122: 2 | K122: 0 | L122: 1 | M122: Vipraj_Nigam_DC
A123: Liam Livingstone | B123: SRH | C123: 2 | D123: 15 | E123: 25 | F123: 7.5 | G123: 60 | H123: 0 | I123: 0 | J123: 0 | K123: 1 | L123: 0 | M123: Liam_Livingstone_SRH
A124: Auqib Nabi | B124: PBKS | C124: 5 | D124: 14 | E124: 4 | F124: 14 | G124: 350 | H124: 0 | I124: 0 | J124: 2 | K124: 1 | L124: 1 | M124: Auqib_Nabi_PBKS
A125: Nandre Burger | B125: PBKS | C125: 13 | D125: 14 | E125: 9 | F125: 14 | G125: 155.55 | H125: 0 | I125: 0 | J125: 0 | K125: 1 | L125: 2 | M125: Nandre_Burger_PBKS
A126: Harpreet Dubey | B126: PBKS | C126: 8 | D126: 13 | E126: 9 | F126: 6.5 | G126: 144.44 | H126: 0 | I126: 0 | J126: 2 | K126: 0 | L126: 3 | M126: Harpreet_Dubey_PBKS
A127: Kyle Jamieson | B127: LSG | C127: 2 | D127: 12 | E127: 13 | F127: 12 | G127: 92.3 | H127: 0 | I127: 0 | J127: 1 | K127: 1 | L127: 0 | M127: Kyle_Jamieson_LSG
A128: Tejasvi Dahiya | B128: LSG | C128: 2 | D128: 12 | E128: 15 | F128: 6 | G128: 80 | H128: 0 | I128: 0 | J128: 2 | K128: 0 | L128: 0 | M128: Tejasvi_Dahiya_LSG
A129: Kartik Tyagi | B129: KKR | C129: 14 | D129: 11 | E129: 10 | F129: 3.66 | G129: 110 | H129: 0 | I129: 0 | J129: 1 | K129: 1 | L129: 0 | M129: Kartik_Tyagi_KKR
A130: Noor Ahmad | B130: CSK | C130: 14 | D130: 11 | E130: 23 | F130: 3.66 | G130: 47.82 | H130: 0 | I130: 0 | J130: 0 | K130: 1 | L130: 1 | M130: Noor_Ahmad_CSK
A131: Harshit Rana | B131: KKR | C131: 5 | D131: 10 | E131: 9 | F131: 3.33 | G131: 111.11 | H131: 0 | I131: 0 | J131: 2 | K131: 0 | L131: 0 | M131: Harshit_Rana_KKR
A132: Krish Bhagat | B132: MI | C132: 3 | D132: 10 | E132: 21 | F132: 10 | G132: 47.61 | H132: 0 | I132: 0 | J132: 0 | K132: 0 | L132: 1 | M132: Krish_Bhagat_MI
A133: Kuldeep Yadav | B133: DC | C133: 12 | D133: 9 | E133: 21 | F133: 3 | G133: 42.85 | H133: 0 | I133: 0 | J133: 0 | K133: 0 | L133: 1 | M133: Kuldeep_Yadav_DC
... A139: Robin Minz | B139: MI | C139: 2 | D139: 6 | E139: 4 | F139: 6 | G139: 150 | H139: 0 | I139: 0 | J139: 1 | K139: 0 | L139: 1 | M139: Robin_Minz_MI
A140: David Payne | B140: MI | C140: 2 | D140: 6 | E140: 5 | F140: - | G140: 120 | H140: 0 | I140: 0 | J140: 0 | K140: 0 | L140: 1 | M140: David_Payne_MI
A141: Avesh Khan | B141: LSG | C141: 7 | D141: 6 | E141: 6 | F141: 6 | G141: 100 | H141: 0 | I141: 0 | J141: 1 | K141: 0 | L141: 3 | M141: Avesh_Khan_LSG
A142: Prasidh Krishna | B142: GT | C142: 12 | D142: 6 | E142: 7 | F142: - | G142: 85.71 | H142: 0 | I142: 0 | J142: 1 | K142: 0 | L142: 1 | M142: Prasidh_Krishna_GT
A143: Harpreet Brar | B143: PBKS | C143: 2 | D143: 5 | E143: 3 | F143: - | G143: 166.66 | H143: 0 | I143: 0 | J143: 1 | K143: 0 | L143: 1 | M143: Harpreet_Brar_PBKS
A144: Akeal Hosein | B144: CSK | C144: 7 | D144: 5 | E144: 3 | F144: - | G144: 166.66 | H144: 0 | I144: 0 | J144: 0 | K144: 0 | L144: 3 | M144: Akeal_Hosein_CSK
A145: Mayank Yadav | B145: LSG | C145: 4 | D145: 5 | E145: 5 | F145: 5 | G145: 100 | H145: 0 | I145: 0 | J145: 1 | K145: 0 | L145: 0 | M145: Mayank_Yadav_LSG
A146: Arjun Tendulkar | B146: PBKS | C146: 1 | D146: 5 | E146: 5 | F146: - | G146: 100 | H146: 0 | I146: 0 | J146: 0 | K146: 0 | L146: 1 | M146: Arjun_Tendulkar_PBKS
A147: CV Varun | B147: PBKS | C147: 11 | D147: 5 | E147: 6 | F147: 2.5 | G147: 83.33 | H147: 0 | I147: 0 | J147: 1 | K147: 0 | L147: 0 | M147: CV_Varun_PBKS
A148: Sakib Hussain | B148: SRH | C148: 11 | D148: 5 | E148: 7 | F148: - | G148: 71.42 | H148: 0 | I148: 0 | J148: 1 | K148: 0 | L148: 1 | M148: Sakib_Hussain_SRH
A149: Mohammed Siraj | B149: GT | C149: 17 | D149: 5 | E149: 16 | F149: 2.5 | G149: 31.25 | H149: 0 | I149: 0 | J149: 1 | K149: 0 | L149: 0 | M149: Mohammed_Siraj_GT
A150: Ravi Singh | B150: PBKS | C150: 1 | D150: 4 | E150: 2 | F150: 4 | G150: 200 | H150: 0 | I150: 0 | J150: 1 | K150: 0 | L150: 0 | M150: Ravi_Singh_PBKS
A151: Shubham Dubey | B151: RR | C151: 4 | D151: 4 | E151: 2 | F151: - | G151: 200 | H151: 0 | I151: 0 | J151: 1 | K151: 0 | L151: 1 | M151: Shubham_Dubey_RR

Sheet Bowling_Clean
A1: Player | B1: Team | C1: Matches | D1: Overs | E1: Runs Conceded | F1: Wickets | G1: Economy | H1: Maidens | I1: Average | J1: Key
A2: Kagiso Rabada | B2: GT | C2: 17 | D2: 64.4 | E2: 626 | F2: 29 | G2: 9.68 | H2: 1 | I2: 21.58 | J2: Kagiso_Rabada_GT
A3: Bhuvneshwar Kumar | B3: SRH | C3: 16 | D3: 63 | E3: 501 | F3: 28 | G3: 7.95 | H3: 0 | I3: 17.89 | J3: Bhuvneshwar_Kumar_SRH
A4: Jofra Archer | B4: RR | C4: 16 | D4: 60 | E4: 559 | F4: 25 | G4: 9.31 | H4: 1 | I4: 22.36 | J4: Jofra_Archer_RR
A5: Rashid Khan | B5: GT | C5: 17 | D5: 56.5 | E5: 516 | F5: 21 | G5: 9.07 | H5: 0 | I5: 24.57 | J5: Rashid_Khan_GT
A6: Anshul Kamboj | B6: CSK | C6: 14 | D6: 50.2 | E6: 530 | F6: 21 | G6: 10.52 | H6: 0 | I6: 25.23 | J6: Anshul_Kamboj_CSK
A7: Eshan Malinga | B7: SRH | C7: 15 | D7: 54.2 | E7: 507 | F7: 20 | G7: 9.33 | H7: 0 | I7: 25.35 | J7: Eshan_Malinga_SRH
A8: Mohammed Siraj | B8: GT | C8: 17 | D8: 62 | E8: 562 | F8: 19 | G8: 9.06 | H8: 1 | I8: 29.57 | J8: Mohammed_Siraj_GT
A9: Rasikh Salam | B9: RCB | C9: 12 | D9: 42.5 | E9: 405 | F9: 19 | G9: 9.45 | H9: 1 | I9: 21.31 | J9: Rasikh_Salam_RCB
A10: Kartik Tyagi | B10: KKR | C10: 14 | D10: 51 | E10: 498 | F10: 18 | G10: 9.76 | H10: 0 | I10: 27.66 | J10: Kartik_Tyagi_KKR
A11: Jason Holder | B11: KKR | C11: 11 | D11: 38.2 | E11: 290 | F11: 17 | G11: 7.56 | H11: 0 | I11: 17.05 | J11: Jason_Holder_KKR
A12: Prince Yadav | B12: LSG | C12: 14 | D12: 52 | E12: 459 | F12: 16 | G12: 8.82 | H12: 0 | I12: 28.68 | J12: Prince_Yadav_LSG
A13: Prasidh Krishna | B13: GT | C13: 12 | D13: 39 | E13: 407 | F13: 16 | G13: 10.43 | H13: 0 | I13: 25.43 | J13: Prasidh_Krishna_GT
... A101: Ramandeep Singh | B101: KKR | C101: 8 | D101: 2.4 | E101: 31 | F101: 1 | G101: 11.62 | H101: 0 | I101: 31 | J101: Ramandeep_Singh_KKR

Sheet Captain_Clean
A1: Captain | B1: Current Team | C1: Matches | D1: Wins | E1: Losses | F1: Win % | G1: NRR | H1: Win/Loss Ratio | I1: Leadership Score
A2: Rajat Patidar | B2: Royal Challengers Bengaluru | C2: 14 | D2: 9 | E2: 5 | F2: 64.29 | G2: 0.783 | H2: 1.8 | I2: 64.285714
A3: Shubman Gill | B3: Gujarat Titans | C3: 14 | D3: 9 | E3: 5 | F3: 64.29 | G3: 0.695 | H3: 1.8 | I3: 64.285714
A4: Pat Cummins | B4: Sunrisers Hyderabad | C4: 14 | D4: 9 | E4: 5 | F4: 64.29 | G4: 0.524 | H4: 1.8 | I4: 64.285714
A5: Riyan Parag | B5: Rajasthan Royals | C5: 14 | D5: 8 | E5: 6 | F5: 57.14 | G5: 0.189 | H5: 1.33 | I5: 57.142857
A6: Shreyas Iyer | B6: Punjab Kings | C6: 14 | D6: 7 | E6: 6 | F6: 50 | G6: 0.309 | H6: 1.17 | I6: 50
A7: Axar Patel | B7: Delhi Capitals | C7: 14 | D7: 7 | E7: 7 | F7: 50 | G7: -0.651 | H7: 1 | I7: 50
A8: Ajinkya Rahane | B8: Kolkata Knight Riders | C8: 14 | D8: 6 | E8: 7 | F8: 42.86 | G8: -0.147 | H8: 0.86 | I8: 42.857143
A9: Ruturaj Gaikwad | B9: Chennai Super Kings | C9: 14 | D9: 6 | E9: 8 | F9: 42.86 | G9: -0.345 | H9: 0.75 | I9: 42.857143
A10: Hardik Pandya | B10: Mumbai Indians | C10: 14 | D10: 4 | E10: 10 | F10: 28.57 | G10: -0.584 | H10: 0.4 | I10: 28.571429
A11: Rishabh Pant | B11: Lucknow Super Giants | C11: 14 | D11: 4 | E11: 10 | F11: 28.57 | G11: -0.74 | H11: 0.4 | I11: 28.571429
B14: Row Labels | C14: Sum of Win %
B15: Ajinkya Rahane | C15: 42.86
B16: Axar Patel | C16: 50
B17: Hardik Pandya | C17: 28.57
B18: Pat Cummins | C18: 64.29
B19: Rajat Patidar | C19: 64.29
B20: Rishabh Pant | C20: 28.57
B21: Riyan Parag | C21: 57.14
B22: Ruturaj Gaikwad | C22: 42.86
B23: Shreyas Iyer | C23: 50
B24: Shubman Gill | C24: 64.29
B25: (blank)
B26: Grand Total | C26: 492.87

Sheet Coach_Clean
A1: Coach | B1: Team | C1: Matches | D1: Wins | E1: Losses | F1: Playoff Finish | G1: Purse Used by teams | H1: Coach Efficiency = Wins / Purse Used
A2: Andy Flower | B2: RCB | C2: =C4 -> 14 | D2: =VLOOKUP(B2,[1]Team_Clean!A:D,3,FALSE) -> 9 | E2: =VLOOKUP(B2,[1]Team_Clean!A:D,4,FALSE) -> 5 | F2: Winner | G2: =_xlfn.XLOOKUP(B2,Team_Analytics!A:A,Team_Analytics!B:B,0) -> 17.75 | H2: =(D2/C2)/G2 -> 0.036217304
A3: Stephen Fleming | B3: CSK | C3: =VLOOKUP(B3,[1]Team_Clean!A:D,2,FALSE) -> 14 | D3: =VLOOKUP(B3,[1]Team_Clean!A:D,3,FALSE) -> 6 | E3: =VLOOKUP(B3,[1]Team_Clean!A:D,4,FALSE) -> 8 | F3: Runner-up | G3: =_xlfn.XLOOKUP(B3,Team_Analytics!A:A,Team_Analytics!B:B,0) -> 39.95 | H3: =(D3/C3)/G3 -> 0.010727695
A4: Mahela Jayawardene | B4: MI | C4: =VLOOKUP(B4,[1]Team_Clean!A:D,2,FALSE) -> 14 | D4: =VLOOKUP(B4,[1]Team_Clean!A:D,3,FALSE) -> 4 | E4: =VLOOKUP(B4,[1]Team_Clean!A:D,4,FALSE) -> 10 | F4: Qualifier 2 | G4: =_xlfn.XLOOKUP(B4,Team_Analytics!A:A,Team_Analytics!B:B,0) -> 2.75 | H4: =(D4/C4)/G4 -> 0.1038961
A5: Abhishek Nayar | B5: KKR | C5: =VLOOKUP(B5,[1]Team_Clean!A:D,2,FALSE) -> 14 | D5: =VLOOKUP(B5,[1]Team_Clean!A:D,3,FALSE) -> 6 | E5: =VLOOKUP(B5,[1]Team_Clean!A:D,4,FALSE) -> 7 | F5: Eliminator | G5: =_xlfn.XLOOKUP(B5,Team_Analytics!A:A,Team_Analytics!B:B,0) -> 37 | H5: =(D5/C5)/G5 -> 0.011583012
A6: Ashish Nehra | B6: GT | C6: =VLOOKUP(B6,[1]Team_Clean!A:D,2,FALSE) -> 14 | D6: =VLOOKUP(B6,[1]Team_Clean!A:D,3,FALSE) -> 9 | E6: =VLOOKUP(B6,[1]Team_Clean!A:D,4,FALSE) -> 5 | F6: League Stage | G6: =_xlfn.XLOOKUP(B6,Team_Analytics!A:A,Team_Analytics!B:B,0) -> 9.7 | H6: =(D6/C6)/G6 -> 0.066273932
A7: Kumar Sangakkara | B7: RR | C7: =VLOOKUP(B7,[1]Team_Clean!A:D,2,FALSE) -> 14 | D7: =VLOOKUP(B7,[1]Team_Clean!A:D,3,FALSE) -> 8 | E7: =VLOOKUP(B7,[1]Team_Clean!A:D,4,FALSE) -> 6 | F7: League Stage | G7: =_xlfn.XLOOKUP(B7,Team_Analytics!A:A,Team_Analytics!B:B,0) -> 12.75 | H7: =(D7/C7)/G7 -> 0.044817927
A8: Ricky Ponting | B8: PBKS | C8: =VLOOKUP(B8,[1]Team_Clean!A:D,2,FALSE) -> 14 | D8: =VLOOKUP(B8,[1]Team_Clean!A:D,3,FALSE) -> 7 | E8: =VLOOKUP(B8,[1]Team_Clean!A:D,4,FALSE) -> 6 | F8: League Stage | G8: =_xlfn.XLOOKUP(B8,Team_Analytics!A:A,Team_Analytics!B:B,0) -> 8 | H8: =(D8/C8)/G8 -> 0.0625
A9: Justin Langer | B9: LSG | C9: =VLOOKUP(B9,[1]Team_Clean!A:D,2,FALSE) -> 14 | D9: =VLOOKUP(B9,[1]Team_Clean!A:D,3,FALSE) -> 4 | E9: =VLOOKUP(B9,[1]Team_Clean!A:D,4,FALSE) -> 10 | F9: League Stage | G9: =_xlfn.XLOOKUP(B9,Team_Analytics!A:A,Team_Analytics!B:B,0) -> 17.4 | H9: =(D9/C9)/G9 -> 0.016420361
A10: Hemang Badani | B10: DC | C10: =VLOOKUP(B10,[1]Team_Clean!A:D,2,FALSE) -> 14 | D10: =VLOOKUP(B10,[1]Team_Clean!A:D,3,FALSE) -> 7 | E10: =VLOOKUP(B10,[1]Team_Clean!A:D,4,FALSE) -> 7 | F10: League Stage | G10: =_xlfn.XLOOKUP(B10,Team_Analytics!A:A,Team_Analytics!B:B,0) -> 20.2 | H10: =(D10/C10)/G10 -> 0.024752475
A11: Daniel Vettori | B11: SRH | C11: =VLOOKUP(B11,[1]Team_Clean!A:D,2,FALSE) -> 14 | D11: =VLOOKUP(B11,[1]Team_Clean!A:D,3,FALSE) -> 9 | E11: =VLOOKUP(B11,[1]Team_Clean!A:D,4,FALSE) -> 5 | F11: League Stage | G11: =_xlfn.XLOOKUP(B11,Team_Analytics!A:A,Team_Analytics!B:B,0) -> 19.35 | H11: =(D11/C11)/G11 -> 0.033222591
B14: Row Labels | C14: Sum of Coach Efficiency = Wins / Purse Used
B15: Ashish Nehra | C15: 0.066273932
B16: Mahela Jayawardene | C16: 0.1038961 | E16: Coach | F16: Purse used by teams | G16: Wins
B17: Ricky Ponting | C17: 0.0625 | E17: Andy Flower | F17: 17.75 | G17: 9
B18: Grand Total | C18: 0.23267004 | E18: Stephen Fleming | F18: 39.95 | G18: 6
E19: Mahela Jayawardene | F19: 2.75 | G19: 4
E20: Abhishek Nayar | F20: 37 | G20: 6
E21: Ashish Nehra | F21: 9.7 | G21: 9
E22: Kumar Sangakkara | F22: 12.75 | G22: 8
E23: Ricky Ponting | F23: 8 | G23: 7
E24: Justin Langer | F24: 17.4 | G24: 4
E25: Hemang Badani | F25: 20.2 | G25: 7
E26: Daniel Vettori | F26: 19.35 | G26: 9

Sheet Team_Clean
A1: Team | B1: Matches | C1: Wins | D1: Losses | E1: Points | F1: NRR
A2: RCB | B2: 14 | C2: 9 | D2: 5 | E2: 18 | F2: 0.783
A3: GT | B3: 14 | C3: 9 | D3: 5 | E3: 18 | F3: 0.695
A4: SRH | B4: 14 | C4: 9 | D4: 5 | E4: 18 | F4: 0.524
A5: RR | B5: 14 | C5: 8 | D5: 6 | E5: 16 | F5: 0.189
A6: PBKS | B6: 14 | C6: 7 | D6: 6 | E6: 15 | F6: 0.309
A7: DC | B7: 14 | C7: 7 | D7: 7 | E7: 14 | F7: -0.651
A8: KKR | B8: 14 | C8: 6 | D8: 7 | E8: 13 | F8: -0.147
A9: CSK | B9: 14 | C9: 6 | D9: 8 | E9: 12 | F9: -0.345
A10: MI | B10: 14 | C10: 4 | D10: 10 | E10: 8 | F10: -0.584
A11: LSG | B11: 14 | C11: 4 | D11: 10 | E11: 8 | F11: -0.74
